Workbook

Sheet Read Me
A1: Passage rune workbook
A2: Made 2026-10-22 from design/14-rune-sets-v0.md and design/affinities/water.md. Nothing here is in the game yet.
A4: Sheets
A5: Affinities: every affinity, its rule, status and rune count, with a link to its sheet. The proposed seven are listed below it.
A6: Base Runes: every base rune in one list, with its character. This is where a rune's name and character live.
A7: Universal Runes: the 28 universal pairs anyone can add to a skill, with characters.
A8: One sheet per affinity: each rune as a skill, as a means, what it releases with its opposite, and the skills built on it.
A10: Colours
A11: Blue text: type here.
A12: Green text: pulled from another sheet. Change it at its source (names and characters on Base Runes).
A13: Black text: worked out on this sheet (opposites, counts).
A14: Yellow fill: not written yet (water is the only affinity with its means and together columns filled).
... A34: 2026-10-22: the base runes were replaced by the revised set (design/runes-data/revised-rune-set.md), approved by Brent. IDs, characters and opposite pairs are unchanged; names, meanings, roles, draws and the skills on each rune changed. Water's means and together columns were kept only for the runes that survived.

Sheet Affinities
A1: Affinity | B1: Rule | C1: Status | D1: Source | E1: Base runes | F1: Pairs | G1: Sheet | I1: Heat | J1: Value | K1: Substance | L1: Value | M1: Vitality | N1: Value | O1: Light | P1: Value | Q1: Mind/Matter | R1: Value
A2: Water | B2: Moves bodies (shove and Crush); works the water that is already there (wetness) | C2: Deep dive v0 | D2: existing (design/05); MODEL: wetness, from C | E2: =COUNTIF('Base Runes'!$B:$B,$A2) -> 16 | F2: =E2/2 -> 8 | G2: Water | J2: ='Slider Links'!G2 -> -0.3 | L2: ='Slider Links'!H2 -> -0.6 | N2: ='Slider Links'!I2 -> 0.5 | P2: ='Slider Links'!J2 -> 0 | R2: ='Slider Links'!K2 -> 0.6
A3: Fire | B3: Runs on its own heat | C3: First pass | E3: =COUNTIF('Base Runes'!$B:$B,$A3) -> 10 | F3: =E3/2 -> 5 | G3: Fire | J3: ='Slider Links'!G3 -> 1 | L3: ='Slider Links'!H3 -> -0.3 | N3: ='Slider Links'!I3 -> 0 | P3: ='Slider Links'!J3 -> 0.6 | R3: ='Slider Links'!K3 -> 0
A4: Earth | B4: Builds stone that stays | C4: First pass | E4: =COUNTIF('Base Runes'!$B:$B,$A4) -> 10 | F4: =E4/2 -> 5 | G4: Earth | J4: ='Slider Links'!G4 -> 0 | L4: ='Slider Links'!H4 -> 1 | N4: ='Slider Links'!I4 -> 0.2 | P4: ='Slider Links'!J4 -> -0.2 | R4: ='Slider Links'!K4 -> 1
A5: Wind | B5: Paid for by moving (Slipstream) | C5: First pass | E5: =COUNTIF('Base Runes'!$B:$B,$A5) -> 10 | F5: =E5/2 -> 5 | G5: Wind | J5: ='Slider Links'!G5 -> 0 | L5: ='Slider Links'!H5 -> -0.8 | N5: ='Slider Links'!I5 -> 0.2 | P5: ='Slider Links'!J5 -> 0 | R5: ='Slider Links'!K5 -> 0.4
A6: Lightning | B6: Marks a target, then overloads it | C6: First pass | E6: =COUNTIF('Base Runes'!$B:$B,$A6) -> 10 | F6: =E6/2 -> 5 | G6: Lightning | J6: ='Slider Links'!G6 -> 0.6 | L6: ='Slider Links'!H6 -> -0.5 | N6: ='Slider Links'!I6 -> 0 | P6: ='Slider Links'!J6 -> 0.7 | R6: ='Slider Links'!K6 -> -0.1
A7: Ice | B7: What it freezes stays frozen | C7: First pass (new 2026-10-22) | D7: B 2026-10-21: ice is its own affinity, taking water's Freeze; MODEL: the rule | E7: =COUNTIF('Base Runes'!$B:$B,$A7) -> 10 | F7: =E7/2 -> 5 | G7: Ice | J7: ='Slider Links'!G7 -> -1 | L7: ='Slider Links'!H7 -> 0.5 | N7: ='Slider Links'!I7 -> -0.3 | P7: ='Slider Links'!J7 -> 0.1 | R7: ='Slider Links'!K7 -> 0.2
A8: Dark | B8: Strongest where the light is weakest | C8: First pass (new 2026-10-22) | D8: B 2026-10-21: dark is an affinity; MODEL: the rule | E8: =COUNTIF('Base Runes'!$B:$B,$A8) -> 10 | F8: =E8/2 -> 5 | G8: Dark | J8: ='Slider Links'!G8 -> -0.3 | L8: ='Slider Links'!H8 -> -0.3 | N8: ='Slider Links'!I8 -> -0.2 | P8: ='Slider Links'!J8 -> -1 | R8: ='Slider Links'!K8 -> -0.4
A9: Metal | B9: Worn and carried metal is its material | C9: First pass | D9: MODEL | E9: =COUNTIF('Base Runes'!$B:$B,$A9) -> 10 | F9: =E9/2 -> 5 | G9: Metal | J9: ='Slider Links'!G9 -> 0 | L9: ='Slider Links'!H9 -> 0.8 | N9: ='Slider Links'!I9 -> -0.3 | P9: ='Slider Links'!J9 -> 0.2 | R9: ='Slider Links'!K9 -> 1
A10: Blood | B10: Works the blood that is already out | C10: First pass | D10: C: blood storage and blood-to-metal techniques exist; MODEL: the rule | E10: =COUNTIF('Base Runes'!$B:$B,$A10) -> 10 | F10: =E10/2 -> 5 | G10: Blood | J10: ='Slider Links'!G10 -> 0.3 | L10: ='Slider Links'!H10 -> -0.5 | N10: ='Slider Links'!I10 -> 0.6 | P10: ='Slider Links'!J10 -> -0.2 | R10: ='Slider Links'!K10 -> 0.8
A11: Life | B11: Works inside living bodies | C11: First pass | D11: C: life practitioners work inside a body, with consent; MODEL: the rule | E11: =COUNTIF('Base Runes'!$B:$B,$A11) -> 10 | F11: =E11/2 -> 5 | G11: Life | J11: ='Slider Links'!G11 -> 0.3 | L11: ='Slider Links'!H11 -> 0 | N11: ='Slider Links'!I11 -> 1 | P11: ='Slider Links'!J11 -> 0.2 | R11: ='Slider Links'!K11 -> 0.4
A12: Death | B12: What has died stays useful | C12: First pass | D12: C: death affinity and undeath exist; MODEL: the rule | E12: =COUNTIF('Base Runes'!$B:$B,$A12) -> 10 | F12: =E12/2 -> 5 | G12: Death | J12: ='Slider Links'!G12 -> -0.5 | L12: ='Slider Links'!H12 -> 0.2 | N12: ='Slider Links'!I12 -> -1 | P12: ='Slider Links'!J12 -> -0.4 | R12: ='Slider Links'!K12 -> 0
A13: Nature | B13: Grows from the ground and keeps growing | C13: First pass | D13: C: nature is named; MODEL: the rule | E13: =COUNTIF('Base Runes'!$B:$B,$A13) -> 10 | F13: =E13/2 -> 5 | G13: Nature | J13: ='Slider Links'!G13 -> 0 | L13: ='Slider Links'!H13 -> 0.2 | N13: ='Slider Links'!I13 -> 1 | P13: ='Slider Links'!J13 -> 0.1 | R13: ='Slider Links'!K13 -> 0.5
A14: Light | B14: Straight and instant; reveals the hidden | C14: First pass | D14: MODEL: the rule | E14: =COUNTIF('Base Runes'!$B:$B,$A14) -> 10 | F14: =E14/2 -> 5 | G14: Light | J14: ='Slider Links'!G14 -> 0.4 | L14: ='Slider Links'!H14 -> -0.4 | N14: ='Slider Links'!I14 -> 0.3 | P14: ='Slider Links'!J14 -> 1 | R14: ='Slider Links'!K14 -> 0
A15: Dream | B15: The mind | C15: First pass | D15: C: dream is a named, valued affinity; MODEL: the rule | E15: =COUNTIF('Base Runes'!$B:$B,$A15) -> 10 | F15: =E15/2 -> 5 | G15: Dream | J15: ='Slider Links'!G15 -> 0 | L15: ='Slider Links'!H15 -> -0.6 | N15: ='Slider Links'!I15 -> 0 | P15: ='Slider Links'!J15 -> -0.6 | R15: ='Slider Links'!K15 -> -1
A16: Poison | B16: Doses stack inside a body and come due later | C16: First pass | D16: MODEL: the rule | E16: =COUNTIF('Base Runes'!$B:$B,$A16) -> 10 | F16: =E16/2 -> 5 | G16: Poison | J16: ='Slider Links'!G16 -> 0 | L16: ='Slider Links'!H16 -> -0.3 | N16: ='Slider Links'!I16 -> -0.8 | P16: ='Slider Links'!J16 -> -0.6 | R16: ='Slider Links'!K16 -> 0.4
A17: Disease | B17: A cloud that only harms flesh | C17: First pass | D17: B 2026-10-21: renamed from Miasma; C: miasma is flesh-only and armour counters it; MODEL: the rest | E17: =COUNTIF('Base Runes'!$B:$B,$A17) -> 10 | F17: =E17/2 -> 5 | G17: Disease | J17: ='Slider Links'!G17 -> 0.2 | L17: ='Slider Links'!H17 -> -0.5 | N17: ='Slider Links'!I17 -> -1 | P17: ='Slider Links'!J17 -> -0.3 | R17: ='Slider Links'!K17 -> 0.3
A18: Total | E18: =SUM(E2:E17) -> 166 | F18: =SUM(F2:F17) -> 83
A20: Proposed, awaiting your yes or no (no sheets yet)
A21: Sound | C21: Proposed
A22: Gravity | C22: Proposed
A23: Space | C23: Proposed
A24: Time | C24: Proposed
A25: Mind | C25: Proposed
A26: Beast | C26: Proposed
A27: Spirit | C27: Proposed

Sheet Alignment
B1: ='Slider Links'!A2 -> Water | C1: ='Slider Links'!A3 -> Fire | D1: ='Slider Links'!A4 -> Earth | E1: ='Slider Links'!A5 -> Wind | F1: ='Slider Links'!A6 -> Lightning | G1: ='Slider Links'!A7 -> Ice | H1: ='Slider Links'!A8 -> Dark | I1: ='Slider Links'!A9 -> Metal | J1: ='Slider Links'!A10 -> Blood | K1: ='Slider Links'!A11 -> Life | L1: ='Slider Links'!A12 -> Death | M1: ='Slider Links'!A13 -> Nature | N1: ='Slider Links'!A14 -> Light | O1: ='Slider Links'!A15 -> Dream | P1: ='Slider Links'!A16 -> Poison | Q1: ='Slider Links'!A17 -> Disease
A2: ='Slider Links'!A2 -> Water | B2: =IFERROR(SUMPRODUCT('Slider Links'!$G$2:$K$2,'Slider Links'!$G$2:$K$2)/SQRT(SUMSQ('Slider Links'!$G$2:$K$2)*SUMSQ('Slider Links'!$G$2:$K$2)),0) -> 1 | C2: =IFERROR(SUMPRODUCT('Slider Links'!$G$2:$K$2,'Slider Links'!$G$3:$K$3)/SQRT(SUMSQ('Slider Links'!$G$2:$K$2)*SUMSQ('Slider Links'!$G$3:$K$3)),0) -> -0.096793081 | D2: =IFERROR(SUMPRODUCT('Slider Links'!$G$2:$K$2,'Slider Links'!$G$4:$K$4)/SQRT(SUMSQ('Slider Links'!$G$2:$K$2)*SUMSQ('Slider Links'!$G$4:$K$4)),0) -> 0.067346557 | E2: =IFERROR(SUMPRODUCT('Slider Links'!$G$2:$K$2,'Slider Links'!$G$5:$K$5)/SQRT(SUMSQ('Slider Links'!$G$2:$K$2)*SUMSQ('Slider Links'!$G$5:$K$5)),0) -> 0.869003 | F2: =IFERROR(SUMPRODUCT('Slider Links'!$G$2:$K$2,'Slider Links'!$G$6:$K$6)/SQRT(SUMSQ('Slider Links'!$G$2:$K$2)*SUMSQ('Slider Links'!$G$6:$K$6)),0) -> 0.055314225 | G2: =IFERROR(SUMPRODUCT('Slider Links'!$G$2:$K$2,'Slider Links'!$G$7:$K$7)/SQRT(SUMSQ('Slider Links'!$G$2:$K$2)*SUMSQ('Slider Links'!$G$7:$K$7)),0) -> -0.024715017 | H2: =IFERROR(SUMPRODUCT('Slider Links'!$G$2:$K$2,'Slider Links'!$G$8:$K$8)/SQRT(SUMSQ('Slider Links'!$G$2:$K$2)*SUMSQ('Slider Links'!$G$8:$K$8)),0) -> -0.05787694 | I2: =IFERROR(SUMPRODUCT('Slider Links'!$G$2:$K$2,'Slider Links'!$G$9:$K$9)/SQRT(SUMSQ('Slider Links'!$G$2:$K$2)*SUMSQ('Slider Links'!$G$9:$K$9)),0) -> -0.021901895 | J2: =IFERROR(SUMPRODUCT('Slider Links'!$G$2:$K$2,'Slider Links'!$G$10:$K$10)/SQRT(SUMSQ('Slider Links'!$G$2:$K$2)*SUMSQ('Slider Links'!$G$10:$K$10)),0) -> 0.8185453 | K2: =IFERROR(SUMPRODUCT('Slider Links'!$G$2:$K$2,'Slider Links'!$G$11:$K$11)/SQRT(SUMSQ('Slider Links'!$G$2:$K$2)*SUMSQ('Slider Links'!$G$11:$K$11)),0) -> 0.55586019 | L2: =IFERROR(SUMPRODUCT('Slider Links'!$G$2:$K$2,'Slider Links'!$G$12:$K$12)/SQRT(SUMSQ('Slider Links'!$G$2:$K$2)*SUMSQ('Slider Links'!$G$12:$K$12)),0) -> -0.37910623 | M2: =IFERROR(SUMPRODUCT('Slider Links'!$G$2:$K$2,'Slider Links'!$G$13:$K$13)/SQRT(SUMSQ('Slider Links'!$G$2:$K$2)*SUMSQ('Slider Links'!$G$13:$K$13)),0) -> 0.57927436 | N2: =IFERROR(SUMPRODUCT('Slider Links'!$G$2:$K$2,'Slider Links'!$G$14:$K$14)/SQRT(SUMSQ('Slider Links'!$G$2:$K$2)*SUMSQ('Slider Links'!$G$14:$K$14)),0) -> 0.22085197 | O2: =IFERROR(SUMPRODUCT('Slider Links'!$G$2:$K$2,'Slider Links'!$G$15:$K$15)/SQRT(SUMSQ('Slider Links'!$G$2:$K$2)*SUMSQ('Slider Links'!$G$15:$K$15)),0) -> -0.17774365 | P2: =IFERROR(SUMPRODUCT('Slider Links'!$G$2:$K$2,'Slider Links'!$G$16:$K$16)/SQRT(SUMSQ('Slider Links'!$G$2:$K$2)*SUMSQ('Slider Links'!$G$16:$K$16)),0) -> 0.01737489 | Q2: =IFERROR(SUMPRODUCT('Slider Links'!$G$2:$K$2,'Slider Links'!$G$17:$K$17)/SQRT(SUMSQ('Slider Links'!$G$2:$K$2)*SUMSQ('Slider Links'!$G$17:$K$17)),0) -> -0.064088246
A3: ='Slider Links'!A3 -> Fire | B3: =IFERROR(SUMPRODUCT('Slider Links'!$G$3:$K$3,'Slider Links'!$G$2:$K$2)/SQRT(SUMSQ('Slider Links'!$G$3:$K$3)*SUMSQ('Slider Links'!$G$2:$K$2)),0) -> -0.096793081 | C3: =IFERROR(SUMPRODUCT('Slider Links'!$G$3:$K$3,'Slider Links'!$G$3:$K$3)/SQRT(SUMSQ('Slider Links'!$G$3:$K$3)*SUMSQ('Slider Links'!$G$3:$K$3)),0) -> 1 | D3: =IFERROR(SUMPRODUCT('Slider Links'!$G$3:$K$3,'Slider Links'!$G$4:$K$4)/SQRT(SUMSQ('Slider Links'!$G$3:$K$3)*SUMSQ('Slider Links'!$G$4:$K$4)),0) -> -0.24184306 | E3: =IFERROR(SUMPRODUCT('Slider Links'!$G$3:$K$3,'Slider Links'!$G$5:$K$5)/SQRT(SUMSQ('Slider Links'!$G$3:$K$3)*SUMSQ('Slider Links'!$G$5:$K$5)),0) -> 0.21746411 | F3: =IFERROR(SUMPRODUCT('Slider Links'!$G$3:$K$3,'Slider Links'!$G$6:$K$6)/SQRT(SUMSQ('Slider Links'!$G$3:$K$3)*SUMSQ('Slider Links'!$G$6:$K$6)),0) -> 0.92223239 | G3: =IFERROR(SUMPRODUCT('Slider Links'!$G$3:$K$3,'Slider Links'!$G$7:$K$7)/SQRT(SUMSQ('Slider Links'!$G$3:$K$3)*SUMSQ('Slider Links'!$G$7:$K$7)),0) -> -0.767777 | H3: =IFERROR(SUMPRODUCT('Slider Links'!$G$3:$K$3,'Slider Links'!$G$8:$K$8)/SQRT(SUMSQ('Slider Links'!$G$3:$K$3)*SUMSQ('Slider Links'!$G$8:$K$8)),0) -> -0.57261336 | I3: =IFERROR(SUMPRODUCT('Slider Links'!$G$3:$K$3,'Slider Links'!$G$9:$K$9)/SQRT(SUMSQ('Slider Links'!$G$3:$K$3)*SUMSQ('Slider Links'!$G$9:$K$9)),0) -> -0.074904966 | J3: =IFERROR(SUMPRODUCT('Slider Links'!$G$3:$K$3,'Slider Links'!$G$10:$K$10)/SQRT(SUMSQ('Slider Links'!$G$3:$K$3)*SUMSQ('Slider Links'!$G$10:$K$10)),0) -> 0.23328692 | K3: =IFERROR(SUMPRODUCT('Slider Links'!$G$3:$K$3,'Slider Links'!$G$11:$K$11)/SQRT(SUMSQ('Slider Links'!$G$3:$K$3)*SUMSQ('Slider Links'!$G$11:$K$11)),0) -> 0.30709337 | L3: =IFERROR(SUMPRODUCT('Slider Links'!$G$3:$K$3,'Slider Links'!$G$12:$K$12)/SQRT(SUMSQ('Slider Links'!$G$3:$K$3)*SUMSQ('Slider Links'!$G$12:$K$12)),0) -> -0.55172414 | M3: =IFERROR(SUMPRODUCT('Slider Links'!$G$3:$K$3,'Slider Links'!$G$13:$K$13)/SQRT(SUMSQ('Slider Links'!$G$3:$K$3)*SUMSQ('Slider Links'!$G$13:$K$13)),0) -> 0 | N3: =IFERROR(SUMPRODUCT('Slider Links'!$G$3:$K$3,'Slider Links'!$G$14:$K$14)/SQRT(SUMSQ('Slider Links'!$G$3:$K$3)*SUMSQ('Slider Links'!$G$14:$K$14)),0) -> 0.7832934 | O3: =IFERROR(SUMPRODUCT('Slider Links'!$G$3:$K$3,'Slider Links'!$G$15:$K$15)/SQRT(SUMSQ('Slider Links'!$G$3:$K$3)*SUMSQ('Slider Links'!$G$15:$K$15)),0) -> -0.11397885 | P3: =IFERROR(SUMPRODUCT('Slider Links'!$G$3:$K$3,'Slider Links'!$G$16:$K$16)/SQRT(SUMSQ('Slider Links'!$G$3:$K$3)*SUMSQ('Slider Links'!$G$16:$K$16)),0) -> -0.20055097 | Q3: =IFERROR(SUMPRODUCT('Slider Links'!$G$3:$K$3,'Slider Links'!$G$17:$K$17)/SQRT(SUMSQ('Slider Links'!$G$3:$K$3)*SUMSQ('Slider Links'!$G$17:$K$17)),0) -> 0.11644109
A4: ='Slider Links'!A4 -> Earth | B4: =IFERROR(SUMPRODUCT('Slider Links'!$G$4:$K$4,'Slider Links'!$G$2:$K$2)/SQRT(SUMSQ('Slider Links'!$G$4:$K$4)*SUMSQ('Slider Links'!$G$2:$K$2)),0) -> 0.067346557 | C4: =IFERROR(SUMPRODUCT('Slider Links'!$G$4:$K$4,'Slider Links'!$G$3:$K$3)/SQRT(SUMSQ('Slider Links'!$G$4:$K$4)*SUMSQ('Slider Links'!$G$3:$K$3)),0) -> -0.24184306 | D4: =IFERROR(SUMPRODUCT('Slider Links'!$G$4:$K$4,'Slider Links'!$G$4:$K$4)/SQRT(SUMSQ('Slider Links'!$G$4:$K$4)*SUMSQ('Slider Links'!$G$4:$K$4)),0) -> 1 | E4: =IFERROR(SUMPRODUCT('Slider Links'!$G$4:$K$4,'Slider Links'!$G$5:$K$5)/SQRT(SUMSQ('Slider Links'!$G$4:$K$4)*SUMSQ('Slider Links'!$G$5:$K$5)),0) -> -0.27235239 | F4: =IFERROR(SUMPRODUCT('Slider Links'!$G$4:$K$4,'Slider Links'!$G$6:$K$6)/SQRT(SUMSQ('Slider Links'!$G$4:$K$4)*SUMSQ('Slider Links'!$G$6:$K$6)),0) -> -0.48701077 | G4: =IFERROR(SUMPRODUCT('Slider Links'!$G$4:$K$4,'Slider Links'!$G$7:$K$7)/SQRT(SUMSQ('Slider Links'!$G$4:$K$4)*SUMSQ('Slider Links'!$G$7:$K$7)),0) -> 0.36463019 | H4: =IFERROR(SUMPRODUCT('Slider Links'!$G$4:$K$4,'Slider Links'!$G$8:$K$8)/SQRT(SUMSQ('Slider Links'!$G$4:$K$4)*SUMSQ('Slider Links'!$G$8:$K$8)),0) -> -0.31872971 | I4: =IFERROR(SUMPRODUCT('Slider Links'!$G$4:$K$4,'Slider Links'!$G$9:$K$9)/SQRT(SUMSQ('Slider Links'!$G$4:$K$4)*SUMSQ('Slider Links'!$G$9:$K$9)),0) -> 0.88599367 | J4: =IFERROR(SUMPRODUCT('Slider Links'!$G$4:$K$4,'Slider Links'!$G$10:$K$10)/SQRT(SUMSQ('Slider Links'!$G$4:$K$4)*SUMSQ('Slider Links'!$G$10:$K$10)),0) -> 0.27151049 | K4: =IFERROR(SUMPRODUCT('Slider Links'!$G$4:$K$4,'Slider Links'!$G$11:$K$11)/SQRT(SUMSQ('Slider Links'!$G$4:$K$4)*SUMSQ('Slider Links'!$G$11:$K$11)),0) -> 0.3418704 | L4: =IFERROR(SUMPRODUCT('Slider Links'!$G$4:$K$4,'Slider Links'!$G$12:$K$12)/SQRT(SUMSQ('Slider Links'!$G$4:$K$4)*SUMSQ('Slider Links'!$G$12:$K$12)),0) -> 0.046065344 | M4: =IFERROR(SUMPRODUCT('Slider Links'!$G$4:$K$4,'Slider Links'!$G$13:$K$13)/SQRT(SUMSQ('Slider Links'!$G$4:$K$4)*SUMSQ('Slider Links'!$G$13:$K$13)),0) -> 0.53515468 | N4: =IFERROR(SUMPRODUCT('Slider Links'!$G$4:$K$4,'Slider Links'!$G$14:$K$14)/SQRT(SUMSQ('Slider Links'!$G$4:$K$4)*SUMSQ('Slider Links'!$G$14:$K$14)),0) -> -0.31532074 | O4: =IFERROR(SUMPRODUCT('Slider Links'!$G$4:$K$4,'Slider Links'!$G$15:$K$15)/SQRT(SUMSQ('Slider Links'!$G$4:$K$4)*SUMSQ('Slider Links'!$G$15:$K$15)),0) -> -0.78246663 | P4: =IFERROR(SUMPRODUCT('Slider Links'!$G$4:$K$4,'Slider Links'!$G$16:$K$16)/SQRT(SUMSQ('Slider Links'!$G$4:$K$4)*SUMSQ('Slider Links'!$G$16:$K$16)),0) -> 0.03721042 | Q4: =IFERROR(SUMPRODUCT('Slider Links'!$G$4:$K$4,'Slider Links'!$G$17:$K$17)/SQRT(SUMSQ('Slider Links'!$G$4:$K$4)*SUMSQ('Slider Links'!$G$17:$K$17)),0) -> -0.19444133
A5: ='Slider Links'!A5 -> Wind | B5: =IFERROR(SUMPRODUCT('Slider Links'!$G$5:$K$5,'Slider Links'!$G$2:$K$2)/SQRT(SUMSQ('Slider Links'!$G$5:$K$5)*SUMSQ('Slider Links'!$G$2:$K$2)),0) -> 0.869003 | C5: =IFERROR(SUMPRODUCT('Slider Links'!$G$5:$K$5,'Slider Links'!$G$3:$K$3)/SQRT(SUMSQ('Slider Links'!$G$5:$K$5)*SUMSQ('Slider Links'!$G$3:$K$3)),0) -> 0.21746411 | D5: =IFERROR(SUMPRODUCT('Slider Links'!$G$5:$K$5,'Slider Links'!$G$4:$K$4)/SQRT(SUMSQ('Slider Links'!$G$5:$K$5)*SUMSQ('Slider Links'!$G$4:$K$4)),0) -> -0.27235239 | E5: =IFERROR(SUMPRODUCT('Slider Links'!$G$5:$K$5,'Slider Links'!$G$5:$K$5)/SQRT(SUMSQ('Slider Links'!$G$5:$K$5)*SUMSQ('Slider Links'!$G$5:$K$5)),0) -> 1 | F5: =IFERROR(SUMPRODUCT('Slider Links'!$G$5:$K$5,'Slider Links'!$G$6:$K$6)/SQRT(SUMSQ('Slider Links'!$G$5:$K$5)*SUMSQ('Slider Links'!$G$6:$K$6)),0) -> 0.37282186 | G5: =IFERROR(SUMPRODUCT('Slider Links'!$G$5:$K$5,'Slider Links'!$G$7:$K$7)/SQRT(SUMSQ('Slider Links'!$G$5:$K$5)*SUMSQ('Slider Links'!$G$7:$K$7)),0) -> -0.351671 | H5: =IFERROR(SUMPRODUCT('Slider Links'!$G$5:$K$5,'Slider Links'!$G$8:$K$8)/SQRT(SUMSQ('Slider Links'!$G$5:$K$5)*SUMSQ('Slider Links'!$G$8:$K$8)),0) -> 0.037151881 | I5: =IFERROR(SUMPRODUCT('Slider Links'!$G$5:$K$5,'Slider Links'!$G$9:$K$9)/SQRT(SUMSQ('Slider Links'!$G$5:$K$5)*SUMSQ('Slider Links'!$G$9:$K$9)),0) -> -0.24603392 | J5: =IFERROR(SUMPRODUCT('Slider Links'!$G$5:$K$5,'Slider Links'!$G$10:$K$10)/SQRT(SUMSQ('Slider Links'!$G$5:$K$5)*SUMSQ('Slider Links'!$G$10:$K$10)),0) -> 0.7801895 | K5: =IFERROR(SUMPRODUCT('Slider Links'!$G$5:$K$5,'Slider Links'!$G$11:$K$11)/SQRT(SUMSQ('Slider Links'!$G$5:$K$5)*SUMSQ('Slider Links'!$G$11:$K$11)),0) -> 0.34583425 | L5: =IFERROR(SUMPRODUCT('Slider Links'!$G$5:$K$5,'Slider Links'!$G$12:$K$12)/SQRT(SUMSQ('Slider Links'!$G$5:$K$5)*SUMSQ('Slider Links'!$G$12:$K$12)),0) -> -0.32619617 | M5: =IFERROR(SUMPRODUCT('Slider Links'!$G$5:$K$5,'Slider Links'!$G$13:$K$13)/SQRT(SUMSQ('Slider Links'!$G$5:$K$5)*SUMSQ('Slider Links'!$G$13:$K$13)),0) -> 0.2296677 | N5: =IFERROR(SUMPRODUCT('Slider Links'!$G$5:$K$5,'Slider Links'!$G$14:$K$14)/SQRT(SUMSQ('Slider Links'!$G$5:$K$5)*SUMSQ('Slider Links'!$G$14:$K$14)),0) -> 0.34916797 | O5: =IFERROR(SUMPRODUCT('Slider Links'!$G$5:$K$5,'Slider Links'!$G$15:$K$15)/SQRT(SUMSQ('Slider Links'!$G$5:$K$5)*SUMSQ('Slider Links'!$G$15:$K$15)),0) -> 0.066555833 | P5: =IFERROR(SUMPRODUCT('Slider Links'!$G$5:$K$5,'Slider Links'!$G$16:$K$16)/SQRT(SUMSQ('Slider Links'!$G$5:$K$5)*SUMSQ('Slider Links'!$G$16:$K$16)),0) -> 0.23421602 | Q5: =IFERROR(SUMPRODUCT('Slider Links'!$G$5:$K$5,'Slider Links'!$G$17:$K$17)/SQRT(SUMSQ('Slider Links'!$G$5:$K$5)*SUMSQ('Slider Links'!$G$17:$K$17)),0) -> 0.28797293
A6: ='Slider Links'!A6 -> Lightning | B6: =IFERROR(SUMPRODUCT('Slider Links'!$G$6:$K$6,'Slider Links'!$G$2:$K$2)/SQRT(SUMSQ('Slider Links'!$G$6:$K$6)*SUMSQ('Slider Links'!$G$2:$K$2)),0) -> 0.055314225 | C6: =IFERROR(SUMPRODUCT('Slider Links'!$G$6:$K$6,'Slider Links'!$G$3:$K$3)/SQRT(SUMSQ('Slider Links'!$G$6:$K$6)*SUMSQ('Slider Links'!$G$3:$K$3)),0) -> 0.92223239 | D6: =IFERROR(SUMPRODUCT('Slider Links'!$G$6:$K$6,'Slider Links'!$G$4:$K$4)/SQRT(SUMSQ('Slider Links'!$G$6:$K$6)*SUMSQ('Slider Links'!$G$4:$K$4)),0) -> -0.48701077 | E6: =IFERROR(SUMPRODUCT('Slider Links'!$G$6:$K$6,'Slider Links'!$G$5:$K$5)/SQRT(SUMSQ('Slider Links'!$G$6:$K$6)*SUMSQ('Slider Links'!$G$5:$K$5)),0) -> 0.37282186 | F6: =IFERROR(SUMPRODUCT('Slider Links'!$G$6:$K$6,'Slider Links'!$G$6:$K$6)/SQRT(SUMSQ('Slider Links'!$G$6:$K$6)*SUMSQ('Slider Links'!$G$6:$K$6)),0) -> 1 | G6: =IFERROR(SUMPRODUCT('Slider Links'!$G$6:$K$6,'Slider Links'!$G$7:$K$7)/SQRT(SUMSQ('Slider Links'!$G$6:$K$6)*SUMSQ('Slider Links'!$G$7:$K$7)),0) -> -0.64405224 | H6: =IFERROR(SUMPRODUCT('Slider Links'!$G$6:$K$6,'Slider Links'!$G$8:$K$8)/SQRT(SUMSQ('Slider Links'!$G$6:$K$6)*SUMSQ('Slider Links'!$G$8:$K$8)),0) -> -0.55750409 | I6: =IFERROR(SUMPRODUCT('Slider Links'!$G$6:$K$6,'Slider Links'!$G$9:$K$9)/SQRT(SUMSQ('Slider Links'!$G$6:$K$6)*SUMSQ('Slider Links'!$G$9:$K$9)),0) -> -0.2568351 | J6: =IFERROR(SUMPRODUCT('Slider Links'!$G$6:$K$6,'Slider Links'!$G$10:$K$10)/SQRT(SUMSQ('Slider Links'!$G$6:$K$6)*SUMSQ('Slider Links'!$G$10:$K$10)),0) -> 0.16967516 | K6: =IFERROR(SUMPRODUCT('Slider Links'!$G$6:$K$6,'Slider Links'!$G$11:$K$11)/SQRT(SUMSQ('Slider Links'!$G$6:$K$6)*SUMSQ('Slider Links'!$G$11:$K$11)),0) -> 0.23399236 | L6: =IFERROR(SUMPRODUCT('Slider Links'!$G$6:$K$6,'Slider Links'!$G$12:$K$12)/SQRT(SUMSQ('Slider Links'!$G$6:$K$6)*SUMSQ('Slider Links'!$G$12:$K$12)),0) -> -0.53599831 | M6: =IFERROR(SUMPRODUCT('Slider Links'!$G$6:$K$6,'Slider Links'!$G$13:$K$13)/SQRT(SUMSQ('Slider Links'!$G$6:$K$6)*SUMSQ('Slider Links'!$G$13:$K$13)),0) -> -0.066597331 | N6: =IFERROR(SUMPRODUCT('Slider Links'!$G$6:$K$6,'Slider Links'!$G$14:$K$14)/SQRT(SUMSQ('Slider Links'!$G$6:$K$6)*SUMSQ('Slider Links'!$G$14:$K$14)),0) -> 0.91124216 | O6: =IFERROR(SUMPRODUCT('Slider Links'!$G$6:$K$6,'Slider Links'!$G$15:$K$15)/SQRT(SUMSQ('Slider Links'!$G$6:$K$6)*SUMSQ('Slider Links'!$G$15:$K$15)),0) -> -0.014474524 | P6: =IFERROR(SUMPRODUCT('Slider Links'!$G$6:$K$6,'Slider Links'!$G$16:$K$16)/SQRT(SUMSQ('Slider Links'!$G$6:$K$6)*SUMSQ('Slider Links'!$G$16:$K$16)),0) -> -0.26317534 | Q6: =IFERROR(SUMPRODUCT('Slider Links'!$G$6:$K$6,'Slider Links'!$G$17:$K$17)/SQRT(SUMSQ('Slider Links'!$G$6:$K$6)*SUMSQ('Slider Links'!$G$17:$K$17)),0) -> 0.1017708
A7: ='Slider Links'!A7 -> Ice | B7: =IFERROR(SUMPRODUCT('Slider Links'!$G$7:$K$7,'Slider Links'!$G$2:$K$2)/SQRT(SUMSQ('Slider Links'!$G$7:$K$7)*SUMSQ('Slider Links'!$G$2:$K$2)),0) -> -0.024715017 | C7: =IFERROR(SUMPRODUCT('Slider Links'!$G$7:$K$7,'Slider Links'!$G$3:$K$3)/SQRT(SUMSQ('Slider Links'!$G$7:$K$7)*SUMSQ('Slider Links'!$G$3:$K$3)),0) -> -0.767777 | D7: =IFERROR(SUMPRODUCT('Slider Links'!$G$7:$K$7,'Slider Links'!$G$4:$K$4)/SQRT(SUMSQ('Slider Links'!$G$7:$K$7)*SUMSQ('Slider Links'!$G$4:$K$4)),0) -> 0.36463019 | E7: =IFERROR(SUMPRODUCT('Slider Links'!$G$7:$K$7,'Slider Links'!$G$5:$K$5)/SQRT(SUMSQ('Slider Links'!$G$7:$K$7)*SUMSQ('Slider Links'!$G$5:$K$5)),0) -> -0.351671 | F7: =IFERROR(SUMPRODUCT('Slider Links'!$G$7:$K$7,'Slider Links'!$G$6:$K$6)/SQRT(SUMSQ('Slider Links'!$G$7:$K$7)*SUMSQ('Slider Links'!$G$6:$K$6)),0) -> -0.64405224 | G7: =IFERROR(SUMPRODUCT('Slider Links'!$G$7:$K$7,'Slider Links'!$G$7:$K$7)/SQRT(SUMSQ('Slider Links'!$G$7:$K$7)*SUMSQ('Slider Links'!$G$7:$K$7)),0) -> 1 | H7: =IFERROR(SUMPRODUCT('Slider Links'!$G$7:$K$7,'Slider Links'!$G$8:$K$8)/SQRT(SUMSQ('Slider Links'!$G$7:$K$7)*SUMSQ('Slider Links'!$G$8:$K$8)),0) -> 0.021660791 | I7: =IFERROR(SUMPRODUCT('Slider Links'!$G$7:$K$7,'Slider Links'!$G$9:$K$9)/SQRT(SUMSQ('Slider Links'!$G$7:$K$7)*SUMSQ('Slider Links'!$G$9:$K$9)),0) -> 0.45265187 | J7: =IFERROR(SUMPRODUCT('Slider Links'!$G$7:$K$7,'Slider Links'!$G$10:$K$10)/SQRT(SUMSQ('Slider Links'!$G$7:$K$7)*SUMSQ('Slider Links'!$G$10:$K$10)),0) -> -0.42599556 | K7: =IFERROR(SUMPRODUCT('Slider Links'!$G$7:$K$7,'Slider Links'!$G$11:$K$11)/SQRT(SUMSQ('Slider Links'!$G$7:$K$7)*SUMSQ('Slider Links'!$G$11:$K$11)),0) -> -0.37339436 | L7: =IFERROR(SUMPRODUCT('Slider Links'!$G$7:$K$7,'Slider Links'!$G$12:$K$12)/SQRT(SUMSQ('Slider Links'!$G$7:$K$7)*SUMSQ('Slider Links'!$G$12:$K$12)),0) -> 0.60576901 | M7: =IFERROR(SUMPRODUCT('Slider Links'!$G$7:$K$7,'Slider Links'!$G$13:$K$13)/SQRT(SUMSQ('Slider Links'!$G$7:$K$7)*SUMSQ('Slider Links'!$G$13:$K$13)),0) -> -0.066951981 | N7: =IFERROR(SUMPRODUCT('Slider Links'!$G$7:$K$7,'Slider Links'!$G$14:$K$14)/SQRT(SUMSQ('Slider Links'!$G$7:$K$7)*SUMSQ('Slider Links'!$G$14:$K$14)),0) -> -0.42143932 | O7: =IFERROR(SUMPRODUCT('Slider Links'!$G$7:$K$7,'Slider Links'!$G$15:$K$15)/SQRT(SUMSQ('Slider Links'!$G$7:$K$7)*SUMSQ('Slider Links'!$G$15:$K$15)),0) -> -0.36217328 | P7: =IFERROR(SUMPRODUCT('Slider Links'!$G$7:$K$7,'Slider Links'!$G$16:$K$16)/SQRT(SUMSQ('Slider Links'!$G$7:$K$7)*SUMSQ('Slider Links'!$G$16:$K$16)),0) -> 0.083450757 | Q7: =IFERROR(SUMPRODUCT('Slider Links'!$G$7:$K$7,'Slider Links'!$G$17:$K$17)/SQRT(SUMSQ('Slider Links'!$G$7:$K$7)*SUMSQ('Slider Links'!$G$17:$K$17)),0) -> -0.083948933
A8: ='Slider Links'!A8 -> Dark | B8: =IFERROR(SUMPRODUCT('Slider Links'!$G$8:$K$8,'Slider Links'!$G$2:$K$2)/SQRT(SUMSQ('Slider Links'!$G$8:$K$8)*SUMSQ('Slider Links'!$G$2:$K$2)),0) -> -0.05787694 | C8: =IFERROR(SUMPRODUCT('Slider Links'!$G$8:$K$8,'Slider Links'!$G$3:$K$3)/SQRT(SUMSQ('Slider Links'!$G$8:$K$8)*SUMSQ('Slider Links'!$G$3:$K$3)),0) -> -0.57261336 | D8: =IFERROR(SUMPRODUCT('Slider Links'!$G$8:$K$8,'Slider Links'!$G$4:$K$4)/SQRT(SUMSQ('Slider Links'!$G$8:$K$8)*SUMSQ('Slider Links'!$G$4:$K$4)),0) -> -0.31872971 | E8: =IFERROR(SUMPRODUCT('Slider Links'!$G$8:$K$8,'Slider Links'!$G$5:$K$5)/SQRT(SUMSQ('Slider Links'!$G$8:$K$8)*SUMSQ('Slider Links'!$G$5:$K$5)),0) -> 0.037151881 | F8: =IFERROR(SUMPRODUCT('Slider Links'!$G$8:$K$8,'Slider Links'!$G$6:$K$6)/SQRT(SUMSQ('Slider Links'!$G$8:$K$8)*SUMSQ('Slider Links'!$G$6:$K$6)),0) -> -0.55750409 | G8: =IFERROR(SUMPRODUCT('Slider Links'!$G$8:$K$8,'Slider Links'!$G$7:$K$7)/SQRT(SUMSQ('Slider Links'!$G$8:$K$8)*SUMSQ('Slider Links'!$G$7:$K$7)),0) -> 0.021660791 | H8: =IFERROR(SUMPRODUCT('Slider Links'!$G$8:$K$8,'Slider Links'!$G$8:$K$8)/SQRT(SUMSQ('Slider Links'!$G$8:$K$8)*SUMSQ('Slider Links'!$G$8:$K$8)),0) -> 1 | I8: =IFERROR(SUMPRODUCT('Slider Links'!$G$8:$K$8,'Slider Links'!$G$9:$K$9)/SQRT(SUMSQ('Slider Links'!$G$8:$K$8)*SUMSQ('Slider Links'!$G$9:$K$9)),0) -> -0.499078 | J8: =IFERROR(SUMPRODUCT('Slider Links'!$G$8:$K$8,'Slider Links'!$G$10:$K$10)/SQRT(SUMSQ('Slider Links'!$G$8:$K$8)*SUMSQ('Slider Links'!$G$10:$K$10)),0) -> -0.13043478 | K8: =IFERROR(SUMPRODUCT('Slider Links'!$G$8:$K$8,'Slider Links'!$G$11:$K$11)/SQRT(SUMSQ('Slider Links'!$G$8:$K$8)*SUMSQ('Slider Links'!$G$11:$K$11)),0) -> -0.48716823 | L8: =IFERROR(SUMPRODUCT('Slider Links'!$G$8:$K$8,'Slider Links'!$G$12:$K$12)/SQRT(SUMSQ('Slider Links'!$G$8:$K$8)*SUMSQ('Slider Links'!$G$12:$K$12)),0) -> 0.48778175 | M8: =IFERROR(SUMPRODUCT('Slider Links'!$G$8:$K$8,'Slider Links'!$G$13:$K$13)/SQRT(SUMSQ('Slider Links'!$G$8:$K$8)*SUMSQ('Slider Links'!$G$13:$K$13)),0) -> -0.41809677 | N8: =IFERROR(SUMPRODUCT('Slider Links'!$G$8:$K$8,'Slider Links'!$G$14:$K$14)/SQRT(SUMSQ('Slider Links'!$G$8:$K$8)*SUMSQ('Slider Links'!$G$14:$K$14)),0) -> -0.75990056 | O8: =IFERROR(SUMPRODUCT('Slider Links'!$G$8:$K$8,'Slider Links'!$G$15:$K$15)/SQRT(SUMSQ('Slider Links'!$G$8:$K$8)*SUMSQ('Slider Links'!$G$15:$K$15)),0) -> 0.76591088 | P8: =IFERROR(SUMPRODUCT('Slider Links'!$G$8:$K$8,'Slider Links'!$G$16:$K$16)/SQRT(SUMSQ('Slider Links'!$G$8:$K$8)*SUMSQ('Slider Links'!$G$16:$K$16)),0) -> 0.52535702 | Q8: =IFERROR(SUMPRODUCT('Slider Links'!$G$8:$K$8,'Slider Links'!$G$17:$K$17)/SQRT(SUMSQ('Slider Links'!$G$8:$K$8)*SUMSQ('Slider Links'!$G$17:$K$17)),0) -> 0.32998914
A9: ='Slider Links'!A9 -> Metal | B9: =IFERROR(SUMPRODUCT('Slider Links'!$G$9:$K$9,'Slider Links'!$G$2:$K$2)/SQRT(SUMSQ('Slider Links'!$G$9:$K$9)*SUMSQ('Slider Links'!$G$2:$K$2)),0) -> -0.021901895 | C9: =IFERROR(SUMPRODUCT('Slider Links'!$G$9:$K$9,'Slider Links'!$G$3:$K$3)/SQRT(SUMSQ('Slider Links'!$G$9:$K$9)*SUMSQ('Slider Links'!$G$3:$K$3)),0) -> -0.074904966 | D9: =IFERROR(SUMPRODUCT('Slider Links'!$G$9:$K$9,'Slider Links'!$G$4:$K$4)/SQRT(SUMSQ('Slider Links'!$G$9:$K$9)*SUMSQ('Slider Links'!$G$4:$K$4)),0) -> 0.88599367 | E9: =IFERROR(SUMPRODUCT('Slider Links'!$G$9:$K$9,'Slider Links'!$G$5:$K$5)/SQRT(SUMSQ('Slider Links'!$G$9:$K$9)*SUMSQ('Slider Links'!$G$5:$K$5)),0) -> -0.24603392 | F9: =IFERROR(SUMPRODUCT('Slider Links'!$G$9:$K$9,'Slider Links'!$G$6:$K$6)/SQRT(SUMSQ('Slider Links'!$G$9:$K$9)*SUMSQ('Slider Links'!$G$6:$K$6)),0) -> -0.2568351 | G9: =IFERROR(SUMPRODUCT('Slider Links'!$G$9:$K$9,'Slider Links'!$G$7:$K$7)/SQRT(SUMSQ('Slider Links'!$G$9:$K$9)*SUMSQ('Slider Links'!$G$7:$K$7)),0) -> 0.45265187 | H9: =IFERROR(SUMPRODUCT('Slider Links'!$G$9:$K$9,'Slider Links'!$G$8:$K$8)/SQRT(SUMSQ('Slider Links'!$G$9:$K$9)*SUMSQ('Slider Links'!$G$8:$K$8)),0) -> -0.499078 | I9: =IFERROR(SUMPRODUCT('Slider Links'!$G$9:$K$9,'Slider Links'!$G$9:$K$9)/SQRT(SUMSQ('Slider Links'!$G$9:$K$9)*SUMSQ('Slider Links'!$G$9:$K$9)),0) -> 1 | J9: =IFERROR(SUMPRODUCT('Slider Links'!$G$9:$K$9,'Slider Links'!$G$10:$K$10)/SQRT(SUMSQ('Slider Links'!$G$9:$K$9)*SUMSQ('Slider Links'!$G$10:$K$10)),0) -> 0.11517185 | K9: =IFERROR(SUMPRODUCT('Slider Links'!$G$9:$K$9,'Slider Links'!$G$11:$K$11)/SQRT(SUMSQ('Slider Links'!$G$9:$K$9)*SUMSQ('Slider Links'!$G$11:$K$11)),0) -> 0.09265024 | L9: =IFERROR(SUMPRODUCT('Slider Links'!$G$9:$K$9,'Slider Links'!$G$12:$K$12)/SQRT(SUMSQ('Slider Links'!$G$9:$K$9)*SUMSQ('Slider Links'!$G$12:$K$12)),0) -> 0.23719906 | M9: =IFERROR(SUMPRODUCT('Slider Links'!$G$9:$K$9,'Slider Links'!$G$13:$K$13)/SQRT(SUMSQ('Slider Links'!$G$9:$K$9)*SUMSQ('Slider Links'!$G$13:$K$13)),0) -> 0.25051013 | N9: =IFERROR(SUMPRODUCT('Slider Links'!$G$9:$K$9,'Slider Links'!$G$14:$K$14)/SQRT(SUMSQ('Slider Links'!$G$9:$K$9)*SUMSQ('Slider Links'!$G$14:$K$14)),0) -> -0.13293003 | O9: =IFERROR(SUMPRODUCT('Slider Links'!$G$9:$K$9,'Slider Links'!$G$15:$K$15)/SQRT(SUMSQ('Slider Links'!$G$9:$K$9)*SUMSQ('Slider Links'!$G$15:$K$15)),0) -> -0.91699956 | P9: =IFERROR(SUMPRODUCT('Slider Links'!$G$9:$K$9,'Slider Links'!$G$16:$K$16)/SQRT(SUMSQ('Slider Links'!$G$9:$K$9)*SUMSQ('Slider Links'!$G$16:$K$16)),0) -> 0.18824194 | Q9: =IFERROR(SUMPRODUCT('Slider Links'!$G$9:$K$9,'Slider Links'!$G$17:$K$17)/SQRT(SUMSQ('Slider Links'!$G$9:$K$9)*SUMSQ('Slider Links'!$G$17:$K$17)),0) -> 0.086792607
A10: ='Slider Links'!A10 -> Blood | B10: =IFERROR(SUMPRODUCT('Slider Links'!$G$10:$K$10,'Slider Links'!$G$2:$K$2)/SQRT(SUMSQ('Slider Links'!$G$10:$K$10)*SUMSQ('Slider Links'!$G$2:$K$2)),0) -> 0.8185453 | C10: =IFERROR(SUMPRODUCT('Slider Links'!$G$10:$K$10,'Slider Links'!$G$3:$K$3)/SQRT(SUMSQ('Slider Links'!$G$10:$K$10)*SUMSQ('Slider Links'!$G$3:$K$3)),0) -> 0.23328692 | D10: =IFERROR(SUMPRODUCT('Slider Links'!$G$10:$K$10,'Slider Links'!$G$4:$K$4)/SQRT(SUMSQ('Slider Links'!$G$10:$K$10)*SUMSQ('Slider Links'!$G$4:$K$4)),0) -> 0.27151049 | E10: =IFERROR(SUMPRODUCT('Slider Links'!$G$10:$K$10,'Slider Links'!$G$5:$K$5)/SQRT(SUMSQ('Slider Links'!$G$10:$K$10)*SUMSQ('Slider Links'!$G$5:$K$5)),0) -> 0.7801895 | F10: =IFERROR(SUMPRODUCT('Slider Links'!$G$10:$K$10,'Slider Links'!$G$6:$K$6)/SQRT(SUMSQ('Slider Links'!$G$10:$K$10)*SUMSQ('Slider Links'!$G$6:$K$6)),0) -> 0.16967516 | G10: =IFERROR(SUMPRODUCT('Slider Links'!$G$10:$K$10,'Slider Links'!$G$7:$K$7)/SQRT(SUMSQ('Slider Links'!$G$10:$K$10)*SUMSQ('Slider Links'!$G$7:$K$7)),0) -> -0.42599556 | H10: =IFERROR(SUMPRODUCT('Slider Links'!$G$10:$K$10,'Slider Links'!$G$8:$K$8)/SQRT(SUMSQ('Slider Links'!$G$10:$K$10)*SUMSQ('Slider Links'!$G$8:$K$8)),0) -> -0.13043478 | I10: =IFERROR(SUMPRODUCT('Slider Links'!$G$10:$K$10,'Slider Links'!$G$9:$K$9)/SQRT(SUMSQ('Slider Links'!$G$10:$K$10)*SUMSQ('Slider Links'!$G$9:$K$9)),0) -> 0.11517185 | J10: =IFERROR(SUMPRODUCT('Slider Links'!$G$10:$K$10,'Slider Links'!$G$10:$K$10)/SQRT(SUMSQ('Slider Links'!$G$10:$K$10)*SUMSQ('Slider Links'!$G$10:$K$10)),0) -> 1 | K10: =IFERROR(SUMPRODUCT('Slider Links'!$G$10:$K$10,'Slider Links'!$G$11:$K$11)/SQRT(SUMSQ('Slider Links'!$G$10:$K$10)*SUMSQ('Slider Links'!$G$11:$K$11)),0) -> 0.7270049 | L10: =IFERROR(SUMPRODUCT('Slider Links'!$G$10:$K$10,'Slider Links'!$G$12:$K$12)/SQRT(SUMSQ('Slider Links'!$G$10:$K$10)*SUMSQ('Slider Links'!$G$12:$K$12)),0) -> -0.54433615 | M10: =IFERROR(SUMPRODUCT('Slider Links'!$G$10:$K$10,'Slider Links'!$G$13:$K$13)/SQRT(SUMSQ('Slider Links'!$G$10:$K$10)*SUMSQ('Slider Links'!$G$13:$K$13)),0) -> 0.6570092 | N10: =IFERROR(SUMPRODUCT('Slider Links'!$G$10:$K$10,'Slider Links'!$G$14:$K$14)/SQRT(SUMSQ('Slider Links'!$G$10:$K$10)*SUMSQ('Slider Links'!$G$14:$K$14)),0) -> 0.2150662 | O10: =IFERROR(SUMPRODUCT('Slider Links'!$G$10:$K$10,'Slider Links'!$G$15:$K$15)/SQRT(SUMSQ('Slider Links'!$G$10:$K$10)*SUMSQ('Slider Links'!$G$15:$K$15)),0) -> -0.24664927 | P10: =IFERROR(SUMPRODUCT('Slider Links'!$G$10:$K$10,'Slider Links'!$G$16:$K$16)/SQRT(SUMSQ('Slider Links'!$G$10:$K$10)*SUMSQ('Slider Links'!$G$16:$K$16)),0) -> 0.083752569 | Q10: =IFERROR(SUMPRODUCT('Slider Links'!$G$10:$K$10,'Slider Links'!$G$17:$K$17)/SQRT(SUMSQ('Slider Links'!$G$10:$K$10)*SUMSQ('Slider Links'!$G$17:$K$17)),0) -> 0.0070210455
A11: ='Slider Links'!A11 -> Life | B11: =IFERROR(SUMPRODUCT('Slider Links'!$G$11:$K$11,'Slider Links'!$G$2:$K$2)/SQRT(SUMSQ('Slider Links'!$G$11:$K$11)*SUMSQ('Slider Links'!$G$2:$K$2)),0) -> 0.55586019 | C11: =IFERROR(SUMPRODUCT('Slider Links'!$G$11:$K$11,'Slider Links'!$G$3:$K$3)/SQRT(SUMSQ('Slider Links'!$G$11:$K$11)*SUMSQ('Slider Links'!$G$3:$K$3)),0) -> 0.30709337 | D11: =IFERROR(SUMPRODUCT('Slider Links'!$G$11:$K$11,'Slider Links'!$G$4:$K$4)/SQRT(SUMSQ('Slider Links'!$G$11:$K$11)*SUMSQ('Slider Links'!$G$4:$K$4)),0) -> 0.3418704 | E11: =IFERROR(SUMPRODUCT('Slider Links'!$G$11:$K$11,'Slider Links'!$G$5:$K$5)/SQRT(SUMSQ('Slider Links'!$G$11:$K$11)*SUMSQ('Slider Links'!$G$5:$K$5)),0) -> 0.34583425 | F11: =IFERROR(SUMPRODUCT('Slider Links'!$G$11:$K$11,'Slider Links'!$G$6:$K$6)/SQRT(SUMSQ('Slider Links'!$G$11:$K$11)*SUMSQ('Slider Links'!$G$6:$K$6)),0) -> 0.23399236 | G11: =IFERROR(SUMPRODUCT('Slider Links'!$G$11:$K$11,'Slider Links'!$G$7:$K$7)/SQRT(SUMSQ('Slider Links'!$G$11:$K$11)*SUMSQ('Slider Links'!$G$7:$K$7)),0) -> -0.37339436 | H11: =IFERROR(SUMPRODUCT('Slider Links'!$G$11:$K$11,'Slider Links'!$G$8:$K$8)/SQRT(SUMSQ('Slider Links'!$G$11:$K$11)*SUMSQ('Slider Links'!$G$8:$K$8)),0) -> -0.48716823 | I11: =IFERROR(SUMPRODUCT('Slider Links'!$G$11:$K$11,'Slider Links'!$G$9:$K$9)/SQRT(SUMSQ('Slider Links'!$G$11:$K$11)*SUMSQ('Slider Links'!$G$9:$K$9)),0) -> 0.09265024 | J11: =IFERROR(SUMPRODUCT('Slider Links'!$G$11:$K$11,'Slider Links'!$G$10:$K$10)/SQRT(SUMSQ('Slider Links'!$G$11:$K$11)*SUMSQ('Slider Links'!$G$10:$K$10)),0) -> 0.7270049 | K11: =IFERROR(SUMPRODUCT('Slider Links'!$G$11:$K$11,'Slider Links'!$G$11:$K$11)/SQRT(SUMSQ('Slider Links'!$G$11:$K$11)*SUMSQ('Slider Links'!$G$11:$K$11)),0) -> 1 | L11: =IFERROR(SUMPRODUCT('Slider Links'!$G$11:$K$11,'Slider Links'!$G$12:$K$12)/SQRT(SUMSQ('Slider Links'!$G$11:$K$11)*SUMSQ('Slider Links'!$G$12:$K$12)),0) -> -0.89934486 | M11: =IFERROR(SUMPRODUCT('Slider Links'!$G$11:$K$11,'Slider Links'!$G$13:$K$13)/SQRT(SUMSQ('Slider Links'!$G$11:$K$11)*SUMSQ('Slider Links'!$G$13:$K$13)),0) -> 0.94209196 | N11: =IFERROR(SUMPRODUCT('Slider Links'!$G$11:$K$11,'Slider Links'!$G$14:$K$14)/SQRT(SUMSQ('Slider Links'!$G$11:$K$11)*SUMSQ('Slider Links'!$G$14:$K$14)),0) -> 0.45971352 | O11: =IFERROR(SUMPRODUCT('Slider Links'!$G$11:$K$11,'Slider Links'!$G$15:$K$15)/SQRT(SUMSQ('Slider Links'!$G$11:$K$11)*SUMSQ('Slider Links'!$G$15:$K$15)),0) -> -0.34909551 | P11: =IFERROR(SUMPRODUCT('Slider Links'!$G$11:$K$11,'Slider Links'!$G$16:$K$16)/SQRT(SUMSQ('Slider Links'!$G$11:$K$11)*SUMSQ('Slider Links'!$G$16:$K$16)),0) -> -0.59849942 | Q11: =IFERROR(SUMPRODUCT('Slider Links'!$G$11:$K$11,'Slider Links'!$G$17:$K$17)/SQRT(SUMSQ('Slider Links'!$G$11:$K$11)*SUMSQ('Slider Links'!$G$17:$K$17)),0) -> -0.63904163
A12: ='Slider Links'!A12 -> Death | B12: =IFERROR(SUMPRODUCT('Slider Links'!$G$12:$K$12,'Slider Links'!$G$2:$K$2)/SQRT(SUMSQ('Slider Links'!$G$12:$K$12)*SUMSQ('Slider Links'!$G$2:$K$2)),0) -> -0.37910623 | C12: =IFERROR(SUMPRODUCT('Slider Links'!$G$12:$K$12,'Slider Links'!$G$3:$K$3)/SQRT(SUMSQ('Slider Links'!$G$12:$K$12)*SUMSQ('Slider Links'!$G$3:$K$3)),0) -> -0.55172414 | D12: =IFERROR(SUMPRODUCT('Slider Links'!$G$12:$K$12,'Slider Links'!$G$4:$K$4)/SQRT(SUMSQ('Slider Links'!$G$12:$K$12)*SUMSQ('Slider Links'!$G$4:$K$4)),0) -> 0.046065344 | E12: =IFERROR(SUMPRODUCT('Slider Links'!$G$12:$K$12,'Slider Links'!$G$5:$K$5)/SQRT(SUMSQ('Slider Links'!$G$12:$K$12)*SUMSQ('Slider Links'!$G$5:$K$5)),0) -> -0.32619617 | F12: =IFERROR(SUMPRODUCT('Slider Links'!$G$12:$K$12,'Slider Links'!$G$6:$K$6)/SQRT(SUMSQ('Slider Links'!$G$12:$K$12)*SUMSQ('Slider Links'!$G$6:$K$6)),0) -> -0.53599831 | G12: =IFERROR(SUMPRODUCT('Slider Links'!$G$12:$K$12,'Slider Links'!$G$7:$K$7)/SQRT(SUMSQ('Slider Links'!$G$12:$K$12)*SUMSQ('Slider Links'!$G$7:$K$7)),0) -> 0.60576901 | H12: =IFERROR(SUMPRODUCT('Slider Links'!$G$12:$K$12,'Slider Links'!$G$8:$K$8)/SQRT(SUMSQ('Slider Links'!$G$12:$K$12)*SUMSQ('Slider Links'!$G$8:$K$8)),0) -> 0.48778175 | I12: =IFERROR(SUMPRODUCT('Slider Links'!$G$12:$K$12,'Slider Links'!$G$9:$K$9)/SQRT(SUMSQ('Slider Links'!$G$12:$K$12)*SUMSQ('Slider Links'!$G$9:$K$9)),0) -> 0.23719906 | J12: =IFERROR(SUMPRODUCT('Slider Links'!$G$12:$K$12,'Slider Links'!$G$10:$K$10)/SQRT(SUMSQ('Slider Links'!$G$12:$K$12)*SUMSQ('Slider Links'!$G$10:$K$10)),0) -> -0.54433615 | K12: =IFERROR(SUMPRODUCT('Slider Links'!$G$12:$K$12,'Slider Links'!$G$11:$K$11)/SQRT(SUMSQ('Slider Links'!$G$12:$K$12)*SUMSQ('Slider Links'!$G$11:$K$11)),0) -> -0.89934486 | L12: =IFERROR(SUMPRODUCT('Slider Links'!$G$12:$K$12,'Slider Links'!$G$12:$K$12)/SQRT(SUMSQ('Slider Links'!$G$12:$K$12)*SUMSQ('Slider Links'!$G$12:$K$12)),0) -> 1 | M12: =IFERROR(SUMPRODUCT('Slider Links'!$G$12:$K$12,'Slider Links'!$G$13:$K$13)/SQRT(SUMSQ('Slider Links'!$G$12:$K$12)*SUMSQ('Slider Links'!$G$13:$K$13)),0) -> -0.72835704 | N12: =IFERROR(SUMPRODUCT('Slider Links'!$G$12:$K$12,'Slider Links'!$G$14:$K$14)/SQRT(SUMSQ('Slider Links'!$G$12:$K$12)*SUMSQ('Slider Links'!$G$14:$K$14)),0) -> -0.68538172 | O12: =IFERROR(SUMPRODUCT('Slider Links'!$G$12:$K$12,'Slider Links'!$G$15:$K$15)/SQRT(SUMSQ('Slider Links'!$G$12:$K$12)*SUMSQ('Slider Links'!$G$15:$K$15)),0) -> 0.075985902 | P12: =IFERROR(SUMPRODUCT('Slider Links'!$G$12:$K$12,'Slider Links'!$G$16:$K$16)/SQRT(SUMSQ('Slider Links'!$G$12:$K$12)*SUMSQ('Slider Links'!$G$16:$K$16)),0) -> 0.72792573 | Q12: =IFERROR(SUMPRODUCT('Slider Links'!$G$12:$K$12,'Slider Links'!$G$17:$K$17)/SQRT(SUMSQ('Slider Links'!$G$12:$K$12)*SUMSQ('Slider Links'!$G$17:$K$17)),0) -> 0.63015177
A13: ='Slider Links'!A13 -> Nature | B13: =IFERROR(SUMPRODUCT('Slider Links'!$G$13:$K$13,'Slider Links'!$G$2:$K$2)/SQRT(SUMSQ('Slider Links'!$G$13:$K$13)*SUMSQ('Slider Links'!$G$2:$K$2)),0) -> 0.57927436 | C13: =IFERROR(SUMPRODUCT('Slider Links'!$G$13:$K$13,'Slider Links'!$G$3:$K$3)/SQRT(SUMSQ('Slider Links'!$G$13:$K$13)*SUMSQ('Slider Links'!$G$3:$K$3)),0) -> 0 | D13: =IFERROR(SUMPRODUCT('Slider Links'!$G$13:$K$13,'Slider Links'!$G$4:$K$4)/SQRT(SUMSQ('Slider Links'!$G$13:$K$13)*SUMSQ('Slider Links'!$G$4:$K$4)),0) -> 0.53515468 | E13: =IFERROR(SUMPRODUCT('Slider Links'!$G$13:$K$13,'Slider Links'!$G$5:$K$5)/SQRT(SUMSQ('Slider Links'!$G$13:$K$13)*SUMSQ('Slider Links'!$G$5:$K$5)),0) -> 0.2296677 | F13: =IFERROR(SUMPRODUCT('Slider Links'!$G$13:$K$13,'Slider Links'!$G$6:$K$6)/SQRT(SUMSQ('Slider Links'!$G$13:$K$13)*SUMSQ('Slider Links'!$G$6:$K$6)),0) -> -0.066597331 | G13: =IFERROR(SUMPRODUCT('Slider Links'!$G$13:$K$13,'Slider Links'!$G$7:$K$7)/SQRT(SUMSQ('Slider Links'!$G$13:$K$13)*SUMSQ('Slider Links'!$G$7:$K$7)),0) -> -0.066951981 | H13: =IFERROR(SUMPRODUCT('Slider Links'!$G$13:$K$13,'Slider Links'!$G$8:$K$8)/SQRT(SUMSQ('Slider Links'!$G$13:$K$13)*SUMSQ('Slider Links'!$G$8:$K$8)),0) -> -0.41809677 | I13: =IFERROR(SUMPRODUCT('Slider Links'!$G$13:$K$13,'Slider Links'!$G$9:$K$9)/SQRT(SUMSQ('Slider Links'!$G$13:$K$13)*SUMSQ('Slider Links'!$G$9:$K$9)),0) -> 0.25051013 | J13: =IFERROR(SUMPRODUCT('Slider Links'!$G$13:$K$13,'Slider Links'!$G$10:$K$10)/SQRT(SUMSQ('Slider Links'!$G$13:$K$13)*SUMSQ('Slider Links'!$G$10:$K$10)),0) -> 0.6570092 | K13: =IFERROR(SUMPRODUCT('Slider Links'!$G$13:$K$13,'Slider Links'!$G$11:$K$11)/SQRT(SUMSQ('Slider Links'!$G$13:$K$13)*SUMSQ('Slider Links'!$G$11:$K$11)),0) -> 0.94209196 | L13: =IFERROR(SUMPRODUCT('Slider Links'!$G$13:$K$13,'Slider Links'!$G$12:$K$12)/SQRT(SUMSQ('Slider Links'!$G$13:$K$13)*SUMSQ('Slider Links'!$G$12:$K$12)),0) -> -0.72835704 | M13: =IFERROR(SUMPRODUCT('Slider Links'!$G$13:$K$13,'Slider Links'!$G$13:$K$13)/SQRT(SUMSQ('Slider Links'!$G$13:$K$13)*SUMSQ('Slider Links'!$G$13:$K$13)),0) -> 1 | N13: =IFERROR(SUMPRODUCT('Slider Links'!$G$13:$K$13,'Slider Links'!$G$14:$K$14)/SQRT(SUMSQ('Slider Links'!$G$13:$K$13)*SUMSQ('Slider Links'!$G$14:$K$14)),0) -> 0.23635715 | O13: =IFERROR(SUMPRODUCT('Slider Links'!$G$13:$K$13,'Slider Links'!$G$15:$K$15)/SQRT(SUMSQ('Slider Links'!$G$13:$K$13)*SUMSQ('Slider Links'!$G$15:$K$15)),0) -> -0.45475032 | P13: =IFERROR(SUMPRODUCT('Slider Links'!$G$13:$K$13,'Slider Links'!$G$16:$K$16)/SQRT(SUMSQ('Slider Links'!$G$13:$K$13)*SUMSQ('Slider Links'!$G$16:$K$16)),0) -> -0.56481447 | Q13: =IFERROR(SUMPRODUCT('Slider Links'!$G$13:$K$13,'Slider Links'!$G$17:$K$17)/SQRT(SUMSQ('Slider Links'!$G$13:$K$13)*SUMSQ('Slider Links'!$G$17:$K$17)),0) -> -0.70891756
A14: ='Slider Links'!A14 -> Light | B14: =IFERROR(SUMPRODUCT('Slider Links'!$G$14:$K$14,'Slider Links'!$G$2:$K$2)/SQRT(SUMSQ('Slider Links'!$G$14:$K$14)*SUMSQ('Slider Links'!$G$2:$K$2)),0) -> 0.22085197 | C14: =IFERROR(SUMPRODUCT('Slider Links'!$G$14:$K$14,'Slider Links'!$G$3:$K$3)/SQRT(SUMSQ('Slider Links'!$G$14:$K$14)*SUMSQ('Slider Links'!$G$3:$K$3)),0) -> 0.7832934 | D14: =IFERROR(SUMPRODUCT('Slider Links'!$G$14:$K$14,'Slider Links'!$G$4:$K$4)/SQRT(SUMSQ('Slider Links'!$G$14:$K$14)*SUMSQ('Slider Links'!$G$4:$K$4)),0) -> -0.31532074 | E14: =IFERROR(SUMPRODUCT('Slider Links'!$G$14:$K$14,'Slider Links'!$G$5:$K$5)/SQRT(SUMSQ('Slider Links'!$G$14:$K$14)*SUMSQ('Slider Links'!$G$5:$K$5)),0) -> 0.34916797 | F14: =IFERROR(SUMPRODUCT('Slider Links'!$G$14:$K$14,'Slider Links'!$G$6:$K$6)/SQRT(SUMSQ('Slider Links'!$G$14:$K$14)*SUMSQ('Slider Links'!$G$6:$K$6)),0) -> 0.91124216 | G14: =IFERROR(SUMPRODUCT('Slider Links'!$G$14:$K$14,'Slider Links'!$G$7:$K$7)/SQRT(SUMSQ('Slider Links'!$G$14:$K$14)*SUMSQ('Slider Links'!$G$7:$K$7)),0) -> -0.42143932 | H14: =IFERROR(SUMPRODUCT('Slider Links'!$G$14:$K$14,'Slider Links'!$G$8:$K$8)/SQRT(SUMSQ('Slider Links'!$G$14:$K$14)*SUMSQ('Slider Links'!$G$8:$K$8)),0) -> -0.75990056 | I14: =IFERROR(SUMPRODUCT('Slider Links'!$G$14:$K$14,'Slider Links'!$G$9:$K$9)/SQRT(SUMSQ('Slider Links'!$G$14:$K$14)*SUMSQ('Slider Links'!$G$9:$K$9)),0) -> -0.13293003 | J14: =IFERROR(SUMPRODUCT('Slider Links'!$G$14:$K$14,'Slider Links'!$G$10:$K$10)/SQRT(SUMSQ('Slider Links'!$G$14:$K$14)*SUMSQ('Slider Links'!$G$10:$K$10)),0) -> 0.2150662 | K14: =IFERROR(SUMPRODUCT('Slider Links'!$G$14:$K$14,'Slider Links'!$G$11:$K$11)/SQRT(SUMSQ('Slider Links'!$G$14:$K$14)*SUMSQ('Slider Links'!$G$11:$K$11)),0) -> 0.45971352 | L14: =IFERROR(SUMPRODUCT('Slider Links'!$G$14:$K$14,'Slider Links'!$G$12:$K$12)/SQRT(SUMSQ('Slider Links'!$G$14:$K$14)*SUMSQ('Slider Links'!$G$12:$K$12)),0) -> -0.68538172 | M14: =IFERROR(SUMPRODUCT('Slider Links'!$G$14:$K$14,'Slider Links'!$G$13:$K$13)/SQRT(SUMSQ('Slider Links'!$G$14:$K$14)*SUMSQ('Slider Links'!$G$13:$K$13)),0) -> 0.23635715 | N14: =IFERROR(SUMPRODUCT('Slider Links'!$G$14:$K$14,'Slider Links'!$G$14:$K$14)/SQRT(SUMSQ('Slider Links'!$G$14:$K$14)*SUMSQ('Slider Links'!$G$14:$K$14)),0) -> 1 | O14: =IFERROR(SUMPRODUCT('Slider Links'!$G$14:$K$14,'Slider Links'!$G$15:$K$15)/SQRT(SUMSQ('Slider Links'!$G$14:$K$14)*SUMSQ('Slider Links'!$G$15:$K$15)),0) -> -0.23116854 | P14: =IFERROR(SUMPRODUCT('Slider Links'!$G$14:$K$14,'Slider Links'!$G$16:$K$16)/SQRT(SUMSQ('Slider Links'!$G$14:$K$14)*SUMSQ('Slider Links'!$G$16:$K$16)),0) -> -0.54233538 | Q14: =IFERROR(SUMPRODUCT('Slider Links'!$G$14:$K$14,'Slider Links'!$G$17:$K$17)/SQRT(SUMSQ('Slider Links'!$G$14:$K$14)*SUMSQ('Slider Links'!$G$17:$K$17)),0) -> -0.22227046
A15: ='Slider Links'!A15 -> Dream | B15: =IFERROR(SUMPRODUCT('Slider Links'!$G$15:$K$15,'Slider Links'!$G$2:$K$2)/SQRT(SUMSQ('Slider Links'!$G$15:$K$15)*SUMSQ('Slider Links'!$G$2:$K$2)),0) -> -0.17774365 | C15: =IFERROR(SUMPRODUCT('Slider Links'!$G$15:$K$15,'Slider Links'!$G$3:$K$3)/SQRT(SUMSQ('Slider Links'!$G$15:$K$15)*SUMSQ('Slider Links'!$G$3:$K$3)),0) -> -0.11397885 | D15: =IFERROR(SUMPRODUCT('Slider Links'!$G$15:$K$15,'Slider Links'!$G$4:$K$4)/SQRT(SUMSQ('Slider Links'!$G$15:$K$15)*SUMSQ('Slider Links'!$G$4:$K$4)),0) -> -0.78246663 | E15: =IFERROR(SUMPRODUCT('Slider Links'!$G$15:$K$15,'Slider Links'!$G$5:$K$5)/SQRT(SUMSQ('Slider Links'!$G$15:$K$15)*SUMSQ('Slider Links'!$G$5:$K$5)),0) -> 0.066555833 | F15: =IFERROR(SUMPRODUCT('Slider Links'!$G$15:$K$15,'Slider Links'!$G$6:$K$6)/SQRT(SUMSQ('Slider Links'!$G$15:$K$15)*SUMSQ('Slider Links'!$G$6:$K$6)),0) -> -0.014474524 | G15: =IFERROR(SUMPRODUCT('Slider Links'!$G$15:$K$15,'Slider Links'!$G$7:$K$7)/SQRT(SUMSQ('Slider Links'!$G$15:$K$15)*SUMSQ('Slider Links'!$G$7:$K$7)),0) -> -0.36217328 | H15: =IFERROR(SUMPRODUCT('Slider Links'!$G$15:$K$15,'Slider Links'!$G$8:$K$8)/SQRT(SUMSQ('Slider Links'!$G$15:$K$15)*SUMSQ('Slider Links'!$G$8:$K$8)),0) -> 0.76591088 | I15: =IFERROR(SUMPRODUCT('Slider Links'!$G$15:$K$15,'Slider Links'!$G$9:$K$9)/SQRT(SUMSQ('Slider Links'!$G$15:$K$15)*SUMSQ('Slider Links'!$G$9:$K$9)),0) -> -0.91699956 | J15: =IFERROR(SUMPRODUCT('Slider Links'!$G$15:$K$15,'Slider Links'!$G$10:$K$10)/SQRT(SUMSQ('Slider Links'!$G$15:$K$15)*SUMSQ('Slider Links'!$G$10:$K$10)),0) -> -0.24664927 | K15: =IFERROR(SUMPRODUCT('Slider Links'!$G$15:$K$15,'Slider Links'!$G$11:$K$11)/SQRT(SUMSQ('Slider Links'!$G$15:$K$15)*SUMSQ('Slider Links'!$G$11:$K$11)),0) -> -0.34909551 | L15: =IFERROR(SUMPRODUCT('Slider Links'!$G$15:$K$15,'Slider Links'!$G$12:$K$12)/SQRT(SUMSQ('Slider Links'!$G$15:$K$15)*SUMSQ('Slider Links'!$G$12:$K$12)),0) -> 0.075985902 | M15: =IFERROR(SUMPRODUCT('Slider Links'!$G$15:$K$15,'Slider Links'!$G$13:$K$13)/SQRT(SUMSQ('Slider Links'!$G$15:$K$15)*SUMSQ('Slider Links'!$G$13:$K$13)),0) -> -0.45475032 | N15: =IFERROR(SUMPRODUCT('Slider Links'!$G$15:$K$15,'Slider Links'!$G$14:$K$14)/SQRT(SUMSQ('Slider Links'!$G$15:$K$15)*SUMSQ('Slider Links'!$G$14:$K$14)),0) -> -0.23116854 | O15: =IFERROR(SUMPRODUCT('Slider Links'!$G$15:$K$15,'Slider Links'!$G$15:$K$15)/SQRT(SUMSQ('Slider Links'!$G$15:$K$15)*SUMSQ('Slider Links'!$G$15:$K$15)),0) -> 1 | P15: =IFERROR(SUMPRODUCT('Slider Links'!$G$15:$K$15,'Slider Links'!$G$16:$K$16)/SQRT(SUMSQ('Slider Links'!$G$15:$K$15)*SUMSQ('Slider Links'!$G$16:$K$16)),0) -> 0.095479208 | Q15: =IFERROR(SUMPRODUCT('Slider Links'!$G$15:$K$15,'Slider Links'!$G$17:$K$17)/SQRT(SUMSQ('Slider Links'!$G$15:$K$15)*SUMSQ('Slider Links'!$G$17:$K$17)),0) -> 0.11320083
A16: ='Slider Links'!A16 -> Poison | B16: =IFERROR(SUMPRODUCT('Slider Links'!$G$16:$K$16,'Slider Links'!$G$2:$K$2)/SQRT(SUMSQ('Slider Links'!$G$16:$K$16)*SUMSQ('Slider Links'!$G$2:$K$2)),0) -> 0.01737489 | C16: =IFERROR(SUMPRODUCT('Slider Links'!$G$16:$K$16,'Slider Links'!$G$3:$K$3)/SQRT(SUMSQ('Slider Links'!$G$16:$K$16)*SUMSQ('Slider Links'!$G$3:$K$3)),0) -> -0.20055097 | D16: =IFERROR(SUMPRODUCT('Slider Links'!$G$16:$K$16,'Slider Links'!$G$4:$K$4)/SQRT(SUMSQ('Slider Links'!$G$16:$K$16)*SUMSQ('Slider Links'!$G$4:$K$4)),0) -> 0.03721042 | E16: =IFERROR(SUMPRODUCT('Slider Links'!$G$16:$K$16,'Slider Links'!$G$5:$K$5)/SQRT(SUMSQ('Slider Links'!$G$16:$K$16)*SUMSQ('Slider Links'!$G$5:$K$5)),0) -> 0.23421602 | F16: =IFERROR(SUMPRODUCT('Slider Links'!$G$16:$K$16,'Slider Links'!$G$6:$K$6)/SQRT(SUMSQ('Slider Links'!$G$16:$K$16)*SUMSQ('Slider Links'!$G$6:$K$6)),0) -> -0.26317534 | G16: =IFERROR(SUMPRODUCT('Slider Links'!$G$16:$K$16,'Slider Links'!$G$7:$K$7)/SQRT(SUMSQ('Slider Links'!$G$16:$K$16)*SUMSQ('Slider Links'!$G$7:$K$7)),0) -> 0.083450757 | H16: =IFERROR(SUMPRODUCT('Slider Links'!$G$16:$K$16,'Slider Links'!$G$8:$K$8)/SQRT(SUMSQ('Slider Links'!$G$16:$K$16)*SUMSQ('Slider Links'!$G$8:$K$8)),0) -> 0.52535702 | I16: =IFERROR(SUMPRODUCT('Slider Links'!$G$16:$K$16,'Slider Links'!$G$9:$K$9)/SQRT(SUMSQ('Slider Links'!$G$16:$K$16)*SUMSQ('Slider Links'!$G$9:$K$9)),0) -> 0.18824194 | J16: =IFERROR(SUMPRODUCT('Slider Links'!$G$16:$K$16,'Slider Links'!$G$10:$K$10)/SQRT(SUMSQ('Slider Links'!$G$16:$K$16)*SUMSQ('Slider Links'!$G$10:$K$10)),0) -> 0.083752569 | K16: =IFERROR(SUMPRODUCT('Slider Links'!$G$16:$K$16,'Slider Links'!$G$11:$K$11)/SQRT(SUMSQ('Slider Links'!$G$16:$K$16)*SUMSQ('Slider Links'!$G$11:$K$11)),0) -> -0.59849942 | L16: =IFERROR(SUMPRODUCT('Slider Links'!$G$16:$K$16,'Slider Links'!$G$12:$K$12)/SQRT(SUMSQ('Slider Links'!$G$16:$K$16)*SUMSQ('Slider Links'!$G$12:$K$12)),0) -> 0.72792573 | M16: =IFERROR(SUMPRODUCT('Slider Links'!$G$16:$K$16,'Slider Links'!$G$13:$K$13)/SQRT(SUMSQ('Slider Links'!$G$16:$K$16)*SUMSQ('Slider Links'!$G$13:$K$13)),0) -> -0.56481447 | N16: =IFERROR(SUMPRODUCT('Slider Links'!$G$16:$K$16,'Slider Links'!$G$14:$K$14)/SQRT(SUMSQ('Slider Links'!$G$16:$K$16)*SUMSQ('Slider Links'!$G$14:$K$14)),0) -> -0.54233538 | O16: =IFERROR(SUMPRODUCT('Slider Links'!$G$16:$K$16,'Slider Links'!$G$15:$K$15)/SQRT(SUMSQ('Slider Links'!$G$16:$K$16)*SUMSQ('Slider Links'!$G$15:$K$15)),0) -> 0.095479208 | P16: =IFERROR(SUMPRODUCT('Slider Links'!$G$16:$K$16,'Slider Links'!$G$16:$K$16)/SQRT(SUMSQ('Slider Links'!$G$16:$K$16)*SUMSQ('Slider Links'!$G$16:$K$16)),0) -> 1 | Q16: =IFERROR(SUMPRODUCT('Slider Links'!$G$16:$K$16,'Slider Links'!$G$17:$K$17)/SQRT(SUMSQ('Slider Links'!$G$16:$K$16)*SUMSQ('Slider Links'!$G$17:$K$17)),0) -> 0.92213889
A17: ='Slider Links'!A17 -> Disease | B17: =IFERROR(SUMPRODUCT('Slider Links'!$G$17:$K$17,'Slider Links'!$G$2:$K$2)/SQRT(SUMSQ('Slider Links'!$G$17:$K$17)*SUMSQ('Slider Links'!$G$2:$K$2)),0) -> -0.064088246 | C17: =IFERROR(SUMPRODUCT('Slider Links'!$G$17:$K$17,'Slider Links'!$G$3:$K$3)/SQRT(SUMSQ('Slider Links'!$G$17:$K$17)*SUMSQ('Slider Links'!$G$3:$K$3)),0) -> 0.11644109 | D17: =IFERROR(SUMPRODUCT('Slider Links'!$G$17:$K$17,'Slider Links'!$G$4:$K$4)/SQRT(SUMSQ('Slider Links'!$G$17:$K$17)*SUMSQ('Slider Links'!$G$4:$K$4)),0) -> -0.19444133 | E17: =IFERROR(SUMPRODUCT('Slider Links'!$G$17:$K$17,'Slider Links'!$G$5:$K$5)/SQRT(SUMSQ('Slider Links'!$G$17:$K$17)*SUMSQ('Slider Links'!$G$5:$K$5)),0) -> 0.28797293 | F17: =IFERROR(SUMPRODUCT('Slider Links'!$G$17:$K$17,'Slider Links'!$G$6:$K$6)/SQRT(SUMSQ('Slider Links'!$G$17:$K$17)*SUMSQ('Slider Links'!$G$6:$K$6)),0) -> 0.1017708 | G17: =IFERROR(SUMPRODUCT('Slider Links'!$G$17:$K$17,'Slider Links'!$G$7:$K$7)/SQRT(SUMSQ('Slider Links'!$G$17:$K$17)*SUMSQ('Slider Links'!$G$7:$K$7)),0) -> -0.083948933 | H17: =IFERROR(SUMPRODUCT('Slider Links'!$G$17:$K$17,'Slider Links'!$G$8:$K$8)/SQRT(SUMSQ('Slider Links'!$G$17:$K$17)*SUMSQ('Slider Links'!$G$8:$K$8)),0) -> 0.32998914 | I17: =IFERROR(SUMPRODUCT('Slider Links'!$G$17:$K$17,'Slider Links'!$G$9:$K$9)/SQRT(SUMSQ('Slider Links'!$G$17:$K$17)*SUMSQ('Slider Links'!$G$9:$K$9)),0) -> 0.086792607 | J17: =IFERROR(SUMPRODUCT('Slider Links'!$G$17:$K$17,'Slider Links'!$G$10:$K$10)/SQRT(SUMSQ('Slider Links'!$G$17:$K$17)*SUMSQ('Slider Links'!$G$10:$K$10)),0) -> 0.0070210455 | K17: =IFERROR(SUMPRODUCT('Slider Links'!$G$17:$K$17,'Slider Links'!$G$11:$K$11)/SQRT(SUMSQ('Slider Links'!$G$17:$K$17)*SUMSQ('Slider Links'!$G$11:$K$11)),0) -> -0.63904163 | L17: =IFERROR(SUMPRODUCT('Slider Links'!$G$17:$K$17,'Slider Links'!$G$12:$K$12)/SQRT(SUMSQ('Slider Links'!$G$17:$K$17)*SUMSQ('Slider Links'!$G$12:$K$12)),0) -> 0.63015177 | M17: =IFERROR(SUMPRODUCT('Slider Links'!$G$17:$K$17,'Slider Links'!$G$13:$K$13)/SQRT(SUMSQ('Slider Links'!$G$17:$K$17)*SUMSQ('Slider Links'!$G$13:$K$13)),0) -> -0.70891756 | N17: =IFERROR(SUMPRODUCT('Slider Links'!$G$17:$K$17,'Slider Links'!$G$14:$K$14)/SQRT(SUMSQ('Slider Links'!$G$17:$K$17)*SUMSQ('Slider Links'!$G$14:$K$14)),0) -> -0.22227046 | O17: =IFERROR(SUMPRODUCT('Slider Links'!$G$17:$K$17,'Slider Links'!$G$15:$K$15)/SQRT(SUMSQ('Slider Links'!$G$17:$K$17)*SUMSQ('Slider Links'!$G$15:$K$15)),0) -> 0.11320083 | P17: =IFERROR(SUMPRODUCT('Slider Links'!$G$17:$K$17,'Slider Links'!$G$16:$K$16)/SQRT(SUMSQ('Slider Links'!$G$17:$K$17)*SUMSQ('Slider Links'!$G$16:$K$16)),0) -> 0.92213889 | Q17: =IFERROR(SUMPRODUCT('Slider Links'!$G$17:$K$17,'Slider Links'!$G$17:$K$17)/SQRT(SUMSQ('Slider Links'!$G$17:$K$17)*SUMSQ('Slider Links'!$G$17:$K$17)),0) -> 1
A19: Refuse below | B19: -0.7
A20: Weaken below | B20: 0
A21: Pairs that refuse | B21: =COUNTIF($B$2:$Q$17,"<"&$B$19)/2 -> 7
A22: Pairs weakened | B22: =(COUNTIF($B$2:$Q$17,"<"&$B$20)-COUNTIF($B$2:$Q$17,"<"&$B$19))/2 -> 50
A24: Each cell is how well two affinities line up (the cosine of their five positions): +1 the same way, -1 opposite. Red: they refuse to bond. Amber: they bond, weakened. Green: they bond, strengthened. Universal runes have no position and bond with anything. Move the sliders on the Affinities sheet; change the two thresholds in yellow.

Sheet Base Runes
A1: ID | B1: Affinity | C1: Pair | D1: Rune | E1: Character | F1: Opposite ID | G1: Opposite | H1: Opposite character | I1: As a skill (from the affinity sheet) | J1: Code point as first assigned | K1: Role | L1: Draw (-1 gives ... +1 takes) | M1: Valence | N1: Electronegativity | O1: Effect (game)
A2: WAT-1a | B2: Water | C2: 1 | D2: Flood | E2: ᚠ | F2: WAT-1b | G2: =IFERROR(INDEX($D:$D,MATCH($F2,$A:$A,0)),"") -> Drain | H2: =IFERROR(INDEX($E:$E,MATCH($F2,$A:$A,0)),"") -> ᚡ | I2: =Water!$E$6 -> fill an area with water; the ground turns Wet | J2: U+16A0 | K2: Branch | L2: -0.6 | M2: =IFERROR(INDEX('Bond Rules'!$B$4:$B$7,MATCH(K2,'Bond Rules'!$A$4:$A$7,0)),"") -> 3 | N2: =IFERROR(ROUND('Bond Rules'!$B$9+L2*INDEX('Bond Rules'!$C$4:$C$7,MATCH(K2,'Bond Rules'!$A$4:$A$7,0)),2),"") -> 2.08 | O2: reach x1.2; status soaked
A3: WAT-1b | B3: Water | C3: 1 | D3: Drain | E3: ᚡ | F3: WAT-1a | G3: =IFERROR(INDEX($D:$D,MATCH($F3,$A:$A,0)),"") -> Flood | H3: =IFERROR(INDEX($E:$E,MATCH($F3,$A:$A,0)),"") -> ᚠ | I3: =Water!$E$7 -> empty the water from an area or a target, and draw it in | J3: U+16A1 | K3: Link | L3: 0.6 | M3: =IFERROR(INDEX('Bond Rules'!$B$4:$B$7,MATCH(K3,'Bond Rules'!$A$4:$A$7,0)),"") -> 2 | N3: =IFERROR(ROUND('Bond Rules'!$B$9+L3*INDEX('Bond Rules'!$C$4:$C$7,MATCH(K3,'Bond Rules'!$A$4:$A$7,0)),2),"") -> 3.1 | O3: bonus soaked +0.25; cost x0.9
A4: WAT-2a | B4: Water | C4: 2 | D4: Surge | E4: ᚢ | F4: WAT-2b | G4: =IFERROR(INDEX($D:$D,MATCH($F4,$A:$A,0)),"") -> Ebb | H4: =IFERROR(INDEX($E:$E,MATCH($F4,$A:$A,0)),"") -> ᚣ | I4: =Water!$E$8 -> push bodies away | J4: U+16A2 | K4: Link | L4: -0.6 | M4: =IFERROR(INDEX('Bond Rules'!$B$4:$B$7,MATCH(K4,'Bond Rules'!$A$4:$A$7,0)),"") -> 2 | N4: =IFERROR(ROUND('Bond Rules'!$B$9+L4*INDEX('Bond Rules'!$C$4:$C$7,MATCH(K4,'Bond Rules'!$A$4:$A$7,0)),2),"") -> 1.9 | O4: shove +1.5
A5: WAT-2b | B5: Water | C5: 2 | D5: Ebb | E5: ᚣ | F5: WAT-2a | G5: =IFERROR(INDEX($D:$D,MATCH($F5,$A:$A,0)),"") -> Surge | H5: =IFERROR(INDEX($E:$E,MATCH($F5,$A:$A,0)),"") -> ᚢ | I5: =Water!$E$9 -> draw bodies in | J5: U+16A3 | K5: Link | L5: 0.6 | M5: =IFERROR(INDEX('Bond Rules'!$B$4:$B$7,MATCH(K5,'Bond Rules'!$A$4:$A$7,0)),"") -> 2 | N5: =IFERROR(ROUND('Bond Rules'!$B$9+L5*INDEX('Bond Rules'!$C$4:$C$7,MATCH(K5,'Bond Rules'!$A$4:$A$7,0)),2),"") -> 3.1 | O5: pull +1.5
A6: WAT-3a | B6: Water | C6: 3 | D6: Soak | E6: ᚤ | F6: WAT-3b | G6: =IFERROR(INDEX($D:$D,MATCH($F6,$A:$A,0)),"") -> Dry | H6: =IFERROR(INDEX($E:$E,MATCH($F6,$A:$A,0)),"") -> ᚥ | I6: =Water!$E$10 -> saturate a target | J6: U+16A4 | K6: Link | L6: -0.5 | M6: =IFERROR(INDEX('Bond Rules'!$B$4:$B$7,MATCH(K6,'Bond Rules'!$A$4:$A$7,0)),"") -> 2 | N6: =IFERROR(ROUND('Bond Rules'!$B$9+L6*INDEX('Bond Rules'!$C$4:$C$7,MATCH(K6,'Bond Rules'!$A$4:$A$7,0)),2),"") -> 2 | O6: status soaked
A7: WAT-3b | B7: Water | C7: 3 | D7: Dry | E7: ᚥ | F7: WAT-3a | G7: =IFERROR(INDEX($D:$D,MATCH($F7,$A:$A,0)),"") -> Soak | H7: =IFERROR(INDEX($E:$E,MATCH($F7,$A:$A,0)),"") -> ᚤ | I7: =Water!$E$11 -> pull the water out of a body: damage by how wet it is | J7: U+16A5 | K7: Cap | L7: 0.8 | M7: =IFERROR(INDEX('Bond Rules'!$B$4:$B$7,MATCH(K7,'Bond Rules'!$A$4:$A$7,0)),"") -> 1 | N7: =IFERROR(ROUND('Bond Rules'!$B$9+L7*INDEX('Bond Rules'!$C$4:$C$7,MATCH(K7,'Bond Rules'!$A$4:$A$7,0)),2),"") -> 3.7 | O7: bonus soaked +0.4
A8: WAT-4a | B8: Water | C8: 4 | D8: Float | E8: ᚦ | F8: WAT-4b | G8: =IFERROR(INDEX($D:$D,MATCH($F8,$A:$A,0)),"") -> Drown | H8: =IFERROR(INDEX($E:$E,MATCH($F8,$A:$A,0)),"") -> ᚧ | I8: =Water!$E$12 -> buoyancy: lift, lighten, walk on water | J8: U+16A6 | K8: Link | L8: -0.5 | M8: =IFERROR(INDEX('Bond Rules'!$B$4:$B$7,MATCH(K8,'Bond Rules'!$A$4:$A$7,0)),"") -> 2 | N8: =IFERROR(ROUND('Bond Rules'!$B$9+L8*INDEX('Bond Rules'!$C$4:$C$7,MATCH(K8,'Bond Rules'!$A$4:$A$7,0)),2),"") -> 2 | O8: status aloft
A9: WAT-4b | B9: Water | C9: 4 | D9: Drown | E9: ᚧ | F9: WAT-4a | G9: =IFERROR(INDEX($D:$D,MATCH($F9,$A:$A,0)),"") -> Float | H9: =IFERROR(INDEX($E:$E,MATCH($F9,$A:$A,0)),"") -> ᚦ | I9: =Water!$E$13 -> water in the lungs: no casting, no calls for help, damage over time | J9: U+16A7 | K9: Cap | L9: 0.9 | M9: =IFERROR(INDEX('Bond Rules'!$B$4:$B$7,MATCH(K9,'Bond Rules'!$A$4:$A$7,0)),"") -> 1 | N9: =IFERROR(ROUND('Bond Rules'!$B$9+L9*INDEX('Bond Rules'!$C$4:$C$7,MATCH(K9,'Bond Rules'!$A$4:$A$7,0)),2),"") -> 3.85 | O9: interrupts; status dazed
A10: WAT-5a | B10: Water | C10: 5 | D10: Gush | E10: ᚨ | F10: WAT-5b | G10: =IFERROR(INDEX($D:$D,MATCH($F10,$A:$A,0)),"") -> Drip | H10: =IFERROR(INDEX($E:$E,MATCH($F10,$A:$A,0)),"") -> ᚩ | I10: =Water!$E$14 -> a sudden forceful jet | J10: U+16A8 | K10: Link | L10: -0.8 | M10: =IFERROR(INDEX('Bond Rules'!$B$4:$B$7,MATCH(K10,'Bond Rules'!$A$4:$A$7,0)),"") -> 2 | N10: =IFERROR(ROUND('Bond Rules'!$B$9+L10*INDEX('Bond Rules'!$C$4:$C$7,MATCH(K10,'Bond Rules'!$A$4:$A$7,0)),2),"") -> 1.7 | O10: speed x1.3; power x1.1
A11: WAT-5b | B11: Water | C11: 5 | D11: Drip | E11: ᚩ | F11: WAT-5a | G11: =IFERROR(INDEX($D:$D,MATCH($F11,$A:$A,0)),"") -> Gush | H11: =IFERROR(INDEX($E:$E,MATCH($F11,$A:$A,0)),"") -> ᚨ | I11: =Water!$E$15 -> a slow steady trickle that wears and lingers | J11: U+16A9 | K11: Link | L11: 0.3 | M11: =IFERROR(INDEX('Bond Rules'!$B$4:$B$7,MATCH(K11,'Bond Rules'!$A$4:$A$7,0)),"") -> 2 | N11: =IFERROR(ROUND('Bond Rules'!$B$9+L11*INDEX('Bond Rules'!$C$4:$C$7,MATCH(K11,'Bond Rules'!$A$4:$A$7,0)),2),"") -> 2.8 | O11: duration x1.4; cost x0.85
A12: WAT-6a | B12: Water | C12: 6 | D12: Sweep | E12: ᚪ | F12: WAT-6b | G12: =IFERROR(INDEX($D:$D,MATCH($F12,$A:$A,0)),"") -> Settle | H12: =IFERROR(INDEX($E:$E,MATCH($F12,$A:$A,0)),"") -> ᚫ | I12: =Water!$E$16 -> a current that carries things along | J12: U+16AA | K12: Link | L12: -0.4 | M12: =IFERROR(INDEX('Bond Rules'!$B$4:$B$7,MATCH(K12,'Bond Rules'!$A$4:$A$7,0)),"") -> 2 | N12: =IFERROR(ROUND('Bond Rules'!$B$9+L12*INDEX('Bond Rules'!$C$4:$C$7,MATCH(K12,'Bond Rules'!$A$4:$A$7,0)),2),"") -> 2.1 | O12: reach x1.3
A13: WAT-6b | B13: Water | C13: 6 | D13: Settle | E13: ᚫ | F13: WAT-6a | G13: =IFERROR(INDEX($D:$D,MATCH($F13,$A:$A,0)),"") -> Sweep | H13: =IFERROR(INDEX($E:$E,MATCH($F13,$A:$A,0)),"") -> ᚪ | I13: =Water!$E$17 -> the water goes still, and what it carries sinks and stays | J13: U+16AB | K13: Frame | L13: 0.4 | M13: =IFERROR(INDEX('Bond Rules'!$B$4:$B$7,MATCH(K13,'Bond Rules'!$A$4:$A$7,0)),"") -> 4 | N13: =IFERROR(ROUND('Bond Rules'!$B$9+L13*INDEX('Bond Rules'!$C$4:$C$7,MATCH(K13,'Bond Rules'!$A$4:$A$7,0)),2),"") -> 2.66 | O13: status mired
A14: WAT-7a | B14: Water | C14: 7 | D14: Splash | E14: ᚬ | F14: WAT-7b | G14: =IFERROR(INDEX($D:$D,MATCH($F14,$A:$A,0)),"") -> Seep | H14: =IFERROR(INDEX($E:$E,MATCH($F14,$A:$A,0)),"") -> ᚭ | I14: =Water!$E$18 -> burst outward on contact, spraying those near | J14: U+16AC | K14: Branch | L14: -0.7 | M14: =IFERROR(INDEX('Bond Rules'!$B$4:$B$7,MATCH(K14,'Bond Rules'!$A$4:$A$7,0)),"") -> 3 | N14: =IFERROR(ROUND('Bond Rules'!$B$9+L14*INDEX('Bond Rules'!$C$4:$C$7,MATCH(K14,'Bond Rules'!$A$4:$A$7,0)),2),"") -> 2.01 | O14: reach x1.25; power x0.9
A15: WAT-7b | B15: Water | C15: 7 | D15: Seep | E15: ᚭ | F15: WAT-7a | G15: =IFERROR(INDEX($D:$D,MATCH($F15,$A:$A,0)),"") -> Splash | H15: =IFERROR(INDEX($E:$E,MATCH($F15,$A:$A,0)),"") -> ᚬ | I15: =Water!$E$19 -> soak in slowly, getting behind shields and armour | J15: U+16AD | K15: Link | L15: 0.4 | M15: =IFERROR(INDEX('Bond Rules'!$B$4:$B$7,MATCH(K15,'Bond Rules'!$A$4:$A$7,0)),"") -> 2 | N15: =IFERROR(ROUND('Bond Rules'!$B$9+L15*INDEX('Bond Rules'!$C$4:$C$7,MATCH(K15,'Bond Rules'!$A$4:$A$7,0)),2),"") -> 2.9 | O15: pierce +1
A16: WAT-8a | B16: Water | C16: 8 | D16: Wave | E16: ᚮ | F16: WAT-8b | G16: =IFERROR(INDEX($D:$D,MATCH($F16,$A:$A,0)),"") -> Slack | H16: =IFERROR(INDEX($E:$E,MATCH($F16,$A:$A,0)),"") -> ᚯ | I16: =Water!$E$20 -> a rolling wall of water | J16: U+16AE | K16: Branch | L16: -0.5 | M16: =IFERROR(INDEX('Bond Rules'!$B$4:$B$7,MATCH(K16,'Bond Rules'!$A$4:$A$7,0)),"") -> 3 | N16: =IFERROR(ROUND('Bond Rules'!$B$9+L16*INDEX('Bond Rules'!$C$4:$C$7,MATCH(K16,'Bond Rules'!$A$4:$A$7,0)),2),"") -> 2.15 | O16: reach x1.2; poise x1.3
A17: WAT-8b | B17: Water | C17: 8 | D17: Slack | E17: ᚯ | F17: WAT-8a | G17: =IFERROR(INDEX($D:$D,MATCH($F17,$A:$A,0)),"") -> Wave | H17: =IFERROR(INDEX($E:$E,MATCH($F17,$A:$A,0)),"") -> ᚮ | I17: =Water!$E$21 -> the still moment at the turn of the tide: everything pauses, reflux eases | J17: U+16AF | K17: Cap | L17: 0.5 | M17: =IFERROR(INDEX('Bond Rules'!$B$4:$B$7,MATCH(K17,'Bond Rules'!$A$4:$A$7,0)),"") -> 1 | N17: =IFERROR(ROUND('Bond Rules'!$B$9+L17*INDEX('Bond Rules'!$C$4:$C$7,MATCH(K17,'Bond Rules'!$A$4:$A$7,0)),2),"") -> 3.25 | O17: reflux x0.75
A18: FIR-1a | B18: Fire | C18: 1 | D18: Burn | E18: ᚰ | F18: FIR-1b | G18: =IFERROR(INDEX($D:$D,MATCH($F18,$A:$A,0)),"") -> Quench | H18: =IFERROR(INDEX($E:$E,MATCH($F18,$A:$A,0)),"") -> ᚱ | I18: =Fire!$E$6 -> set a target burning (Alight) | J18: U+16B0 | K18: Link | L18: -0.5 | M18: =IFERROR(INDEX('Bond Rules'!$B$4:$B$7,MATCH(K18,'Bond Rules'!$A$4:$A$7,0)),"") -> 2 | N18: =IFERROR(ROUND('Bond Rules'!$B$9+L18*INDEX('Bond Rules'!$C$4:$C$7,MATCH(K18,'Bond Rules'!$A$4:$A$7,0)),2),"") -> 2 | O18: status alight
A19: FIR-1b | B19: Fire | C19: 1 | D19: Quench | E19: ᚱ | F19: FIR-1a | G19: =IFERROR(INDEX($D:$D,MATCH($F19,$A:$A,0)),"") -> Burn | H19: =IFERROR(INDEX($E:$E,MATCH($F19,$A:$A,0)),"") -> ᚰ | I19: =Fire!$E$7 -> put fire out, and cash the heat in | J19: U+16B1 | K19: Cap | L19: 0.7 | M19: =IFERROR(INDEX('Bond Rules'!$B$4:$B$7,MATCH(K19,'Bond Rules'!$A$4:$A$7,0)),"") -> 1 | N19: =IFERROR(ROUND('Bond Rules'!$B$9+L19*INDEX('Bond Rules'!$C$4:$C$7,MATCH(K19,'Bond Rules'!$A$4:$A$7,0)),2),"") -> 3.55 | O19: reflux x0.7; power x1.1
A20: FIR-2a | B20: Fire | C20: 2 | D20: Ignite | E20: ᚲ | F20: FIR-2b | G20: =IFERROR(INDEX($D:$D,MATCH($F20,$A:$A,0)),"") -> Snuff | H20: =IFERROR(INDEX($E:$E,MATCH($F20,$A:$A,0)),"") -> ᚳ | I20: =Fire!$E$8 -> start a fire at a point | J20: U+16B2 | K20: Link | L20: -0.4 | M20: =IFERROR(INDEX('Bond Rules'!$B$4:$B$7,MATCH(K20,'Bond Rules'!$A$4:$A$7,0)),"") -> 2 | N20: =IFERROR(ROUND('Bond Rules'!$B$9+L20*INDEX('Bond Rules'!$C$4:$C$7,MATCH(K20,'Bond Rules'!$A$4:$A$7,0)),2),"") -> 2.1 | O20: status alight; windup x0.9
A21: FIR-2b | B21: Fire | C21: 2 | D21: Snuff | E21: ᚳ | F21: FIR-2a | G21: =IFERROR(INDEX($D:$D,MATCH($F21,$A:$A,0)),"") -> Ignite | H21: =IFERROR(INDEX($E:$E,MATCH($F21,$A:$A,0)),"") -> ᚲ | I21: =Fire!$E$9 -> put out one flame or source at once | J21: U+16B3 | K21: Cap | L21: 0.6 | M21: =IFERROR(INDEX('Bond Rules'!$B$4:$B$7,MATCH(K21,'Bond Rules'!$A$4:$A$7,0)),"") -> 1 | N21: =IFERROR(ROUND('Bond Rules'!$B$9+L21*INDEX('Bond Rules'!$C$4:$C$7,MATCH(K21,'Bond Rules'!$A$4:$A$7,0)),2),"") -> 3.4 | O21: interrupts
A22: FIR-3a | B22: Fire | C22: 3 | D22: Explode | E22: ᚴ | F22: FIR-3b | G22: =IFERROR(INDEX($D:$D,MATCH($F22,$A:$A,0)),"") -> Implode | H22: =IFERROR(INDEX($E:$E,MATCH($F22,$A:$A,0)),"") -> ᚵ | I22: =Fire!$E$10 -> blast outward | J22: U+16B4 | K22: Branch | L22: -1 | M22: =IFERROR(INDEX('Bond Rules'!$B$4:$B$7,MATCH(K22,'Bond Rules'!$A$4:$A$7,0)),"") -> 3 | N22: =IFERROR(ROUND('Bond Rules'!$B$9+L22*INDEX('Bond Rules'!$C$4:$C$7,MATCH(K22,'Bond Rules'!$A$4:$A$7,0)),2),"") -> 1.8 | O22: reach x1.3; power x1.15; cost x1.15
A23: FIR-3b | B23: Fire | C23: 3 | D23: Implode | E23: ᚵ | F23: FIR-3a | G23: =IFERROR(INDEX($D:$D,MATCH($F23,$A:$A,0)),"") -> Explode | H23: =IFERROR(INDEX($E:$E,MATCH($F23,$A:$A,0)),"") -> ᚴ | I23: =Fire!$E$11 -> flame rushing inward | J23: U+16B5 | K23: Cap | L23: 1 | M23: =IFERROR(INDEX('Bond Rules'!$B$4:$B$7,MATCH(K23,'Bond Rules'!$A$4:$A$7,0)),"") -> 1 | N23: =IFERROR(ROUND('Bond Rules'!$B$9+L23*INDEX('Bond Rules'!$C$4:$C$7,MATCH(K23,'Bond Rules'!$A$4:$A$7,0)),2),"") -> 4 | O23: pull +1.5
A24: FIR-4a | B24: Fire | C24: 4 | D24: Blaze | E24: ᚶ | F24: FIR-4b | G24: =IFERROR(INDEX($D:$D,MATCH($F24,$A:$A,0)),"") -> Smoulder | H24: =IFERROR(INDEX($E:$E,MATCH($F24,$A:$A,0)),"") -> ᚷ | I24: =Fire!$E$12 -> a fierce, spreading fire | J24: U+16B6 | K24: Branch | L24: -0.8 | M24: =IFERROR(INDEX('Bond Rules'!$B$4:$B$7,MATCH(K24,'Bond Rules'!$A$4:$A$7,0)),"") -> 3 | N24: =IFERROR(ROUND('Bond Rules'!$B$9+L24*INDEX('Bond Rules'!$C$4:$C$7,MATCH(K24,'Bond Rules'!$A$4:$A$7,0)),2),"") -> 1.94 | O24: power x1.2; reflux x1.2
A25: FIR-4b | B25: Fire | C25: 4 | D25: Smoulder | E25: ᚷ | F25: FIR-4a | G25: =IFERROR(INDEX($D:$D,MATCH($F25,$A:$A,0)),"") -> Blaze | H25: =IFERROR(INDEX($E:$E,MATCH($F25,$A:$A,0)),"") -> ᚶ | I25: =Fire!$E$13 -> a low, lasting burn | J25: U+16B7 | K25: Frame | L25: 0.4 | M25: =IFERROR(INDEX('Bond Rules'!$B$4:$B$7,MATCH(K25,'Bond Rules'!$A$4:$A$7,0)),"") -> 4 | N25: =IFERROR(ROUND('Bond Rules'!$B$9+L25*INDEX('Bond Rules'!$C$4:$C$7,MATCH(K25,'Bond Rules'!$A$4:$A$7,0)),2),"") -> 2.66 | O25: duration x1.5; status alight
A26: FIR-5a | B26: Fire | C26: 5 | D26: Flare | E26: ᚸ | F26: FIR-5b | G26: =IFERROR(INDEX($D:$D,MATCH($F26,$A:$A,0)),"") -> Smother | H26: =IFERROR(INDEX($E:$E,MATCH($F26,$A:$A,0)),"") -> ᚹ | I26: =Fire!$E$14 -> a sudden flash of flame | J26: U+16B8 | K26: Branch | L26: -0.6 | M26: =IFERROR(INDEX('Bond Rules'!$B$4:$B$7,MATCH(K26,'Bond Rules'!$A$4:$A$7,0)),"") -> 3 | N26: =IFERROR(ROUND('Bond Rules'!$B$9+L26*INDEX('Bond Rules'!$C$4:$C$7,MATCH(K26,'Bond Rules'!$A$4:$A$7,0)),2),"") -> 2.08 | O26: status dazed
A27: FIR-5b | B27: Fire | C27: 5 | D27: Smother | E27: ᚹ | F27: FIR-5a | G27: =IFERROR(INDEX($D:$D,MATCH($F27,$A:$A,0)),"") -> Flare | H27: =IFERROR(INDEX($E:$E,MATCH($F27,$A:$A,0)),"") -> ᚸ | I27: =Fire!$E$15 -> starve a fire, or a foe, of air | J27: U+16B9 | K27: Cap | L27: 0.8 | M27: =IFERROR(INDEX('Bond Rules'!$B$4:$B$7,MATCH(K27,'Bond Rules'!$A$4:$A$7,0)),"") -> 1 | N27: =IFERROR(ROUND('Bond Rules'!$B$9+L27*INDEX('Bond Rules'!$C$4:$C$7,MATCH(K27,'Bond Rules'!$A$4:$A$7,0)),2),"") -> 3.7 | O27: interrupts; status slowed
A28: EAR-1a | B28: Earth | C28: 1 | D28: Raise | E28: ᚺ | F28: EAR-1b | G28: =IFERROR(INDEX($D:$D,MATCH($F28,$A:$A,0)),"") -> Sink | H28: =IFERROR(INDEX($E:$E,MATCH($F28,$A:$A,0)),"") -> ᚻ | I28: =Earth!$E$6 -> stone up | J28: U+16BA | K28: Frame | L28: -0.2 | M28: =IFERROR(INDEX('Bond Rules'!$B$4:$B$7,MATCH(K28,'Bond Rules'!$A$4:$A$7,0)),"") -> 4 | N28: =IFERROR(ROUND('Bond Rules'!$B$9+L28*INDEX('Bond Rules'!$C$4:$C$7,MATCH(K28,'Bond Rules'!$A$4:$A$7,0)),2),"") -> 2.42 | O28: poise x1.3
A29: EAR-1b | B29: Earth | C29: 1 | D29: Sink | E29: ᚻ | F29: EAR-1a | G29: =IFERROR(INDEX($D:$D,MATCH($F29,$A:$A,0)),"") -> Raise | H29: =IFERROR(INDEX($E:$E,MATCH($F29,$A:$A,0)),"") -> ᚺ | I29: =Earth!$E$7 -> ground down, pits | J29: U+16BB | K29: Link | L29: 0.5 | M29: =IFERROR(INDEX('Bond Rules'!$B$4:$B$7,MATCH(K29,'Bond Rules'!$A$4:$A$7,0)),"") -> 2 | N29: =IFERROR(ROUND('Bond Rules'!$B$9+L29*INDEX('Bond Rules'!$C$4:$C$7,MATCH(K29,'Bond Rules'!$A$4:$A$7,0)),2),"") -> 3 | O29: status mired
A30: EAR-2a | B30: Earth | C30: 2 | D30: Harden | E30: ᚼ | F30: EAR-2b | G30: =IFERROR(INDEX($D:$D,MATCH($F30,$A:$A,0)),"") -> Crumble | H30: =IFERROR(INDEX($E:$E,MATCH($F30,$A:$A,0)),"") -> ᚽ | I30: =Earth!$E$8 -> solidify, armour | J30: U+16BC | K30: Frame | L30: 0.4 | M30: =IFERROR(INDEX('Bond Rules'!$B$4:$B$7,MATCH(K30,'Bond Rules'!$A$4:$A$7,0)),"") -> 4 | N30: =IFERROR(ROUND('Bond Rules'!$B$9+L30*INDEX('Bond Rules'!$C$4:$C$7,MATCH(K30,'Bond Rules'!$A$4:$A$7,0)),2),"") -> 2.66 | O30: power x1.15; speed x0.9
A31: EAR-2b | B31: Earth | C31: 2 | D31: Crumble | E31: ᚽ | F31: EAR-2a | G31: =IFERROR(INDEX($D:$D,MATCH($F31,$A:$A,0)),"") -> Harden | H31: =IFERROR(INDEX($E:$E,MATCH($F31,$A:$A,0)),"") -> ᚼ | I31: =Earth!$E$9 -> break stone and guard | J31: U+16BD | K31: Branch | L31: -0.6 | M31: =IFERROR(INDEX('Bond Rules'!$B$4:$B$7,MATCH(K31,'Bond Rules'!$A$4:$A$7,0)),"") -> 3 | N31: =IFERROR(ROUND('Bond Rules'!$B$9+L31*INDEX('Bond Rules'!$C$4:$C$7,MATCH(K31,'Bond Rules'!$A$4:$A$7,0)),2),"") -> 2.08 | O31: poise x1.5
A32: EAR-3a | B32: Earth | C32: 3 | D32: Root | E32: ᚾ | F32: EAR-3b | G32: =IFERROR(INDEX($D:$D,MATCH($F32,$A:$A,0)),"") -> Quake | H32: =IFERROR(INDEX($E:$E,MATCH($F32,$A:$A,0)),"") -> ᚿ | I32: =Earth!$E$10 -> anchor, stand firm | J32: U+16BE | K32: Frame | L32: 0.6 | M32: =IFERROR(INDEX('Bond Rules'!$B$4:$B$7,MATCH(K32,'Bond Rules'!$A$4:$A$7,0)),"") -> 4 | N32: =IFERROR(ROUND('Bond Rules'!$B$9+L32*INDEX('Bond Rules'!$C$4:$C$7,MATCH(K32,'Bond Rules'!$A$4:$A$7,0)),2),"") -> 2.74 | O32: braced
A33: EAR-3b | B33: Earth | C33: 3 | D33: Quake | E33: ᚿ | F33: EAR-3a | G33: =IFERROR(INDEX($D:$D,MATCH($F33,$A:$A,0)),"") -> Root | H33: =IFERROR(INDEX($E:$E,MATCH($F33,$A:$A,0)),"") -> ᚾ | I33: =Earth!$E$11 -> shake, unbalance | J33: U+16BF | K33: Branch | L33: -0.7 | M33: =IFERROR(INDEX('Bond Rules'!$B$4:$B$7,MATCH(K33,'Bond Rules'!$A$4:$A$7,0)),"") -> 3 | N33: =IFERROR(ROUND('Bond Rules'!$B$9+L33*INDEX('Bond Rules'!$C$4:$C$7,MATCH(K33,'Bond Rules'!$A$4:$A$7,0)),2),"") -> 2.01 | O33: reach x1.2; poise x1.3
A34: EAR-4a | B34: Earth | C34: 4 | D34: Dig | E34: ᛀ | F34: EAR-4b | G34: =IFERROR(INDEX($D:$D,MATCH($F34,$A:$A,0)),"") -> Bury | H34: =IFERROR(INDEX($E:$E,MATCH($F34,$A:$A,0)),"") -> ᛁ | I34: =Earth!$E$12 -> tear into the ground and bring stone up to throw | J34: U+16C0 | K34: Link | L34: -0.4 | M34: =IFERROR(INDEX('Bond Rules'!$B$4:$B$7,MATCH(K34,'Bond Rules'!$A$4:$A$7,0)),"") -> 2 | N34: =IFERROR(ROUND('Bond Rules'!$B$9+L34*INDEX('Bond Rules'!$C$4:$C$7,MATCH(K34,'Bond Rules'!$A$4:$A$7,0)),2),"") -> 2.1 | O34: power x1.15; cost x0.9
A35: EAR-4b | B35: Earth | C35: 4 | D35: Bury | E35: ᛁ | F35: EAR-4a | G35: =IFERROR(INDEX($D:$D,MATCH($F35,$A:$A,0)),"") -> Dig | H35: =IFERROR(INDEX($E:$E,MATCH($F35,$A:$A,0)),"") -> ᛀ | I35: =Earth!$E$13 -> cover over with earth | J35: U+16C1 | K35: Cap | L35: 0.7 | M35: =IFERROR(INDEX('Bond Rules'!$B$4:$B$7,MATCH(K35,'Bond Rules'!$A$4:$A$7,0)),"") -> 1 | N35: =IFERROR(ROUND('Bond Rules'!$B$9+L35*INDEX('Bond Rules'!$C$4:$C$7,MATCH(K35,'Bond Rules'!$A$4:$A$7,0)),2),"") -> 3.55 | O35: status pinned
A36: EAR-5a | B36: Earth | C36: 5 | D36: Tunnel | E36: ᛂ | F36: EAR-5b | G36: =IFERROR(INDEX($D:$D,MATCH($F36,$A:$A,0)),"") -> Collapse | H36: =IFERROR(INDEX($E:$E,MATCH($F36,$A:$A,0)),"") -> ᛃ | I36: =Earth!$E$14 -> pass through the ground | J36: U+16C2 | K36: Link | L36: -0.3 | M36: =IFERROR(INDEX('Bond Rules'!$B$4:$B$7,MATCH(K36,'Bond Rules'!$A$4:$A$7,0)),"") -> 2 | N36: =IFERROR(ROUND('Bond Rules'!$B$9+L36*INDEX('Bond Rules'!$C$4:$C$7,MATCH(K36,'Bond Rules'!$A$4:$A$7,0)),2),"") -> 2.2 | O36: pierce +1
A37: EAR-5b | B37: Earth | C37: 5 | D37: Collapse | E37: ᛃ | F37: EAR-5a | G37: =IFERROR(INDEX($D:$D,MATCH($F37,$A:$A,0)),"") -> Tunnel | H37: =IFERROR(INDEX($E:$E,MATCH($F37,$A:$A,0)),"") -> ᛂ | I37: =Earth!$E$15 -> bring the ground down and close a passage | J37: U+16C3 | K37: Cap | L37: 0.6 | M37: =IFERROR(INDEX('Bond Rules'!$B$4:$B$7,MATCH(K37,'Bond Rules'!$A$4:$A$7,0)),"") -> 1 | N37: =IFERROR(ROUND('Bond Rules'!$B$9+L37*INDEX('Bond Rules'!$C$4:$C$7,MATCH(K37,'Bond Rules'!$A$4:$A$7,0)),2),"") -> 3.4 | O37: status stunned; cost x1.2
A38: WIN-1a | B38: Wind | C38: 1 | D38: Blow | E38: ᛄ | F38: WIN-1b | G38: =IFERROR(INDEX($D:$D,MATCH($F38,$A:$A,0)),"") -> Lull | H38: =IFERROR(INDEX($E:$E,MATCH($F38,$A:$A,0)),"") -> ᛅ | I38: =Wind!$E$6 -> moving air pushes | J38: U+16C4 | K38: Link | L38: -0.6 | M38: =IFERROR(INDEX('Bond Rules'!$B$4:$B$7,MATCH(K38,'Bond Rules'!$A$4:$A$7,0)),"") -> 2 | N38: =IFERROR(ROUND('Bond Rules'!$B$9+L38*INDEX('Bond Rules'!$C$4:$C$7,MATCH(K38,'Bond Rules'!$A$4:$A$7,0)),2),"") -> 1.9 | O38: shove +1
A39: WIN-1b | B39: Wind | C39: 1 | D39: Lull | E39: ᛅ | F39: WIN-1a | G39: =IFERROR(INDEX($D:$D,MATCH($F39,$A:$A,0)),"") -> Blow | H39: =IFERROR(INDEX($E:$E,MATCH($F39,$A:$A,0)),"") -> ᛄ | I39: =Wind!$E$7 -> dead air; shots drop | J39: U+16C5 | K39: Cap | L39: 0.5 | M39: =IFERROR(INDEX('Bond Rules'!$B$4:$B$7,MATCH(K39,'Bond Rules'!$A$4:$A$7,0)),"") -> 1 | N39: =IFERROR(ROUND('Bond Rules'!$B$9+L39*INDEX('Bond Rules'!$C$4:$C$7,MATCH(K39,'Bond Rules'!$A$4:$A$7,0)),2),"") -> 3.25 | O39: reflux x0.8
A40: WIN-2a | B40: Wind | C40: 2 | D40: Lash | E40: ᛆ | F40: WIN-2b | G40: =IFERROR(INDEX($D:$D,MATCH($F40,$A:$A,0)),"") -> Buffer | H40: =IFERROR(INDEX($E:$E,MATCH($F40,$A:$A,0)),"") -> ᛇ | I40: =Wind!$E$8 -> air that strikes and cuts | J40: U+16C6 | K40: Link | L40: 0.3 | M40: =IFERROR(INDEX('Bond Rules'!$B$4:$B$7,MATCH(K40,'Bond Rules'!$A$4:$A$7,0)),"") -> 2 | N40: =IFERROR(ROUND('Bond Rules'!$B$9+L40*INDEX('Bond Rules'!$C$4:$C$7,MATCH(K40,'Bond Rules'!$A$4:$A$7,0)),2),"") -> 2.8 | O40: power x1.2; speed x1.1
A41: WIN-2b | B41: Wind | C41: 2 | D41: Buffer | E41: ᛇ | F41: WIN-2a | G41: =IFERROR(INDEX($D:$D,MATCH($F41,$A:$A,0)),"") -> Lash | H41: =IFERROR(INDEX($E:$E,MATCH($F41,$A:$A,0)),"") -> ᛆ | I41: =Wind!$E$9 -> cushioning air | J41: U+16C7 | K41: Frame | L41: -0.2 | M41: =IFERROR(INDEX('Bond Rules'!$B$4:$B$7,MATCH(K41,'Bond Rules'!$A$4:$A$7,0)),"") -> 4 | N41: =IFERROR(ROUND('Bond Rules'!$B$9+L41*INDEX('Bond Rules'!$C$4:$C$7,MATCH(K41,'Bond Rules'!$A$4:$A$7,0)),2),"") -> 2.42 | O41: windup x0.85
A42: WIN-3a | B42: Wind | C42: 3 | D42: Lift | E42: ᛈ | F42: WIN-3b | G42: =IFERROR(INDEX($D:$D,MATCH($F42,$A:$A,0)),"") -> Drop | H42: =IFERROR(INDEX($E:$E,MATCH($F42,$A:$A,0)),"") -> ᛉ | I42: =Wind!$E$10 -> raise aloft | J42: U+16C8 | K42: Link | L42: -0.4 | M42: =IFERROR(INDEX('Bond Rules'!$B$4:$B$7,MATCH(K42,'Bond Rules'!$A$4:$A$7,0)),"") -> 2 | N42: =IFERROR(ROUND('Bond Rules'!$B$9+L42*INDEX('Bond Rules'!$C$4:$C$7,MATCH(K42,'Bond Rules'!$A$4:$A$7,0)),2),"") -> 2.1 | O42: status aloft
A43: WIN-3b | B43: Wind | C43: 3 | D43: Drop | E43: ᛉ | F43: WIN-3a | G43: =IFERROR(INDEX($D:$D,MATCH($F43,$A:$A,0)),"") -> Lift | H43: =IFERROR(INDEX($E:$E,MATCH($F43,$A:$A,0)),"") -> ᛈ | I43: =Wind!$E$11 -> slam down | J43: U+16C9 | K43: Link | L43: 0.5 | M43: =IFERROR(INDEX('Bond Rules'!$B$4:$B$7,MATCH(K43,'Bond Rules'!$A$4:$A$7,0)),"") -> 2 | N43: =IFERROR(ROUND('Bond Rules'!$B$9+L43*INDEX('Bond Rules'!$C$4:$C$7,MATCH(K43,'Bond Rules'!$A$4:$A$7,0)),2),"") -> 3 | O43: poise x1.4
A44: WIN-4a | B44: Wind | C44: 4 | D44: Carry | E44: ᛊ | F44: WIN-4b | G44: =IFERROR(INDEX($D:$D,MATCH($F44,$A:$A,0)),"") -> Stall | H44: =IFERROR(INDEX($E:$E,MATCH($F44,$A:$A,0)),"") -> ᛋ | I44: =Wind!$E$12 -> be carried along, faster | J44: U+16CA | K44: Link | L44: -0.5 | M44: =IFERROR(INDEX('Bond Rules'!$B$4:$B$7,MATCH(K44,'Bond Rules'!$A$4:$A$7,0)),"") -> 2 | N44: =IFERROR(ROUND('Bond Rules'!$B$9+L44*INDEX('Bond Rules'!$C$4:$C$7,MATCH(K44,'Bond Rules'!$A$4:$A$7,0)),2),"") -> 2 | O44: speed x1.3; reach x1.15
A45: WIN-4b | B45: Wind | C45: 4 | D45: Stall | E45: ᛋ | F45: WIN-4a | G45: =IFERROR(INDEX($D:$D,MATCH($F45,$A:$A,0)),"") -> Carry | H45: =IFERROR(INDEX($E:$E,MATCH($F45,$A:$A,0)),"") -> ᛊ | I45: =Wind!$E$13 -> stalled; slipstream stolen | J45: U+16CB | K45: Link | L45: 0.6 | M45: =IFERROR(INDEX('Bond Rules'!$B$4:$B$7,MATCH(K45,'Bond Rules'!$A$4:$A$7,0)),"") -> 2 | N45: =IFERROR(ROUND('Bond Rules'!$B$9+L45*INDEX('Bond Rules'!$C$4:$C$7,MATCH(K45,'Bond Rules'!$A$4:$A$7,0)),2),"") -> 3.1 | O45: status slowed
A46: WIN-5a | B46: Wind | C46: 5 | D46: Whirl | E46: ᛌ | F46: WIN-5b | G46: =IFERROR(INDEX($D:$D,MATCH($F46,$A:$A,0)),"") -> Disperse | H46: =IFERROR(INDEX($E:$E,MATCH($F46,$A:$A,0)),"") -> ᛍ | I46: =Wind!$E$14 -> spin together | J46: U+16CC | K46: Frame | L46: 0.4 | M46: =IFERROR(INDEX('Bond Rules'!$B$4:$B$7,MATCH(K46,'Bond Rules'!$A$4:$A$7,0)),"") -> 4 | N46: =IFERROR(ROUND('Bond Rules'!$B$9+L46*INDEX('Bond Rules'!$C$4:$C$7,MATCH(K46,'Bond Rules'!$A$4:$A$7,0)),2),"") -> 2.66 | O46: pull +1; reach x1.1
A47: WIN-5b | B47: Wind | C47: 5 | D47: Disperse | E47: ᛍ | F47: WIN-5a | G47: =IFERROR(INDEX($D:$D,MATCH($F47,$A:$A,0)),"") -> Whirl | H47: =IFERROR(INDEX($E:$E,MATCH($F47,$A:$A,0)),"") -> ᛌ | I47: =Wind!$E$15 -> blow apart | J47: U+16CD | K47: Branch | L47: -0.9 | M47: =IFERROR(INDEX('Bond Rules'!$B$4:$B$7,MATCH(K47,'Bond Rules'!$A$4:$A$7,0)),"") -> 3 | N47: =IFERROR(ROUND('Bond Rules'!$B$9+L47*INDEX('Bond Rules'!$C$4:$C$7,MATCH(K47,'Bond Rules'!$A$4:$A$7,0)),2),"") -> 1.87 | O47: reach x1.3; power x0.9
A48: LIG-1a | B48: Lightning | C48: 1 | D48: Strike | E48: ᛎ | F48: LIG-1b | G48: =IFERROR(INDEX($D:$D,MATCH($F48,$A:$A,0)),"") -> Ground | H48: =IFERROR(INDEX($E:$E,MATCH($F48,$A:$A,0)),"") -> ᛏ | I48: =Lightning!$E$6 -> a bolt that hits one target | J48: U+16CE | K48: Link | L48: -0.6 | M48: =IFERROR(INDEX('Bond Rules'!$B$4:$B$7,MATCH(K48,'Bond Rules'!$A$4:$A$7,0)),"") -> 2 | N48: =IFERROR(ROUND('Bond Rules'!$B$9+L48*INDEX('Bond Rules'!$C$4:$C$7,MATCH(K48,'Bond Rules'!$A$4:$A$7,0)),2),"") -> 1.9 | O48: power x1.2; speed x1.2
A49: LIG-1b | B49: Lightning | C49: 1 | D49: Ground | E49: ᛏ | F49: LIG-1a | G49: =IFERROR(INDEX($D:$D,MATCH($F49,$A:$A,0)),"") -> Strike | H49: =IFERROR(INDEX($E:$E,MATCH($F49,$A:$A,0)),"") -> ᛎ | I49: =Lightning!$E$7 -> earth a charge away; draw strikes to a point | J49: U+16CF | K49: Frame | L49: 0.4 | M49: =IFERROR(INDEX('Bond Rules'!$B$4:$B$7,MATCH(K49,'Bond Rules'!$A$4:$A$7,0)),"") -> 4 | N49: =IFERROR(ROUND('Bond Rules'!$B$9+L49*INDEX('Bond Rules'!$C$4:$C$7,MATCH(K49,'Bond Rules'!$A$4:$A$7,0)),2),"") -> 2.66 | O49: reflux x0.75
A50: LIG-2a | B50: Lightning | C50: 2 | D50: Charge | E50: ᛐ | F50: LIG-2b | G50: =IFERROR(INDEX($D:$D,MATCH($F50,$A:$A,0)),"") -> Discharge | H50: =IFERROR(INDEX($E:$E,MATCH($F50,$A:$A,0)),"") -> ᛑ | I50: =Lightning!$E$8 -> build up marks | J50: U+16D0 | K50: Frame | L50: 0.6 | M50: =IFERROR(INDEX('Bond Rules'!$B$4:$B$7,MATCH(K50,'Bond Rules'!$A$4:$A$7,0)),"") -> 4 | N50: =IFERROR(ROUND('Bond Rules'!$B$9+L50*INDEX('Bond Rules'!$C$4:$C$7,MATCH(K50,'Bond Rules'!$A$4:$A$7,0)),2),"") -> 2.74 | O50: marks +1
A51: LIG-2b | B51: Lightning | C51: 2 | D51: Discharge | E51: ᛑ | F51: LIG-2a | G51: =IFERROR(INDEX($D:$D,MATCH($F51,$A:$A,0)),"") -> Charge | H51: =IFERROR(INDEX($E:$E,MATCH($F51,$A:$A,0)),"") -> ᛐ | I51: =Lightning!$E$9 -> release them as an overload | J51: U+16D1 | K51: Cap | L51: -1 | M51: =IFERROR(INDEX('Bond Rules'!$B$4:$B$7,MATCH(K51,'Bond Rules'!$A$4:$A$7,0)),"") -> 1 | N51: =IFERROR(ROUND('Bond Rules'!$B$9+L51*INDEX('Bond Rules'!$C$4:$C$7,MATCH(K51,'Bond Rules'!$A$4:$A$7,0)),2),"") -> 1 | O51: bonus live +0.4
A52: LIG-3a | B52: Lightning | C52: 3 | D52: Arc | E52: ᛒ | F52: LIG-3b | G52: =IFERROR(INDEX($D:$D,MATCH($F52,$A:$A,0)),"") -> Insulate | H52: =IFERROR(INDEX($E:$E,MATCH($F52,$A:$A,0)),"") -> ᛓ | I52: =Lightning!$E$10 -> jump between targets | J52: U+16D2 | K52: Branch | L52: -0.5 | M52: =IFERROR(INDEX('Bond Rules'!$B$4:$B$7,MATCH(K52,'Bond Rules'!$A$4:$A$7,0)),"") -> 3 | N52: =IFERROR(ROUND('Bond Rules'!$B$9+L52*INDEX('Bond Rules'!$C$4:$C$7,MATCH(K52,'Bond Rules'!$A$4:$A$7,0)),2),"") -> 2.15 | O52: jumps +1
A53: LIG-3b | B53: Lightning | C53: 3 | D53: Insulate | E53: ᛓ | F53: LIG-3a | G53: =IFERROR(INDEX($D:$D,MATCH($F53,$A:$A,0)),"") -> Arc | H53: =IFERROR(INDEX($E:$E,MATCH($F53,$A:$A,0)),"") -> ᛒ | I53: =Lightning!$E$11 -> block a jump, isolate a target | J53: U+16D3 | K53: Cap | L53: 0.3 | M53: =IFERROR(INDEX('Bond Rules'!$B$4:$B$7,MATCH(K53,'Bond Rules'!$A$4:$A$7,0)),"") -> 1 | N53: =IFERROR(ROUND('Bond Rules'!$B$9+L53*INDEX('Bond Rules'!$C$4:$C$7,MATCH(K53,'Bond Rules'!$A$4:$A$7,0)),2),"") -> 2.95 | O53: cost x0.85
A54: LIG-4a | B54: Lightning | C54: 4 | D54: Quicken | E54: ᛔ | F54: LIG-4b | G54: =IFERROR(INDEX($D:$D,MATCH($F54,$A:$A,0)),"") -> Stun | H54: =IFERROR(INDEX($E:$E,MATCH($F54,$A:$A,0)),"") -> ᛕ | I54: =Lightning!$E$12 -> nerves in overdrive | J54: U+16D4 | K54: Link | L54: -0.4 | M54: =IFERROR(INDEX('Bond Rules'!$B$4:$B$7,MATCH(K54,'Bond Rules'!$A$4:$A$7,0)),"") -> 2 | N54: =IFERROR(ROUND('Bond Rules'!$B$9+L54*INDEX('Bond Rules'!$C$4:$C$7,MATCH(K54,'Bond Rules'!$A$4:$A$7,0)),2),"") -> 2.1 | O54: windup x0.7; speed x1.2
A55: LIG-4b | B55: Lightning | C55: 4 | D55: Stun | E55: ᛕ | F55: LIG-4a | G55: =IFERROR(INDEX($D:$D,MATCH($F55,$A:$A,0)),"") -> Quicken | H55: =IFERROR(INDEX($E:$E,MATCH($F55,$A:$A,0)),"") -> ᛔ | I55: =Lightning!$E$13 -> nerves locked | J55: U+16D5 | K55: Cap | L55: 0.7 | M55: =IFERROR(INDEX('Bond Rules'!$B$4:$B$7,MATCH(K55,'Bond Rules'!$A$4:$A$7,0)),"") -> 1 | N55: =IFERROR(ROUND('Bond Rules'!$B$9+L55*INDEX('Bond Rules'!$C$4:$C$7,MATCH(K55,'Bond Rules'!$A$4:$A$7,0)),2),"") -> 3.55 | O55: status stunned
A56: LIG-5a | B56: Lightning | C56: 5 | D56: Thunder | E56: ᛖ | F56: LIG-5b | G56: =IFERROR(INDEX($D:$D,MATCH($F56,$A:$A,0)),"") -> Silence | H56: =IFERROR(INDEX($E:$E,MATCH($F56,$A:$A,0)),"") -> ᛗ | I56: =Lightning!$E$14 -> a deafening crack that staggers | J56: U+16D6 | K56: Branch | L56: -0.7 | M56: =IFERROR(INDEX('Bond Rules'!$B$4:$B$7,MATCH(K56,'Bond Rules'!$A$4:$A$7,0)),"") -> 3 | N56: =IFERROR(ROUND('Bond Rules'!$B$9+L56*INDEX('Bond Rules'!$C$4:$C$7,MATCH(K56,'Bond Rules'!$A$4:$A$7,0)),2),"") -> 2.01 | O56: poise x1.3; status dazed
A57: LIG-5b | B57: Lightning | C57: 5 | D57: Silence | E57: ᛗ | F57: LIG-5a | G57: =IFERROR(INDEX($D:$D,MATCH($F57,$A:$A,0)),"") -> Thunder | H57: =IFERROR(INDEX($E:$E,MATCH($F57,$A:$A,0)),"") -> ᛖ | I57: =Lightning!$E$15 -> dead quiet: casting and calls fail | J57: U+16D7 | K57: Cap | L57: 0.5 | M57: =IFERROR(INDEX('Bond Rules'!$B$4:$B$7,MATCH(K57,'Bond Rules'!$A$4:$A$7,0)),"") -> 1 | N57: =IFERROR(ROUND('Bond Rules'!$B$9+L57*INDEX('Bond Rules'!$C$4:$C$7,MATCH(K57,'Bond Rules'!$A$4:$A$7,0)),2),"") -> 3.25 | O57: interrupts
A58: ICE-1a | B58: Ice | C58: 1 | D58: Freeze | E58: 🜀 | F58: ICE-1b | G58: =IFERROR(INDEX($D:$D,MATCH($F58,$A:$A,0)),"") -> Thaw | H58: =IFERROR(INDEX($E:$E,MATCH($F58,$A:$A,0)),"") -> 🜁 | I58: =Ice!$E$6 -> lock solid | J58: U+1F700 | K58: Frame | L58: 0.5 | M58: =IFERROR(INDEX('Bond Rules'!$B$4:$B$7,MATCH(K58,'Bond Rules'!$A$4:$A$7,0)),"") -> 4 | N58: =IFERROR(ROUND('Bond Rules'!$B$9+L58*INDEX('Bond Rules'!$C$4:$C$7,MATCH(K58,'Bond Rules'!$A$4:$A$7,0)),2),"") -> 2.7
A59: ICE-1b | B59: Ice | C59: 1 | D59: Thaw | E59: 🜁 | F59: ICE-1a | G59: =IFERROR(INDEX($D:$D,MATCH($F59,$A:$A,0)),"") -> Freeze | H59: =IFERROR(INDEX($E:$E,MATCH($F59,$A:$A,0)),"") -> 🜀 | I59: =Ice!$E$7 -> release, melt free | J59: U+1F701 | K59: Link | L59: -0.6 | M59: =IFERROR(INDEX('Bond Rules'!$B$4:$B$7,MATCH(K59,'Bond Rules'!$A$4:$A$7,0)),"") -> 2 | N59: =IFERROR(ROUND('Bond Rules'!$B$9+L59*INDEX('Bond Rules'!$C$4:$C$7,MATCH(K59,'Bond Rules'!$A$4:$A$7,0)),2),"") -> 1.9
A60: ICE-2a | B60: Ice | C60: 2 | D60: Frost | E60: 🜂 | F60: ICE-2b | G60: =IFERROR(INDEX($D:$D,MATCH($F60,$A:$A,0)),"") -> Glaze | H60: =IFERROR(INDEX($E:$E,MATCH($F60,$A:$A,0)),"") -> 🜃 | I60: =Ice!$E$8 -> creeping cold on the ground that grips and slows | J60: U+1F702 | K60: Link | L60: 0.4 | M60: =IFERROR(INDEX('Bond Rules'!$B$4:$B$7,MATCH(K60,'Bond Rules'!$A$4:$A$7,0)),"") -> 2 | N60: =IFERROR(ROUND('Bond Rules'!$B$9+L60*INDEX('Bond Rules'!$C$4:$C$7,MATCH(K60,'Bond Rules'!$A$4:$A$7,0)),2),"") -> 2.9
A61: ICE-2b | B61: Ice | C61: 2 | D61: Glaze | E61: 🜃 | F61: ICE-2a | G61: =IFERROR(INDEX($D:$D,MATCH($F61,$A:$A,0)),"") -> Frost | H61: =IFERROR(INDEX($E:$E,MATCH($F61,$A:$A,0)),"") -> 🜂 | I61: =Ice!$E$9 -> glazed ice: fast and slippery | J61: U+1F703 | K61: Link | L61: -0.5 | M61: =IFERROR(INDEX('Bond Rules'!$B$4:$B$7,MATCH(K61,'Bond Rules'!$A$4:$A$7,0)),"") -> 2 | N61: =IFERROR(ROUND('Bond Rules'!$B$9+L61*INDEX('Bond Rules'!$C$4:$C$7,MATCH(K61,'Bond Rules'!$A$4:$A$7,0)),2),"") -> 2
A62: ICE-3a | B62: Ice | C62: 3 | D62: Snow | E62: 🜄 | F62: ICE-3b | G62: =IFERROR(INDEX($D:$D,MATCH($F62,$A:$A,0)),"") -> Melt | H62: =IFERROR(INDEX($E:$E,MATCH($F62,$A:$A,0)),"") -> 🜅 | I62: =Ice!$E$10 -> a fall of snow that blinds and buries | J62: U+1F704 | K62: Branch | L62: -0.5 | M62: =IFERROR(INDEX('Bond Rules'!$B$4:$B$7,MATCH(K62,'Bond Rules'!$A$4:$A$7,0)),"") -> 3 | N62: =IFERROR(ROUND('Bond Rules'!$B$9+L62*INDEX('Bond Rules'!$C$4:$C$7,MATCH(K62,'Bond Rules'!$A$4:$A$7,0)),2),"") -> 2.15
A63: ICE-3b | B63: Ice | C63: 3 | D63: Melt | E63: 🜅 | F63: ICE-3a | G63: =IFERROR(INDEX($D:$D,MATCH($F63,$A:$A,0)),"") -> Snow | H63: =IFERROR(INDEX($E:$E,MATCH($F63,$A:$A,0)),"") -> 🜄 | I63: =Ice!$E$11 -> turn ice and snow to water | J63: U+1F705 | K63: Link | L63: 0.4 | M63: =IFERROR(INDEX('Bond Rules'!$B$4:$B$7,MATCH(K63,'Bond Rules'!$A$4:$A$7,0)),"") -> 2 | N63: =IFERROR(ROUND('Bond Rules'!$B$9+L63*INDEX('Bond Rules'!$C$4:$C$7,MATCH(K63,'Bond Rules'!$A$4:$A$7,0)),2),"") -> 2.9
A64: ICE-4a | B64: Ice | C64: 4 | D64: Rime | E64: 🜆 | F64: ICE-4b | G64: =IFERROR(INDEX($D:$D,MATCH($F64,$A:$A,0)),"") -> Shatter | H64: =IFERROR(INDEX($E:$E,MATCH($F64,$A:$A,0)),"") -> 🜇 | I64: =Ice!$E$12 -> build ice: walls, armour, spikes | J64: U+1F706 | K64: Frame | L64: 0.3 | M64: =IFERROR(INDEX('Bond Rules'!$B$4:$B$7,MATCH(K64,'Bond Rules'!$A$4:$A$7,0)),"") -> 4 | N64: =IFERROR(ROUND('Bond Rules'!$B$9+L64*INDEX('Bond Rules'!$C$4:$C$7,MATCH(K64,'Bond Rules'!$A$4:$A$7,0)),2),"") -> 2.62
A65: ICE-4b | B65: Ice | C65: 4 | D65: Shatter | E65: 🜇 | F65: ICE-4a | G65: =IFERROR(INDEX($D:$D,MATCH($F65,$A:$A,0)),"") -> Rime | H65: =IFERROR(INDEX($E:$E,MATCH($F65,$A:$A,0)),"") -> 🜆 | I65: =Ice!$E$13 -> break ice; brittle things burst | J65: U+1F707 | K65: Branch | L65: -0.9 | M65: =IFERROR(INDEX('Bond Rules'!$B$4:$B$7,MATCH(K65,'Bond Rules'!$A$4:$A$7,0)),"") -> 3 | N65: =IFERROR(ROUND('Bond Rules'!$B$9+L65*INDEX('Bond Rules'!$C$4:$C$7,MATCH(K65,'Bond Rules'!$A$4:$A$7,0)),2),"") -> 1.87
A66: ICE-5a | B66: Ice | C66: 5 | D66: Brittle | E66: 🜈 | F66: ICE-5b | G66: =IFERROR(INDEX($D:$D,MATCH($F66,$A:$A,0)),"") -> Toughen | H66: =IFERROR(INDEX($E:$E,MATCH($F66,$A:$A,0)),"") -> 🜉 | I66: =Ice!$E$14 -> make a thing fragile | J66: U+1F708 | K66: Link | L66: -0.3 | M66: =IFERROR(INDEX('Bond Rules'!$B$4:$B$7,MATCH(K66,'Bond Rules'!$A$4:$A$7,0)),"") -> 2 | N66: =IFERROR(ROUND('Bond Rules'!$B$9+L66*INDEX('Bond Rules'!$C$4:$C$7,MATCH(K66,'Bond Rules'!$A$4:$A$7,0)),2),"") -> 2.2
A67: ICE-5b | B67: Ice | C67: 5 | D67: Toughen | E67: 🜉 | F67: ICE-5a | G67: =IFERROR(INDEX($D:$D,MATCH($F67,$A:$A,0)),"") -> Brittle | H67: =IFERROR(INDEX($E:$E,MATCH($F67,$A:$A,0)),"") -> 🜈 | I67: =Ice!$E$15 -> cold-harden it | J67: U+1F709 | K67: Frame | L67: 0.3 | M67: =IFERROR(INDEX('Bond Rules'!$B$4:$B$7,MATCH(K67,'Bond Rules'!$A$4:$A$7,0)),"") -> 4 | N67: =IFERROR(ROUND('Bond Rules'!$B$9+L67*INDEX('Bond Rules'!$C$4:$C$7,MATCH(K67,'Bond Rules'!$A$4:$A$7,0)),2),"") -> 2.62
A68: DRK-1a | B68: Dark | C68: 1 | D68: Darken | E68: 🜊 | F68: DRK-1b | G68: =IFERROR(INDEX($D:$D,MATCH($F68,$A:$A,0)),"") -> Lighten | H68: =IFERROR(INDEX($E:$E,MATCH($F68,$A:$A,0)),"") -> 🜋 | I68: =Dark!$E$6 -> make it darker | J68: U+1F70A | K68: Link | L68: 0.5 | M68: =IFERROR(INDEX('Bond Rules'!$B$4:$B$7,MATCH(K68,'Bond Rules'!$A$4:$A$7,0)),"") -> 2 | N68: =IFERROR(ROUND('Bond Rules'!$B$9+L68*INDEX('Bond Rules'!$C$4:$C$7,MATCH(K68,'Bond Rules'!$A$4:$A$7,0)),2),"") -> 3
A69: DRK-1b | B69: Dark | C69: 1 | D69: Lighten | E69: 🜋 | F69: DRK-1a | G69: =IFERROR(INDEX($D:$D,MATCH($F69,$A:$A,0)),"") -> Darken | H69: =IFERROR(INDEX($E:$E,MATCH($F69,$A:$A,0)),"") -> 🜊 | I69: =Dark!$E$7 -> let the light back in | J69: U+1F70B | K69: Branch | L69: -0.6 | M69: =IFERROR(INDEX('Bond Rules'!$B$4:$B$7,MATCH(K69,'Bond Rules'!$A$4:$A$7,0)),"") -> 3 | N69: =IFERROR(ROUND('Bond Rules'!$B$9+L69*INDEX('Bond Rules'!$C$4:$C$7,MATCH(K69,'Bond Rules'!$A$4:$A$7,0)),2),"") -> 2.08
A70: DRK-2a | B70: Dark | C70: 2 | D70: Obscure | E70: 🜌 | F70: DRK-2b | G70: =IFERROR(INDEX($D:$D,MATCH($F70,$A:$A,0)),"") -> Expose | H70: =IFERROR(INDEX($E:$E,MATCH($F70,$A:$A,0)),"") -> 🜍 | I70: =Dark!$E$8 -> hide a thing in darkness | J70: U+1F70C | K70: Frame | L70: 0.3 | M70: =IFERROR(INDEX('Bond Rules'!$B$4:$B$7,MATCH(K70,'Bond Rules'!$A$4:$A$7,0)),"") -> 4 | N70: =IFERROR(ROUND('Bond Rules'!$B$9+L70*INDEX('Bond Rules'!$C$4:$C$7,MATCH(K70,'Bond Rules'!$A$4:$A$7,0)),2),"") -> 2.62
A71: DRK-2b | B71: Dark | C71: 2 | D71: Expose | E71: 🜍 | F71: DRK-2a | G71: =IFERROR(INDEX($D:$D,MATCH($F71,$A:$A,0)),"") -> Obscure | H71: =IFERROR(INDEX($E:$E,MATCH($F71,$A:$A,0)),"") -> 🜌 | I71: =Dark!$E$9 -> make a hidden target stand out | J71: U+1F70D | K71: Cap | L71: -0.4 | M71: =IFERROR(INDEX('Bond Rules'!$B$4:$B$7,MATCH(K71,'Bond Rules'!$A$4:$A$7,0)),"") -> 1 | N71: =IFERROR(ROUND('Bond Rules'!$B$9+L71*INDEX('Bond Rules'!$C$4:$C$7,MATCH(K71,'Bond Rules'!$A$4:$A$7,0)),2),"") -> 1.9
A72: DRK-3a | B72: Dark | C72: 3 | D72: Shadowstep | E72: 🜎 | F72: DRK-3b | G72: =IFERROR(INDEX($D:$D,MATCH($F72,$A:$A,0)),"") -> Pin | H72: =IFERROR(INDEX($E:$E,MATCH($F72,$A:$A,0)),"") -> 🜏 | I72: =Dark!$E$10 -> move through shadows | J72: U+1F70E | K72: Link | L72: -0.3 | M72: =IFERROR(INDEX('Bond Rules'!$B$4:$B$7,MATCH(K72,'Bond Rules'!$A$4:$A$7,0)),"") -> 2 | N72: =IFERROR(ROUND('Bond Rules'!$B$9+L72*INDEX('Bond Rules'!$C$4:$C$7,MATCH(K72,'Bond Rules'!$A$4:$A$7,0)),2),"") -> 2.2
A73: DRK-3b | B73: Dark | C73: 3 | D73: Pin | E73: 🜏 | F73: DRK-3a | G73: =IFERROR(INDEX($D:$D,MATCH($F73,$A:$A,0)),"") -> Shadowstep | H73: =IFERROR(INDEX($E:$E,MATCH($F73,$A:$A,0)),"") -> 🜎 | I73: =Dark!$E$11 -> nail a target's shadow, and the target with it | J73: U+1F70F | K73: Cap | L73: 0.9 | M73: =IFERROR(INDEX('Bond Rules'!$B$4:$B$7,MATCH(K73,'Bond Rules'!$A$4:$A$7,0)),"") -> 1 | N73: =IFERROR(ROUND('Bond Rules'!$B$9+L73*INDEX('Bond Rules'!$C$4:$C$7,MATCH(K73,'Bond Rules'!$A$4:$A$7,0)),2),"") -> 3.85
A74: DRK-4a | B74: Dark | C74: 4 | D74: Hush | E74: 🜐 | F74: DRK-4b | G74: =IFERROR(INDEX($D:$D,MATCH($F74,$A:$A,0)),"") -> Resound | H74: =IFERROR(INDEX($E:$E,MATCH($F74,$A:$A,0)),"") -> 🜑 | I74: =Dark!$E$12 -> smother sound | J74: U+1F710 | K74: Cap | L74: 0.4 | M74: =IFERROR(INDEX('Bond Rules'!$B$4:$B$7,MATCH(K74,'Bond Rules'!$A$4:$A$7,0)),"") -> 1 | N74: =IFERROR(ROUND('Bond Rules'!$B$9+L74*INDEX('Bond Rules'!$C$4:$C$7,MATCH(K74,'Bond Rules'!$A$4:$A$7,0)),2),"") -> 3.1
A75: DRK-4b | B75: Dark | C75: 4 | D75: Resound | E75: 🜑 | F75: DRK-4a | G75: =IFERROR(INDEX($D:$D,MATCH($F75,$A:$A,0)),"") -> Hush | H75: =IFERROR(INDEX($E:$E,MATCH($F75,$A:$A,0)),"") -> 🜐 | I75: =Dark!$E$13 -> sound carries and echoes in the dark | J75: U+1F711 | K75: Branch | L75: -0.5 | M75: =IFERROR(INDEX('Bond Rules'!$B$4:$B$7,MATCH(K75,'Bond Rules'!$A$4:$A$7,0)),"") -> 3 | N75: =IFERROR(ROUND('Bond Rules'!$B$9+L75*INDEX('Bond Rules'!$C$4:$C$7,MATCH(K75,'Bond Rules'!$A$4:$A$7,0)),2),"") -> 2.15
A76: DRK-5a | B76: Dark | C76: 5 | D76: Devour | E76: 🜒 | F76: DRK-5b | G76: =IFERROR(INDEX($D:$D,MATCH($F76,$A:$A,0)),"") -> Disgorge | H76: =IFERROR(INDEX($E:$E,MATCH($F76,$A:$A,0)),"") -> 🜓 | I76: =Dark!$E$14 -> swallow light and energy | J76: U+1F712 | K76: Cap | L76: 1 | M76: =IFERROR(INDEX('Bond Rules'!$B$4:$B$7,MATCH(K76,'Bond Rules'!$A$4:$A$7,0)),"") -> 1 | N76: =IFERROR(ROUND('Bond Rules'!$B$9+L76*INDEX('Bond Rules'!$C$4:$C$7,MATCH(K76,'Bond Rules'!$A$4:$A$7,0)),2),"") -> 4
A77: DRK-5b | B77: Dark | C77: 5 | D77: Disgorge | E77: 🜓 | F77: DRK-5a | G77: =IFERROR(INDEX($D:$D,MATCH($F77,$A:$A,0)),"") -> Devour | H77: =IFERROR(INDEX($E:$E,MATCH($F77,$A:$A,0)),"") -> 🜒 | I77: =Dark!$E$15 -> release what was swallowed | J77: U+1F713 | K77: Branch | L77: -1 | M77: =IFERROR(INDEX('Bond Rules'!$B$4:$B$7,MATCH(K77,'Bond Rules'!$A$4:$A$7,0)),"") -> 3 | N77: =IFERROR(ROUND('Bond Rules'!$B$9+L77*INDEX('Bond Rules'!$C$4:$C$7,MATCH(K77,'Bond Rules'!$A$4:$A$7,0)),2),"") -> 1.8
A78: MET-1a | B78: Metal | C78: 1 | D78: Forge | E78: 🜔 | F78: MET-1b | G78: =IFERROR(INDEX($D:$D,MATCH($F78,$A:$A,0)),"") -> Rust | H78: =IFERROR(INDEX($E:$E,MATCH($F78,$A:$A,0)),"") -> 🜕 | I78: =Metal!$E$6 -> shape and harden metal | J78: U+1F714 | K78: Frame | L78: 0.2 | M78: =IFERROR(INDEX('Bond Rules'!$B$4:$B$7,MATCH(K78,'Bond Rules'!$A$4:$A$7,0)),"") -> 4 | N78: =IFERROR(ROUND('Bond Rules'!$B$9+L78*INDEX('Bond Rules'!$C$4:$C$7,MATCH(K78,'Bond Rules'!$A$4:$A$7,0)),2),"") -> 2.58
A79: MET-1b | B79: Metal | C79: 1 | D79: Rust | E79: 🜕 | F79: MET-1a | G79: =IFERROR(INDEX($D:$D,MATCH($F79,$A:$A,0)),"") -> Forge | H79: =IFERROR(INDEX($E:$E,MATCH($F79,$A:$A,0)),"") -> 🜔 | I79: =Metal!$E$7 -> corrode it | J79: U+1F715 | K79: Link | L79: -0.5 | M79: =IFERROR(INDEX('Bond Rules'!$B$4:$B$7,MATCH(K79,'Bond Rules'!$A$4:$A$7,0)),"") -> 2 | N79: =IFERROR(ROUND('Bond Rules'!$B$9+L79*INDEX('Bond Rules'!$C$4:$C$7,MATCH(K79,'Bond Rules'!$A$4:$A$7,0)),2),"") -> 2
A80: MET-2a | B80: Metal | C80: 2 | D80: Fuse | E80: 🜖 | F80: MET-2b | G80: =IFERROR(INDEX($D:$D,MATCH($F80,$A:$A,0)),"") -> Sunder | H80: =IFERROR(INDEX($E:$E,MATCH($F80,$A:$A,0)),"") -> 🜗 | I80: =Metal!$E$8 -> join metal into one piece | J80: U+1F716 | K80: Frame | L80: 0.5 | M80: =IFERROR(INDEX('Bond Rules'!$B$4:$B$7,MATCH(K80,'Bond Rules'!$A$4:$A$7,0)),"") -> 4 | N80: =IFERROR(ROUND('Bond Rules'!$B$9+L80*INDEX('Bond Rules'!$C$4:$C$7,MATCH(K80,'Bond Rules'!$A$4:$A$7,0)),2),"") -> 2.7
A81: MET-2b | B81: Metal | C81: 2 | D81: Sunder | E81: 🜗 | F81: MET-2a | G81: =IFERROR(INDEX($D:$D,MATCH($F81,$A:$A,0)),"") -> Fuse | H81: =IFERROR(INDEX($E:$E,MATCH($F81,$A:$A,0)),"") -> 🜖 | I81: =Metal!$E$9 -> split it apart | J81: U+1F717 | K81: Branch | L81: -0.7 | M81: =IFERROR(INDEX('Bond Rules'!$B$4:$B$7,MATCH(K81,'Bond Rules'!$A$4:$A$7,0)),"") -> 3 | N81: =IFERROR(ROUND('Bond Rules'!$B$9+L81*INDEX('Bond Rules'!$C$4:$C$7,MATCH(K81,'Bond Rules'!$A$4:$A$7,0)),2),"") -> 2.01
A82: MET-3a | B82: Metal | C82: 3 | D82: Seal | E82: 🜘 | F82: MET-3b | G82: =IFERROR(INDEX($D:$D,MATCH($F82,$A:$A,0)),"") -> Breach | H82: =IFERROR(INDEX($E:$E,MATCH($F82,$A:$A,0)),"") -> 🜙 | I82: =Metal!$E$10 -> close and lock with metal | J82: U+1F718 | K82: Cap | L82: 0.6 | M82: =IFERROR(INDEX('Bond Rules'!$B$4:$B$7,MATCH(K82,'Bond Rules'!$A$4:$A$7,0)),"") -> 1 | N82: =IFERROR(ROUND('Bond Rules'!$B$9+L82*INDEX('Bond Rules'!$C$4:$C$7,MATCH(K82,'Bond Rules'!$A$4:$A$7,0)),2),"") -> 3.4
A83: MET-3b | B83: Metal | C83: 3 | D83: Breach | E83: 🜙 | F83: MET-3a | G83: =IFERROR(INDEX($D:$D,MATCH($F83,$A:$A,0)),"") -> Seal | H83: =IFERROR(INDEX($E:$E,MATCH($F83,$A:$A,0)),"") -> 🜘 | I83: =Metal!$E$11 -> break a seal; punch through plate | J83: U+1F719 | K83: Link | L83: -0.6 | M83: =IFERROR(INDEX('Bond Rules'!$B$4:$B$7,MATCH(K83,'Bond Rules'!$A$4:$A$7,0)),"") -> 2 | N83: =IFERROR(ROUND('Bond Rules'!$B$9+L83*INDEX('Bond Rules'!$C$4:$C$7,MATCH(K83,'Bond Rules'!$A$4:$A$7,0)),2),"") -> 1.9
A84: MET-4a | B84: Metal | C84: 4 | D84: Hone | E84: 🜚 | F84: MET-4b | G84: =IFERROR(INDEX($D:$D,MATCH($F84,$A:$A,0)),"") -> Dull | H84: =IFERROR(INDEX($E:$E,MATCH($F84,$A:$A,0)),"") -> 🜛 | I84: =Metal!$E$12 -> sharpen | J84: U+1F71A | K84: Link | L84: 0.5 | M84: =IFERROR(INDEX('Bond Rules'!$B$4:$B$7,MATCH(K84,'Bond Rules'!$A$4:$A$7,0)),"") -> 2 | N84: =IFERROR(ROUND('Bond Rules'!$B$9+L84*INDEX('Bond Rules'!$C$4:$C$7,MATCH(K84,'Bond Rules'!$A$4:$A$7,0)),2),"") -> 3
A85: MET-4b | B85: Metal | C85: 4 | D85: Dull | E85: 🜛 | F85: MET-4a | G85: =IFERROR(INDEX($D:$D,MATCH($F85,$A:$A,0)),"") -> Hone | H85: =IFERROR(INDEX($E:$E,MATCH($F85,$A:$A,0)),"") -> 🜚 | I85: =Metal!$E$13 -> blunt edges, theirs included | J85: U+1F71B | K85: Link | L85: -0.4 | M85: =IFERROR(INDEX('Bond Rules'!$B$4:$B$7,MATCH(K85,'Bond Rules'!$A$4:$A$7,0)),"") -> 2 | N85: =IFERROR(ROUND('Bond Rules'!$B$9+L85*INDEX('Bond Rules'!$C$4:$C$7,MATCH(K85,'Bond Rules'!$A$4:$A$7,0)),2),"") -> 2.1
A86: MET-5a | B86: Metal | C86: 5 | D86: Plate | E86: 🜜 | F86: MET-5b | G86: =IFERROR(INDEX($D:$D,MATCH($F86,$A:$A,0)),"") -> Strip | H86: =IFERROR(INDEX($E:$E,MATCH($F86,$A:$A,0)),"") -> 🜝 | I86: =Metal!$E$14 -> armour up | J86: U+1F71C | K86: Frame | L86: -0.2 | M86: =IFERROR(INDEX('Bond Rules'!$B$4:$B$7,MATCH(K86,'Bond Rules'!$A$4:$A$7,0)),"") -> 4 | N86: =IFERROR(ROUND('Bond Rules'!$B$9+L86*INDEX('Bond Rules'!$C$4:$C$7,MATCH(K86,'Bond Rules'!$A$4:$A$7,0)),2),"") -> 2.42
A87: MET-5b | B87: Metal | C87: 5 | D87: Strip | E87: 🜝 | F87: MET-5a | G87: =IFERROR(INDEX($D:$D,MATCH($F87,$A:$A,0)),"") -> Plate | H87: =IFERROR(INDEX($E:$E,MATCH($F87,$A:$A,0)),"") -> 🜜 | I87: =Metal!$E$15 -> tear armour off | J87: U+1F71D | K87: Cap | L87: 0.6 | M87: =IFERROR(INDEX('Bond Rules'!$B$4:$B$7,MATCH(K87,'Bond Rules'!$A$4:$A$7,0)),"") -> 1 | N87: =IFERROR(ROUND('Bond Rules'!$B$9+L87*INDEX('Bond Rules'!$C$4:$C$7,MATCH(K87,'Bond Rules'!$A$4:$A$7,0)),2),"") -> 3.4
A88: BLD-1a | B88: Blood | C88: 1 | D88: Bleed | E88: 🜞 | F88: BLD-1b | G88: =IFERROR(INDEX($D:$D,MATCH($F88,$A:$A,0)),"") -> Staunch | H88: =IFERROR(INDEX($E:$E,MATCH($F88,$A:$A,0)),"") -> 🜟 | I88: =Blood!$E$6 -> open wounds | J88: U+1F71E | K88: Link | L88: -0.6 | M88: =IFERROR(INDEX('Bond Rules'!$B$4:$B$7,MATCH(K88,'Bond Rules'!$A$4:$A$7,0)),"") -> 2 | N88: =IFERROR(ROUND('Bond Rules'!$B$9+L88*INDEX('Bond Rules'!$C$4:$C$7,MATCH(K88,'Bond Rules'!$A$4:$A$7,0)),2),"") -> 1.9
A89: BLD-1b | B89: Blood | C89: 1 | D89: Staunch | E89: 🜟 | F89: BLD-1a | G89: =IFERROR(INDEX($D:$D,MATCH($F89,$A:$A,0)),"") -> Bleed | H89: =IFERROR(INDEX($E:$E,MATCH($F89,$A:$A,0)),"") -> 🜞 | I89: =Blood!$E$7 -> close them | J89: U+1F71F | K89: Cap | L89: 0.5 | M89: =IFERROR(INDEX('Bond Rules'!$B$4:$B$7,MATCH(K89,'Bond Rules'!$A$4:$A$7,0)),"") -> 1 | N89: =IFERROR(ROUND('Bond Rules'!$B$9+L89*INDEX('Bond Rules'!$C$4:$C$7,MATCH(K89,'Bond Rules'!$A$4:$A$7,0)),2),"") -> 3.25
A90: BLD-2a | B90: Blood | C90: 2 | D90: Drink | E90: 🜠 | F90: BLD-2b | G90: =IFERROR(INDEX($D:$D,MATCH($F90,$A:$A,0)),"") -> Spill | H90: =IFERROR(INDEX($E:$E,MATCH($F90,$A:$A,0)),"") -> 🜡 | I90: =Blood!$E$8 -> take blood in | J90: U+1F720 | K90: Link | L90: 1 | M90: =IFERROR(INDEX('Bond Rules'!$B$4:$B$7,MATCH(K90,'Bond Rules'!$A$4:$A$7,0)),"") -> 2 | N90: =IFERROR(ROUND('Bond Rules'!$B$9+L90*INDEX('Bond Rules'!$C$4:$C$7,MATCH(K90,'Bond Rules'!$A$4:$A$7,0)),2),"") -> 3.5
A91: BLD-2b | B91: Blood | C91: 2 | D91: Spill | E91: 🜡 | F91: BLD-2a | G91: =IFERROR(INDEX($D:$D,MATCH($F91,$A:$A,0)),"") -> Drink | H91: =IFERROR(INDEX($E:$E,MATCH($F91,$A:$A,0)),"") -> 🜠 | I91: =Blood!$E$9 -> give it out, as a weapon or a gift | J91: U+1F721 | K91: Branch | L91: -0.8 | M91: =IFERROR(INDEX('Bond Rules'!$B$4:$B$7,MATCH(K91,'Bond Rules'!$A$4:$A$7,0)),"") -> 3 | N91: =IFERROR(ROUND('Bond Rules'!$B$9+L91*INDEX('Bond Rules'!$C$4:$C$7,MATCH(K91,'Bond Rules'!$A$4:$A$7,0)),2),"") -> 1.94
A92: BLD-3a | B92: Blood | C92: 3 | D92: Clot | E92: 🜢 | F92: BLD-3b | G92: =IFERROR(INDEX($D:$D,MATCH($F92,$A:$A,0)),"") -> Thin | H92: =IFERROR(INDEX($E:$E,MATCH($F92,$A:$A,0)),"") -> 🜣 | I92: =Blood!$E$10 -> blood hardens: armour, blades, a stopped wound | J92: U+1F722 | K92: Frame | L92: 0.4 | M92: =IFERROR(INDEX('Bond Rules'!$B$4:$B$7,MATCH(K92,'Bond Rules'!$A$4:$A$7,0)),"") -> 4 | N92: =IFERROR(ROUND('Bond Rules'!$B$9+L92*INDEX('Bond Rules'!$C$4:$C$7,MATCH(K92,'Bond Rules'!$A$4:$A$7,0)),2),"") -> 2.66
A93: BLD-3b | B93: Blood | C93: 3 | D93: Thin | E93: 🜣 | F93: BLD-3a | G93: =IFERROR(INDEX($D:$D,MATCH($F93,$A:$A,0)),"") -> Clot | H93: =IFERROR(INDEX($E:$E,MATCH($F93,$A:$A,0)),"") -> 🜢 | I93: =Blood!$E$11 -> blood runs quick: speed, reach | J93: U+1F723 | K93: Link | L93: -0.4 | M93: =IFERROR(INDEX('Bond Rules'!$B$4:$B$7,MATCH(K93,'Bond Rules'!$A$4:$A$7,0)),"") -> 2 | N93: =IFERROR(ROUND('Bond Rules'!$B$9+L93*INDEX('Bond Rules'!$C$4:$C$7,MATCH(K93,'Bond Rules'!$A$4:$A$7,0)),2),"") -> 2.1
A94: BLD-4a | B94: Blood | C94: 4 | D94: Pulse | E94: 🜤 | F94: BLD-4b | G94: =IFERROR(INDEX($D:$D,MATCH($F94,$A:$A,0)),"") -> Still | H94: =IFERROR(INDEX($E:$E,MATCH($F94,$A:$A,0)),"") -> 🜥 | I94: =Blood!$E$12 -> the heart pounds | J94: U+1F724 | K94: Link | L94: -0.3 | M94: =IFERROR(INDEX('Bond Rules'!$B$4:$B$7,MATCH(K94,'Bond Rules'!$A$4:$A$7,0)),"") -> 2 | N94: =IFERROR(ROUND('Bond Rules'!$B$9+L94*INDEX('Bond Rules'!$C$4:$C$7,MATCH(K94,'Bond Rules'!$A$4:$A$7,0)),2),"") -> 2.2
A95: BLD-4b | B95: Blood | C95: 4 | D95: Still | E95: 🜥 | F95: BLD-4a | G95: =IFERROR(INDEX($D:$D,MATCH($F95,$A:$A,0)),"") -> Pulse | H95: =IFERROR(INDEX($E:$E,MATCH($F95,$A:$A,0)),"") -> 🜤 | I95: =Blood!$E$13 -> the heart slows | J95: U+1F725 | K95: Cap | L95: 0.4 | M95: =IFERROR(INDEX('Bond Rules'!$B$4:$B$7,MATCH(K95,'Bond Rules'!$A$4:$A$7,0)),"") -> 1 | N95: =IFERROR(ROUND('Bond Rules'!$B$9+L95*INDEX('Bond Rules'!$C$4:$C$7,MATCH(K95,'Bond Rules'!$A$4:$A$7,0)),2),"") -> 3.1
A96: BLD-5a | B96: Blood | C96: 5 | D96: Choke | E96: 🜦 | F96: BLD-5b | G96: =IFERROR(INDEX($D:$D,MATCH($F96,$A:$A,0)),"") -> Breathe | H96: =IFERROR(INDEX($E:$E,MATCH($F96,$A:$A,0)),"") -> 🜧 | I96: =Blood!$E$14 -> cut off breath | J96: U+1F726 | K96: Cap | L96: 0.9 | M96: =IFERROR(INDEX('Bond Rules'!$B$4:$B$7,MATCH(K96,'Bond Rules'!$A$4:$A$7,0)),"") -> 1 | N96: =IFERROR(ROUND('Bond Rules'!$B$9+L96*INDEX('Bond Rules'!$C$4:$C$7,MATCH(K96,'Bond Rules'!$A$4:$A$7,0)),2),"") -> 3.85
A97: BLD-5b | B97: Blood | C97: 5 | D97: Breathe | E97: 🜧 | F97: BLD-5a | G97: =IFERROR(INDEX($D:$D,MATCH($F97,$A:$A,0)),"") -> Choke | H97: =IFERROR(INDEX($E:$E,MATCH($F97,$A:$A,0)),"") -> 🜦 | I97: =Blood!$E$15 -> give breath; steady the body | J97: U+1F727 | K97: Link | L97: -0.6 | M97: =IFERROR(INDEX('Bond Rules'!$B$4:$B$7,MATCH(K97,'Bond Rules'!$A$4:$A$7,0)),"") -> 2 | N97: =IFERROR(ROUND('Bond Rules'!$B$9+L97*INDEX('Bond Rules'!$C$4:$C$7,MATCH(K97,'Bond Rules'!$A$4:$A$7,0)),2),"") -> 1.9
A98: LIF-1a | B98: Life | C98: 1 | D98: Heal | E98: 🜨 | F98: LIF-1b | G98: =IFERROR(INDEX($D:$D,MATCH($F98,$A:$A,0)),"") -> Wither | H98: =IFERROR(INDEX($E:$E,MATCH($F98,$A:$A,0)),"") -> 🜩 | I98: =Life!$E$6 -> restore health and close wounds | J98: U+1F728 | K98: Frame | L98: -0.3 | M98: =IFERROR(INDEX('Bond Rules'!$B$4:$B$7,MATCH(K98,'Bond Rules'!$A$4:$A$7,0)),"") -> 4 | N98: =IFERROR(ROUND('Bond Rules'!$B$9+L98*INDEX('Bond Rules'!$C$4:$C$7,MATCH(K98,'Bond Rules'!$A$4:$A$7,0)),2),"") -> 2.38
A99: LIF-1b | B99: Life | C99: 1 | D99: Wither | E99: 🜩 | F99: LIF-1a | G99: =IFERROR(INDEX($D:$D,MATCH($F99,$A:$A,0)),"") -> Heal | H99: =IFERROR(INDEX($E:$E,MATCH($F99,$A:$A,0)),"") -> 🜨 | I99: =Life!$E$7 -> harm from within | J99: U+1F729 | K99: Link | L99: 0.6 | M99: =IFERROR(INDEX('Bond Rules'!$B$4:$B$7,MATCH(K99,'Bond Rules'!$A$4:$A$7,0)),"") -> 2 | N99: =IFERROR(ROUND('Bond Rules'!$B$9+L99*INDEX('Bond Rules'!$C$4:$C$7,MATCH(K99,'Bond Rules'!$A$4:$A$7,0)),2),"") -> 3.1
A100: LIF-2a | B100: Life | C100: 2 | D100: Renew | E100: 🜪 | F100: LIF-2b | G100: =IFERROR(INDEX($D:$D,MATCH($F100,$A:$A,0)),"") -> Exhaust | H100: =IFERROR(INDEX($E:$E,MATCH($F100,$A:$A,0)),"") -> 🜫 | I100: =Life!$E$8 -> restore vigour and stamina | J100: U+1F72A | K100: Branch | L100: -0.5 | M100: =IFERROR(INDEX('Bond Rules'!$B$4:$B$7,MATCH(K100,'Bond Rules'!$A$4:$A$7,0)),"") -> 3 | N100: =IFERROR(ROUND('Bond Rules'!$B$9+L100*INDEX('Bond Rules'!$C$4:$C$7,MATCH(K100,'Bond Rules'!$A$4:$A$7,0)),2),"") -> 2.15
...

Sheet Universal Runes
A1: ID | B1: Rune | C1: Character | D1: Opposite ID | E1: Opposite | F1: Opposite character | G1: As a means | H1: Effect (game)
A2: UNI-01a | B2: Motion | C2: ⇢ | D2: UNI-01b | E2: =IFERROR(INDEX($B:$B,MATCH($D2,$A:$A,0)),"") -> Stillness | F2: =IFERROR(INDEX($C:$C,MATCH($D2,$A:$A,0)),"") -> ⊡ | G2: it travels, or moves what it touches | H2: speed x1.25
A3: UNI-01b | B3: Stillness | C3: ⊡ | D3: UNI-01a | E3: =IFERROR(INDEX($B:$B,MATCH($D3,$A:$A,0)),"") -> Motion | F3: =IFERROR(INDEX($C:$C,MATCH($D3,$A:$A,0)),"") -> ⇢ | G3: it is held in place; what it touches is held | H3: duration x1.4; speed x0.8
A4: UNI-02a | B4: Haste | C4: » | D4: UNI-02b | E4: =IFERROR(INDEX($B:$B,MATCH($D4,$A:$A,0)),"") -> Delay | F4: =IFERROR(INDEX($C:$C,MATCH($D4,$A:$A,0)),"") -> « | G4: sooner and faster | H4: windup x0.75
A5: UNI-02b | B5: Delay | C5: « | D5: UNI-02a | E5: =IFERROR(INDEX($B:$B,MATCH($D5,$A:$A,0)),"") -> Haste | F5: =IFERROR(INDEX($C:$C,MATCH($D5,$A:$A,0)),"") -> » | G5: later: delayed, built up | H5: power x1.3; windup x1.4
A6: UNI-03a | B6: Curve | C6: ↷ | D6: UNI-03b | E6: =IFERROR(INDEX($B:$B,MATCH($D6,$A:$A,0)),"") -> Straight | F6: =IFERROR(INDEX($C:$C,MATCH($D6,$A:$A,0)),"") -> ⇥ | G6: it bends and seeks | H6: reach x1.1; power x1.05
A7: UNI-03b | B7: Straight | C7: ⇥ | D7: UNI-03a | E7: =IFERROR(INDEX($B:$B,MATCH($D7,$A:$A,0)),"") -> Curve | F7: =IFERROR(INDEX($C:$C,MATCH($D7,$A:$A,0)),"") -> ↷ | G7: a true line that cannot be turned aside | H7: speed x1.2; reach x1.1
A8: UNI-04a | B8: Rise | C8: ↑ | D8: UNI-04b | E8: =IFERROR(INDEX($B:$B,MATCH($D8,$A:$A,0)),"") -> Fall | F8: =IFERROR(INDEX($C:$C,MATCH($D8,$A:$A,0)),"") -> ↓ | G8: lifts | H8: status aloft
A9: UNI-04b | B9: Fall | C9: ↓ | D9: UNI-04a | E9: =IFERROR(INDEX($B:$B,MATCH($D9,$A:$A,0)),"") -> Rise | F9: =IFERROR(INDEX($C:$C,MATCH($D9,$A:$A,0)),"") -> ↑ | G9: brings down, knocks flat | H9: poise x1.3
A10: UNI-05a | B10: Expand | C10: ◯ | D10: UNI-05b | E10: =IFERROR(INDEX($B:$B,MATCH($D10,$A:$A,0)),"") -> Contract | F10: =IFERROR(INDEX($C:$C,MATCH($D10,$A:$A,0)),"") -> ◉ | G10: grows outward, bigger | H10: reach x1.3; power x0.9
A11: UNI-05b | B11: Contract | C11: ◉ | D11: UNI-05a | E11: =IFERROR(INDEX($B:$B,MATCH($D11,$A:$A,0)),"") -> Expand | F11: =IFERROR(INDEX($C:$C,MATCH($D11,$A:$A,0)),"") -> ◯ | G11: draws inward, smaller and denser | H11: reach x0.8; power x1.25
A12: UNI-06a | B12: Near | C12: ⊚ | D12: UNI-06b | E12: =IFERROR(INDEX($B:$B,MATCH($D12,$A:$A,0)),"") -> Far | F12: =IFERROR(INDEX($C:$C,MATCH($D12,$A:$A,0)),"") -> ⋯ | G12: close, and stronger close | H12: power x1.2; reach x0.85
A13: UNI-06b | B13: Far | C13: ⋯ | D13: UNI-06a | E13: =IFERROR(INDEX($B:$B,MATCH($D13,$A:$A,0)),"") -> Near | F13: =IFERROR(INDEX($C:$C,MATCH($D13,$A:$A,0)),"") -> ⊚ | G13: at a distance, with reach | H13: reach x1.4; power x0.9
... A57: UNI-28b | B57: Chance | C57: ⚄ | D57: UNI-28a | E57: =IFERROR(INDEX($B:$B,MATCH($D57,$A:$A,0)),"") -> Fate | F57: =IFERROR(INDEX($C:$C,MATCH($D57,$A:$A,0)),"") -> ⊜ | G57: random | H57: power x1.2; cost x1.1

Sheet Bond Rules
A1: Bond rules
A3: Role | B3: Valence | C3: Electronegativity spread | D3: What the role means | E3: The chemistry it mirrors
A4: Cap | B4: 1 | C4: 1.5 | D4: Ends a structure: a finisher, or a pure state. | E4: Hydrogen, fluorine, sodium: one bond, and the most extreme pull or push.
A5: Link | B5: 2 | C5: 1 | D5: Takes something in and passes it on. | E5: Oxygen: two bonds.
A6: Branch | B6: 3 | C6: 0.7 | D6: Spreads, splits or multiplies. | E6: Nitrogen: three bonds.
A7: Frame | B7: 4 | C7: 0.4 | D7: Holds a structure together. | E7: Carbon: four bonds and a middling pull, the backbone that bonds with almost anything.
A9: Electronegativity centre | B9: 2.5
A10: A rune's electronegativity = centre + draw x its role's spread. Draw runs from -1 (the rune gives or releases outward) to +1 (it takes or holds inward). Valence comes from the role. So a Cap sits at the extremes (1.0 to 4.0) and a Frame near the centre (2.1 to 2.9), as in real chemistry: the elements with the fewest bonds pull hardest or give most easily, and carbon, with four, sits in the middle and bonds with everything.
A12: Bond kind | B12: Difference from | C12: What it means in a word
A13: Even | B13: 0 | C13: The two runes blend equally.
A14: Polar | B14: 0.4 | C14: The rune with more pull dominates; the other colours it.
A15: Ionic | B15: 1.7 | C15: One rune hands its effect to the other outright: a transfer.
A17: Single bonds only, no handedness (Brent, 2026-10-22). Bond strength (Pauling: the bigger the difference, the stronger the bond) and how affinity alignment multiplies it are not given numbers yet.
A19: Rune effects: layers 1-3 (first pass, 2026-10-22)
A20: Layer 1: each rune's Effect (game) on Base Runes and Universal Runes. Layer 2: the bond a rune reaches the skill through scales it by bond kind. Layer 3: it fades with each bond between it and the skill's own rune. Effects only count once the word is locked.
A22: Bonds from the skill's rune | B22: Strength
A23: 1 | B23: 1
A24: 2 | B24: 0.6
A25: 3 | B25: 0.35
A26: 4 or more | B26: 0.2
A28: Bond kind | B28: Rune with more pull | C28: Rune with less pull | D28: Meaning
A29: Even | B29: 0.75 | C29: 0.75 | D29: both blend, each at three-quarters
A30: Polar | B30: 1 | C30: 0.5 | D30: the rune with more pull dominates; the other colours it
A31: Ionic | B31: 1.5 | C31: 0 | D31: the weaker rune hands its effect over: the stronger one is amplified, the weaker one's own effect is gone
A33: A status applies when strength is at least | B33: 0.5
A34: Lowest multiplier a stat group can reach | B34: 0.4
A35: Highest multiplier a stat group can reach | B35: 2.5
A36: A word must be closed to lock (1 yes, 0 no) | B36: 1
A38: The skill's own rune: its Effect names what the skill already does (Surge: the shove). Its bond factors scale that part of the skill, averaged over its bonds: bonded ionically to a stronger rune, Water Bolt loses its shove.
A40: Effect syntax (one op per ";"): <group> x<m> multiplies every field of a stat group the skill has: power (damage), reach (range, radius, arc, width), speed, cost, reflux, windup (wind-up and recovery), duration, poise. Also: status <id> [n], shove +<m>, pull +<m>, marks +<n>, jumps +<n>, pierce +<n>, interrupts, braced, bonus <status> +<fraction>. Strength scales each: a multiplier m becomes 1 + (m - 1) x strength; an amount is multiplied by strength. A skill without a group's fields takes a quarter of the change as power instead, so no rune does nothing.

Sheet Water
A1: Water
A2: Rule: Moves bodies (shove and Crush); works the water that is already there (wetness)
A3: Deep dive: design/affinities/water.md Status: Deep dive v0. Source: existing (design/05); MODEL: wetness, from C.
A5: Pair | B5: ID | C5: Rune | D5: Character | E5: As a skill (the verb a skill is built on) | F5: As a means (added to another skill) | G5: Opposite | H5: Together (rune + opposite release) | I5: Skills on it | J5: Notes
A6: 1 | B6: WAT-1a | C6: =IFERROR(INDEX('Base Runes'!$D:$D,MATCH($B6,'Base Runes'!$A:$A,0)),"") -> Flood | D6: =IFERROR(INDEX('Base Runes'!$E:$E,MATCH($B6,'Base Runes'!$A:$A,0)),"") -> ᚠ | E6: fill an area with water; the ground turns Wet | F6: range and area +20%; applies Soaked | G6: =IFERROR(INDEX('Base Runes'!$G:$G,MATCH($B6,'Base Runes'!$A:$A,0)),"") -> Drain | I6: Standing Pool | J6: Proposed skill: Draw Water
A7: 1 | B7: WAT-1b | C7: =IFERROR(INDEX('Base Runes'!$D:$D,MATCH($B7,'Base Runes'!$A:$A,0)),"") -> Drain | D7: =IFERROR(INDEX('Base Runes'!$E:$E,MATCH($B7,'Base Runes'!$A:$A,0)),"") -> ᚡ | E7: empty the water from an area or a target, and draw it in | F7: +25% damage to Soaked targets; essence cost -10% | G7: =IFERROR(INDEX('Base Runes'!$G:$G,MATCH($B7,'Base Runes'!$A:$A,0)),"") -> Flood
A8: 2 | B8: WAT-2a | C8: =IFERROR(INDEX('Base Runes'!$D:$D,MATCH($B8,'Base Runes'!$A:$A,0)),"") -> Surge | D8: =IFERROR(INDEX('Base Runes'!$E:$E,MATCH($B8,'Base Runes'!$A:$A,0)),"") -> ᚢ | E8: push bodies away | F8: adds a shove away from you | G8: =IFERROR(INDEX('Base Runes'!$G:$G,MATCH($B8,'Base Runes'!$A:$A,0)),"") -> Ebb | H8: Churn: a whirlpool that spins bodies and holds them in place | I8: Water Bolt (starter), Breaker (starter)
A9: 2 | B9: WAT-2b | C9: =IFERROR(INDEX('Base Runes'!$D:$D,MATCH($B9,'Base Runes'!$A:$A,0)),"") -> Ebb | D9: =IFERROR(INDEX('Base Runes'!$E:$E,MATCH($B9,'Base Runes'!$A:$A,0)),"") -> ᚣ | E9: draw bodies in | F9: adds a drag toward you | G9: =IFERROR(INDEX('Base Runes'!$G:$G,MATCH($B9,'Base Runes'!$A:$A,0)),"") -> Surge | H9: Churn: a whirlpool that spins bodies and holds them in place | I9: Undertow, Riptide Lash
A10: 3 | B10: WAT-3a | C10: =IFERROR(INDEX('Base Runes'!$D:$D,MATCH($B10,'Base Runes'!$A:$A,0)),"") -> Soak | D10: =IFERROR(INDEX('Base Runes'!$E:$E,MATCH($B10,'Base Runes'!$A:$A,0)),"") -> ᚤ | E10: saturate a target | F10: applies Soaked | G10: =IFERROR(INDEX('Base Runes'!$G:$G,MATCH($B10,'Base Runes'!$A:$A,0)),"") -> Dry | H10: Rinse: washes every status off, good and bad
A11: 3 | B11: WAT-3b | C11: =IFERROR(INDEX('Base Runes'!$D:$D,MATCH($B11,'Base Runes'!$A:$A,0)),"") -> Dry | D11: =IFERROR(INDEX('Base Runes'!$E:$E,MATCH($B11,'Base Runes'!$A:$A,0)),"") -> ᚥ | E11: pull the water out of a body: damage by how wet it is | F11: consumes Soaked for extra damage | G11: =IFERROR(INDEX('Base Runes'!$G:$G,MATCH($B11,'Base Runes'!$A:$A,0)),"") -> Soak | H11: Rinse: washes every status off, good and bad | J11: Proposed skill: Wringing Grip
A12: 4 | B12: WAT-4a | C12: =IFERROR(INDEX('Base Runes'!$D:$D,MATCH($B12,'Base Runes'!$A:$A,0)),"") -> Float | D12: =IFERROR(INDEX('Base Runes'!$E:$E,MATCH($B12,'Base Runes'!$A:$A,0)),"") -> ᚦ | E12: buoyancy: lift, lighten, walk on water | F12: lifts: lightens, slows falls | G12: =IFERROR(INDEX('Base Runes'!$G:$G,MATCH($B12,'Base Runes'!$A:$A,0)),"") -> Drown | H12: Depth: pinned under; the target cannot jump, blink or be lifted
A13: 4 | B13: WAT-4b | C13: =IFERROR(INDEX('Base Runes'!$D:$D,MATCH($B13,'Base Runes'!$A:$A,0)),"") -> Drown | D13: =IFERROR(INDEX('Base Runes'!$E:$E,MATCH($B13,'Base Runes'!$A:$A,0)),"") -> ᚧ | E13: water in the lungs: no casting, no calls for help, damage over time | F13: silences | G13: =IFERROR(INDEX('Base Runes'!$G:$G,MATCH($B13,'Base Runes'!$A:$A,0)),"") -> Float | H13: Depth: pinned under; the target cannot jump, blink or be lifted | J13: Proposed skill: Drowning Hold
A14: 5 | B14: WAT-5a | C14: =IFERROR(INDEX('Base Runes'!$D:$D,MATCH($B14,'Base Runes'!$A:$A,0)),"") -> Gush | D14: =IFERROR(INDEX('Base Runes'!$E:$E,MATCH($B14,'Base Runes'!$A:$A,0)),"") -> ᚨ | E14: a sudden forceful jet | F14: speed +30%; damage +10% | G14: =IFERROR(INDEX('Base Runes'!$G:$G,MATCH($B14,'Base Runes'!$A:$A,0)),"") -> Drip | I14: Pressure Jet
A15: 5 | B15: WAT-5b | C15: =IFERROR(INDEX('Base Runes'!$D:$D,MATCH($B15,'Base Runes'!$A:$A,0)),"") -> Drip | D15: =IFERROR(INDEX('Base Runes'!$E:$E,MATCH($B15,'Base Runes'!$A:$A,0)),"") -> ᚩ | E15: a slow steady trickle that wears and lingers | F15: duration +40%; essence cost -15% | G15: =IFERROR(INDEX('Base Runes'!$G:$G,MATCH($B15,'Base Runes'!$A:$A,0)),"") -> Gush
A16: 6 | B16: WAT-6a | C16: =IFERROR(INDEX('Base Runes'!$D:$D,MATCH($B16,'Base Runes'!$A:$A,0)),"") -> Sweep | D16: =IFERROR(INDEX('Base Runes'!$E:$E,MATCH($B16,'Base Runes'!$A:$A,0)),"") -> ᚪ | E16: a current that carries things along | F16: range and area +30% | G16: =IFERROR(INDEX('Base Runes'!$G:$G,MATCH($B16,'Base Runes'!$A:$A,0)),"") -> Settle | I16: Sluice Step (starter)
A17: 6 | B17: WAT-6b | C17: =IFERROR(INDEX('Base Runes'!$D:$D,MATCH($B17,'Base Runes'!$A:$A,0)),"") -> Settle | D17: =IFERROR(INDEX('Base Runes'!$E:$E,MATCH($B17,'Base Runes'!$A:$A,0)),"") -> ᚫ | E17: the water goes still, and what it carries sinks and stays | F17: applies Mired | G17: =IFERROR(INDEX('Base Runes'!$G:$G,MATCH($B17,'Base Runes'!$A:$A,0)),"") -> Sweep
A18: 7 | B18: WAT-7a | C18: =IFERROR(INDEX('Base Runes'!$D:$D,MATCH($B18,'Base Runes'!$A:$A,0)),"") -> Splash | D18: =IFERROR(INDEX('Base Runes'!$E:$E,MATCH($B18,'Base Runes'!$A:$A,0)),"") -> ᚬ | E18: burst outward on contact, spraying those near | F18: range and area +25%; damage -10% | G18: =IFERROR(INDEX('Base Runes'!$G:$G,MATCH($B18,'Base Runes'!$A:$A,0)),"") -> Seep | I18: Backwash
A19: 7 | B19: WAT-7b | C19: =IFERROR(INDEX('Base Runes'!$D:$D,MATCH($B19,'Base Runes'!$A:$A,0)),"") -> Seep | D19: =IFERROR(INDEX('Base Runes'!$E:$E,MATCH($B19,'Base Runes'!$A:$A,0)),"") -> ᚭ | E19: soak in slowly, getting behind shields and armour | F19: passes through one more | G19: =IFERROR(INDEX('Base Runes'!$G:$G,MATCH($B19,'Base Runes'!$A:$A,0)),"") -> Splash
A20: 8 | B20: WAT-8a | C20: =IFERROR(INDEX('Base Runes'!$D:$D,MATCH($B20,'Base Runes'!$A:$A,0)),"") -> Wave | D20: =IFERROR(INDEX('Base Runes'!$E:$E,MATCH($B20,'Base Runes'!$A:$A,0)),"") -> ᚮ | E20: a rolling wall of water | F20: range and area +20%; poise damage +30% | G20: =IFERROR(INDEX('Base Runes'!$G:$G,MATCH($B20,'Base Runes'!$A:$A,0)),"") -> Slack
A21: 8 | B21: WAT-8b | C21: =IFERROR(INDEX('Base Runes'!$D:$D,MATCH($B21,'Base Runes'!$A:$A,0)),"") -> Slack | D21: =IFERROR(INDEX('Base Runes'!$E:$E,MATCH($B21,'Base Runes'!$A:$A,0)),"") -> ᚯ | E21: the still moment at the turn of the tide: everything pauses, reflux eases | F21: reflux left -25% | G21: =IFERROR(INDEX('Base Runes'!$G:$G,MATCH($B21,'Base Runes'!$A:$A,0)),"") -> Wave
A23: Blue: type here. Green: pulled from Base Runes (rename a rune or change its character there). Yellow: not written yet.

Sheet Fire
A1: Fire
A2: Rule: Runs on its own heat
A3: Status: First pass.
A5: Pair | B5: ID | C5: Rune | D5: Character | E5: As a skill (the verb a skill is built on) | F5: As a means (added to another skill) | G5: Opposite | H5: Together (rune + opposite release) | I5: Skills on it | J5: Notes
A6: 1 | B6: FIR-1a | C6: =IFERROR(INDEX('Base Runes'!$D:$D,MATCH($B6,'Base Runes'!$A:$A,0)),"") -> Burn | D6: =IFERROR(INDEX('Base Runes'!$E:$E,MATCH($B6,'Base Runes'!$A:$A,0)),"") -> ᚰ | E6: set a target burning (Alight) | F6: applies Alight | G6: =IFERROR(INDEX('Base Runes'!$G:$G,MATCH($B6,'Base Runes'!$A:$A,0)),"") -> Quench | I6: Kiln Fist
A7: 1 | B7: FIR-1b | C7: =IFERROR(INDEX('Base Runes'!$D:$D,MATCH($B7,'Base Runes'!$A:$A,0)),"") -> Quench | D7: =IFERROR(INDEX('Base Runes'!$E:$E,MATCH($B7,'Base Runes'!$A:$A,0)),"") -> ᚱ | E7: put fire out, and cash the heat in | F7: reflux left -30%; damage +10% | G7: =IFERROR(INDEX('Base Runes'!$G:$G,MATCH($B7,'Base Runes'!$A:$A,0)),"") -> Burn
A8: 2 | B8: FIR-2a | C8: =IFERROR(INDEX('Base Runes'!$D:$D,MATCH($B8,'Base Runes'!$A:$A,0)),"") -> Ignite | D8: =IFERROR(INDEX('Base Runes'!$E:$E,MATCH($B8,'Base Runes'!$A:$A,0)),"") -> ᚲ | E8: start a fire at a point | F8: applies Alight; wind-up and recovery -10% | G8: =IFERROR(INDEX('Base Runes'!$G:$G,MATCH($B8,'Base Runes'!$A:$A,0)),"") -> Snuff | I8: Cinder Spit, Flashover
A9: 2 | B9: FIR-2b | C9: =IFERROR(INDEX('Base Runes'!$D:$D,MATCH($B9,'Base Runes'!$A:$A,0)),"") -> Snuff | D9: =IFERROR(INDEX('Base Runes'!$E:$E,MATCH($B9,'Base Runes'!$A:$A,0)),"") -> ᚳ | E9: put out one flame or source at once | F9: interrupts a wind-up | G9: =IFERROR(INDEX('Base Runes'!$G:$G,MATCH($B9,'Base Runes'!$A:$A,0)),"") -> Ignite
A10: 3 | B10: FIR-3a | C10: =IFERROR(INDEX('Base Runes'!$D:$D,MATCH($B10,'Base Runes'!$A:$A,0)),"") -> Explode | D10: =IFERROR(INDEX('Base Runes'!$E:$E,MATCH($B10,'Base Runes'!$A:$A,0)),"") -> ᚴ | E10: blast outward | F10: range and area +30%; damage +15%; essence cost +15% | G10: =IFERROR(INDEX('Base Runes'!$G:$G,MATCH($B10,'Base Runes'!$A:$A,0)),"") -> Implode | I10: Pyre Call
A11: 3 | B11: FIR-3b | C11: =IFERROR(INDEX('Base Runes'!$D:$D,MATCH($B11,'Base Runes'!$A:$A,0)),"") -> Implode | D11: =IFERROR(INDEX('Base Runes'!$E:$E,MATCH($B11,'Base Runes'!$A:$A,0)),"") -> ᚵ | E11: flame rushing inward | F11: pulls 1.5 m | G11: =IFERROR(INDEX('Base Runes'!$G:$G,MATCH($B11,'Base Runes'!$A:$A,0)),"") -> Explode | I11: Backdraft
A12: 4 | B12: FIR-4a | C12: =IFERROR(INDEX('Base Runes'!$D:$D,MATCH($B12,'Base Runes'!$A:$A,0)),"") -> Blaze | D12: =IFERROR(INDEX('Base Runes'!$E:$E,MATCH($B12,'Base Runes'!$A:$A,0)),"") -> ᚶ | E12: a fierce, spreading fire | F12: damage +20%; reflux left +20% | G12: =IFERROR(INDEX('Base Runes'!$G:$G,MATCH($B12,'Base Runes'!$A:$A,0)),"") -> Smoulder | I12: Bellows Breath
A13: 4 | B13: FIR-4b | C13: =IFERROR(INDEX('Base Runes'!$D:$D,MATCH($B13,'Base Runes'!$A:$A,0)),"") -> Smoulder | D13: =IFERROR(INDEX('Base Runes'!$E:$E,MATCH($B13,'Base Runes'!$A:$A,0)),"") -> ᚷ | E13: a low, lasting burn | F13: duration +50%; applies Alight | G13: =IFERROR(INDEX('Base Runes'!$G:$G,MATCH($B13,'Base Runes'!$A:$A,0)),"") -> Blaze | I13: Stoke, Slag Pool
A14: 5 | B14: FIR-5a | C14: =IFERROR(INDEX('Base Runes'!$D:$D,MATCH($B14,'Base Runes'!$A:$A,0)),"") -> Flare | D14: =IFERROR(INDEX('Base Runes'!$E:$E,MATCH($B14,'Base Runes'!$A:$A,0)),"") -> ᚸ | E14: a sudden flash of flame | F14: applies Dazed | G14: =IFERROR(INDEX('Base Runes'!$G:$G,MATCH($B14,'Base Runes'!$A:$A,0)),"") -> Smother
A15: 5 | B15: FIR-5b | C15: =IFERROR(INDEX('Base Runes'!$D:$D,MATCH($B15,'Base Runes'!$A:$A,0)),"") -> Smother | D15: =IFERROR(INDEX('Base Runes'!$E:$E,MATCH($B15,'Base Runes'!$A:$A,0)),"") -> ᚹ | E15: starve a fire, or a foe, of air | F15: interrupts a wind-up; applies Slowed | G15: =IFERROR(INDEX('Base Runes'!$G:$G,MATCH($B15,'Base Runes'!$A:$A,0)),"") -> Flare
A17: Blue: type here. Green: pulled from Base Runes (rename a rune or change its character there). Yellow: not written yet.

Sheet Earth
A1: Earth
A2: Rule: Builds stone that stays
A3: Status: First pass.
A5: Pair | B5: ID | C5: Rune | D5: Character | E5: As a skill (the verb a skill is built on) | F5: As a means (added to another skill) | G5: Opposite | H5: Together (rune + opposite release) | I5: Skills on it | J5: Notes
A6: 1 | B6: EAR-1a | C6: =IFERROR(INDEX('Base Runes'!$D:$D,MATCH($B6,'Base Runes'!$A:$A,0)),"") -> Raise | D6: =IFERROR(INDEX('Base Runes'!$E:$E,MATCH($B6,'Base Runes'!$A:$A,0)),"") -> ᚺ | E6: stone up | F6: poise damage +30% | G6: =IFERROR(INDEX('Base Runes'!$G:$G,MATCH($B6,'Base Runes'!$A:$A,0)),"") -> Sink | I6: Raise Slab, Pillar
A7: 1 | B7: EAR-1b | C7: =IFERROR(INDEX('Base Runes'!$D:$D,MATCH($B7,'Base Runes'!$A:$A,0)),"") -> Sink | D7: =IFERROR(INDEX('Base Runes'!$E:$E,MATCH($B7,'Base Runes'!$A:$A,0)),"") -> ᚻ | E7: ground down, pits | F7: applies Mired | G7: =IFERROR(INDEX('Base Runes'!$G:$G,MATCH($B7,'Base Runes'!$A:$A,0)),"") -> Raise
A8: 2 | B8: EAR-2a | C8: =IFERROR(INDEX('Base Runes'!$D:$D,MATCH($B8,'Base Runes'!$A:$A,0)),"") -> Harden | D8: =IFERROR(INDEX('Base Runes'!$E:$E,MATCH($B8,'Base Runes'!$A:$A,0)),"") -> ᚼ | E8: solidify, armour | F8: damage +15%; speed -10% | G8: =IFERROR(INDEX('Base Runes'!$G:$G,MATCH($B8,'Base Runes'!$A:$A,0)),"") -> Crumble | I8: Stonehide
A9: 2 | B9: EAR-2b | C9: =IFERROR(INDEX('Base Runes'!$D:$D,MATCH($B9,'Base Runes'!$A:$A,0)),"") -> Crumble | D9: =IFERROR(INDEX('Base Runes'!$E:$E,MATCH($B9,'Base Runes'!$A:$A,0)),"") -> ᚽ | E9: break stone and guard | F9: poise damage +50% | G9: =IFERROR(INDEX('Base Runes'!$G:$G,MATCH($B9,'Base Runes'!$A:$A,0)),"") -> Harden | I9: Landslide Blow
A10: 3 | B10: EAR-3a | C10: =IFERROR(INDEX('Base Runes'!$D:$D,MATCH($B10,'Base Runes'!$A:$A,0)),"") -> Root | D10: =IFERROR(INDEX('Base Runes'!$E:$E,MATCH($B10,'Base Runes'!$A:$A,0)),"") -> ᚾ | E10: anchor, stand firm | F10: you are Braced while casting | G10: =IFERROR(INDEX('Base Runes'!$G:$G,MATCH($B10,'Base Runes'!$A:$A,0)),"") -> Quake | I10: Bedrock Shove
A11: 3 | B11: EAR-3b | C11: =IFERROR(INDEX('Base Runes'!$D:$D,MATCH($B11,'Base Runes'!$A:$A,0)),"") -> Quake | D11: =IFERROR(INDEX('Base Runes'!$E:$E,MATCH($B11,'Base Runes'!$A:$A,0)),"") -> ᚿ | E11: shake, unbalance | F11: range and area +20%; poise damage +30% | G11: =IFERROR(INDEX('Base Runes'!$G:$G,MATCH($B11,'Base Runes'!$A:$A,0)),"") -> Root | I11: Tremor
A12: 4 | B12: EAR-4a | C12: =IFERROR(INDEX('Base Runes'!$D:$D,MATCH($B12,'Base Runes'!$A:$A,0)),"") -> Dig | D12: =IFERROR(INDEX('Base Runes'!$E:$E,MATCH($B12,'Base Runes'!$A:$A,0)),"") -> ᛀ | E12: tear into the ground and bring stone up to throw | F12: damage +15%; essence cost -10% | G12: =IFERROR(INDEX('Base Runes'!$G:$G,MATCH($B12,'Base Runes'!$A:$A,0)),"") -> Bury | I12: Slingstone, Quarry Throw
A13: 4 | B13: EAR-4b | C13: =IFERROR(INDEX('Base Runes'!$D:$D,MATCH($B13,'Base Runes'!$A:$A,0)),"") -> Bury | D13: =IFERROR(INDEX('Base Runes'!$E:$E,MATCH($B13,'Base Runes'!$A:$A,0)),"") -> ᛁ | E13: cover over with earth | F13: applies Pinned | G13: =IFERROR(INDEX('Base Runes'!$G:$G,MATCH($B13,'Base Runes'!$A:$A,0)),"") -> Dig
A14: 5 | B14: EAR-5a | C14: =IFERROR(INDEX('Base Runes'!$D:$D,MATCH($B14,'Base Runes'!$A:$A,0)),"") -> Tunnel | D14: =IFERROR(INDEX('Base Runes'!$E:$E,MATCH($B14,'Base Runes'!$A:$A,0)),"") -> ᛂ | E14: pass through the ground | F14: passes through one more | G14: =IFERROR(INDEX('Base Runes'!$G:$G,MATCH($B14,'Base Runes'!$A:$A,0)),"") -> Collapse
A15: 5 | B15: EAR-5b | C15: =IFERROR(INDEX('Base Runes'!$D:$D,MATCH($B15,'Base Runes'!$A:$A,0)),"") -> Collapse | D15: =IFERROR(INDEX('Base Runes'!$E:$E,MATCH($B15,'Base Runes'!$A:$A,0)),"") -> ᛃ | E15: bring the ground down and close a passage | F15: applies Stunned; essence cost +20% | G15: =IFERROR(INDEX('Base Runes'!$G:$G,MATCH($B15,'Base Runes'!$A:$A,0)),"") -> Tunnel
A17: Blue: type here. Green: pulled from Base Runes (rename a rune or change its character there). Yellow: not written yet.

Sheet Wind
A1: Wind
A2: Rule: Paid for by moving (Slipstream)
A3: Status: First pass.
A5: Pair | B5: ID | C5: Rune | D5: Character | E5: As a skill (the verb a skill is built on) | F5: As a means (added to another skill) | G5: Opposite | H5: Together (rune + opposite release) | I5: Skills on it | J5: Notes
A6: 1 | B6: WIN-1a | C6: =IFERROR(INDEX('Base Runes'!$D:$D,MATCH($B6,'Base Runes'!$A:$A,0)),"") -> Blow | D6: =IFERROR(INDEX('Base Runes'!$E:$E,MATCH($B6,'Base Runes'!$A:$A,0)),"") -> ᛄ | E6: moving air pushes | F6: shoves 1 m | G6: =IFERROR(INDEX('Base Runes'!$G:$G,MATCH($B6,'Base Runes'!$A:$A,0)),"") -> Lull | I6: Gale Lane, Spindrift
A7: 1 | B7: WIN-1b | C7: =IFERROR(INDEX('Base Runes'!$D:$D,MATCH($B7,'Base Runes'!$A:$A,0)),"") -> Lull | D7: =IFERROR(INDEX('Base Runes'!$E:$E,MATCH($B7,'Base Runes'!$A:$A,0)),"") -> ᛅ | E7: dead air; shots drop | F7: reflux left -20% | G7: =IFERROR(INDEX('Base Runes'!$G:$G,MATCH($B7,'Base Runes'!$A:$A,0)),"") -> Blow
A8: 2 | B8: WIN-2a | C8: =IFERROR(INDEX('Base Runes'!$D:$D,MATCH($B8,'Base Runes'!$A:$A,0)),"") -> Lash | D8: =IFERROR(INDEX('Base Runes'!$E:$E,MATCH($B8,'Base Runes'!$A:$A,0)),"") -> ᛆ | E8: air that strikes and cuts | F8: damage +20%; speed +10% | G8: =IFERROR(INDEX('Base Runes'!$G:$G,MATCH($B8,'Base Runes'!$A:$A,0)),"") -> Buffer | I8: Cutting Gust, Crosscut
A9: 2 | B9: WIN-2b | C9: =IFERROR(INDEX('Base Runes'!$D:$D,MATCH($B9,'Base Runes'!$A:$A,0)),"") -> Buffer | D9: =IFERROR(INDEX('Base Runes'!$E:$E,MATCH($B9,'Base Runes'!$A:$A,0)),"") -> ᛇ | E9: cushioning air | F9: wind-up and recovery -15% | G9: =IFERROR(INDEX('Base Runes'!$G:$G,MATCH($B9,'Base Runes'!$A:$A,0)),"") -> Lash | I9: Crosswind Veil
A10: 3 | B10: WIN-3a | C10: =IFERROR(INDEX('Base Runes'!$D:$D,MATCH($B10,'Base Runes'!$A:$A,0)),"") -> Lift | D10: =IFERROR(INDEX('Base Runes'!$E:$E,MATCH($B10,'Base Runes'!$A:$A,0)),"") -> ᛈ | E10: raise aloft | F10: applies Aloft | G10: =IFERROR(INDEX('Base Runes'!$G:$G,MATCH($B10,'Base Runes'!$A:$A,0)),"") -> Drop | I10: Updraft
A11: 3 | B11: WIN-3b | C11: =IFERROR(INDEX('Base Runes'!$D:$D,MATCH($B11,'Base Runes'!$A:$A,0)),"") -> Drop | D11: =IFERROR(INDEX('Base Runes'!$E:$E,MATCH($B11,'Base Runes'!$A:$A,0)),"") -> ᛉ | E11: slam down | F11: poise damage +40% | G11: =IFERROR(INDEX('Base Runes'!$G:$G,MATCH($B11,'Base Runes'!$A:$A,0)),"") -> Lift | I11: Downdraft
A12: 4 | B12: WIN-4a | C12: =IFERROR(INDEX('Base Runes'!$D:$D,MATCH($B12,'Base Runes'!$A:$A,0)),"") -> Carry | D12: =IFERROR(INDEX('Base Runes'!$E:$E,MATCH($B12,'Base Runes'!$A:$A,0)),"") -> ᛊ | E12: be carried along, faster | F12: speed +30%; range and area +15% | G12: =IFERROR(INDEX('Base Runes'!$G:$G,MATCH($B12,'Base Runes'!$A:$A,0)),"") -> Stall | I12: Tailwind
A13: 4 | B13: WIN-4b | C13: =IFERROR(INDEX('Base Runes'!$D:$D,MATCH($B13,'Base Runes'!$A:$A,0)),"") -> Stall | D13: =IFERROR(INDEX('Base Runes'!$E:$E,MATCH($B13,'Base Runes'!$A:$A,0)),"") -> ᛋ | E13: stalled; slipstream stolen | F13: applies Slowed | G13: =IFERROR(INDEX('Base Runes'!$G:$G,MATCH($B13,'Base Runes'!$A:$A,0)),"") -> Carry
A14: 5 | B14: WIN-5a | C14: =IFERROR(INDEX('Base Runes'!$D:$D,MATCH($B14,'Base Runes'!$A:$A,0)),"") -> Whirl | D14: =IFERROR(INDEX('Base Runes'!$E:$E,MATCH($B14,'Base Runes'!$A:$A,0)),"") -> ᛌ | E14: spin together | F14: pulls 1 m; range and area +10% | G14: =IFERROR(INDEX('Base Runes'!$G:$G,MATCH($B14,'Base Runes'!$A:$A,0)),"") -> Disperse
A15: 5 | B15: WIN-5b | C15: =IFERROR(INDEX('Base Runes'!$D:$D,MATCH($B15,'Base Runes'!$A:$A,0)),"") -> Disperse | D15: =IFERROR(INDEX('Base Runes'!$E:$E,MATCH($B15,'Base Runes'!$A:$A,0)),"") -> ᛍ | E15: blow apart | F15: range and area +30%; damage -10% | G15: =IFERROR(INDEX('Base Runes'!$G:$G,MATCH($B15,'Base Runes'!$A:$A,0)),"") -> Whirl
A17: Blue: type here. Green: pulled from Base Runes (rename a rune or change its character there). Yellow: not written yet.

Sheet Lightning
A1: Lightning
A2: Rule: Marks a target, then overloads it
A3: Status: First pass.
A5: Pair | B5: ID | C5: Rune | D5: Character | E5: As a skill (the verb a skill is built on) | F5: As a means (added to another skill) | G5: Opposite | H5: Together (rune + opposite release) | I5: Skills on it | J5: Notes
A6: 1 | B6: LIG-1a | C6: =IFERROR(INDEX('Base Runes'!$D:$D,MATCH($B6,'Base Runes'!$A:$A,0)),"") -> Strike | D6: =IFERROR(INDEX('Base Runes'!$E:$E,MATCH($B6,'Base Runes'!$A:$A,0)),"") -> ᛎ | E6: a bolt that hits one target | F6: damage +20%; speed +20% | G6: =IFERROR(INDEX('Base Runes'!$G:$G,MATCH($B6,'Base Runes'!$A:$A,0)),"") -> Ground
A7: 1 | B7: LIG-1b | C7: =IFERROR(INDEX('Base Runes'!$D:$D,MATCH($B7,'Base Runes'!$A:$A,0)),"") -> Ground | D7: =IFERROR(INDEX('Base Runes'!$E:$E,MATCH($B7,'Base Runes'!$A:$A,0)),"") -> ᛏ | E7: earth a charge away; draw strikes to a point | F7: reflux left -25% | G7: =IFERROR(INDEX('Base Runes'!$G:$G,MATCH($B7,'Base Runes'!$A:$A,0)),"") -> Strike | I7: Ground Rod
A8: 2 | B8: LIG-2a | C8: =IFERROR(INDEX('Base Runes'!$D:$D,MATCH($B8,'Base Runes'!$A:$A,0)),"") -> Charge | D8: =IFERROR(INDEX('Base Runes'!$E:$E,MATCH($B8,'Base Runes'!$A:$A,0)),"") -> ᛐ | E8: build up marks | F8: adds a Live mark | G8: =IFERROR(INDEX('Base Runes'!$G:$G,MATCH($B8,'Base Runes'!$A:$A,0)),"") -> Discharge | I8: Static Coat, Stored Bolt
A9: 2 | B9: LIG-2b | C9: =IFERROR(INDEX('Base Runes'!$D:$D,MATCH($B9,'Base Runes'!$A:$A,0)),"") -> Discharge | D9: =IFERROR(INDEX('Base Runes'!$E:$E,MATCH($B9,'Base Runes'!$A:$A,0)),"") -> ᛑ | E9: release them as an overload | F9: +40% damage to Live targets | G9: =IFERROR(INDEX('Base Runes'!$G:$G,MATCH($B9,'Base Runes'!$A:$A,0)),"") -> Charge | I9: Dead Short
A10: 3 | B10: LIG-3a | C10: =IFERROR(INDEX('Base Runes'!$D:$D,MATCH($B10,'Base Runes'!$A:$A,0)),"") -> Arc | D10: =IFERROR(INDEX('Base Runes'!$E:$E,MATCH($B10,'Base Runes'!$A:$A,0)),"") -> ᛒ | E10: jump between targets | F10: jumps to one more target | G10: =IFERROR(INDEX('Base Runes'!$G:$G,MATCH($B10,'Base Runes'!$A:$A,0)),"") -> Insulate | I10: Arc Lash, Forked Path
A11: 3 | B11: LIG-3b | C11: =IFERROR(INDEX('Base Runes'!$D:$D,MATCH($B11,'Base Runes'!$A:$A,0)),"") -> Insulate | D11: =IFERROR(INDEX('Base Runes'!$E:$E,MATCH($B11,'Base Runes'!$A:$A,0)),"") -> ᛓ | E11: block a jump, isolate a target | F11: essence cost -15% | G11: =IFERROR(INDEX('Base Runes'!$G:$G,MATCH($B11,'Base Runes'!$A:$A,0)),"") -> Arc
A12: 4 | B12: LIG-4a | C12: =IFERROR(INDEX('Base Runes'!$D:$D,MATCH($B12,'Base Runes'!$A:$A,0)),"") -> Quicken | D12: =IFERROR(INDEX('Base Runes'!$E:$E,MATCH($B12,'Base Runes'!$A:$A,0)),"") -> ᛔ | E12: nerves in overdrive | F12: wind-up and recovery -30%; speed +20% | G12: =IFERROR(INDEX('Base Runes'!$G:$G,MATCH($B12,'Base Runes'!$A:$A,0)),"") -> Stun | I12: Stepped Leader
A13: 4 | B13: LIG-4b | C13: =IFERROR(INDEX('Base Runes'!$D:$D,MATCH($B13,'Base Runes'!$A:$A,0)),"") -> Stun | D13: =IFERROR(INDEX('Base Runes'!$E:$E,MATCH($B13,'Base Runes'!$A:$A,0)),"") -> ᛕ | E13: nerves locked | F13: applies Stunned | G13: =IFERROR(INDEX('Base Runes'!$G:$G,MATCH($B13,'Base Runes'!$A:$A,0)),"") -> Quicken
A14: 5 | B14: LIG-5a | C14: =IFERROR(INDEX('Base Runes'!$D:$D,MATCH($B14,'Base Runes'!$A:$A,0)),"") -> Thunder | D14: =IFERROR(INDEX('Base Runes'!$E:$E,MATCH($B14,'Base Runes'!$A:$A,0)),"") -> ᛖ | E14: a deafening crack that staggers | F14: poise damage +30%; applies Dazed | G14: =IFERROR(INDEX('Base Runes'!$G:$G,MATCH($B14,'Base Runes'!$A:$A,0)),"") -> Silence | I14: Thunderclap Palm
A15: 5 | B15: LIG-5b | C15: =IFERROR(INDEX('Base Runes'!$D:$D,MATCH($B15,'Base Runes'!$A:$A,0)),"") -> Silence | D15: =IFERROR(INDEX('Base Runes'!$E:$E,MATCH($B15,'Base Runes'!$A:$A,0)),"") -> ᛗ | E15: dead quiet: casting and calls fail | F15: interrupts a wind-up | G15: =IFERROR(INDEX('Base Runes'!$G:$G,MATCH($B15,'Base Runes'!$A:$A,0)),"") -> Thunder
A17: Blue: type here. Green: pulled from Base Runes (rename a rune or change its character there). Yellow: not written yet.

Sheet Ice
A1: Ice
A2: Rule: What it freezes stays frozen
A3: Cold builds up on a target until it locks solid; frozen things turn brittle and break. Status: First pass (new 2026-10-22). Source: B 2026-10-21: ice is its own affinity, taking water's Freeze; MODEL: the rule.
A5: Pair | B5: ID | C5: Rune | D5: Character | E5: As a skill (the verb a skill is built on) | F5: As a means (added to another skill) | G5: Opposite | H5: Together (rune + opposite release) | I5: Skills on it | J5: Notes
A6: 1 | B6: ICE-1a | C6: =IFERROR(INDEX('Base Runes'!$D:$D,MATCH($B6,'Base Runes'!$A:$A,0)),"") -> Freeze | D6: =IFERROR(INDEX('Base Runes'!$E:$E,MATCH($B6,'Base Runes'!$A:$A,0)),"") -> 🜀 | E6: lock solid | G6: =IFERROR(INDEX('Base Runes'!$G:$G,MATCH($B6,'Base Runes'!$A:$A,0)),"") -> Thaw
A7: 1 | B7: ICE-1b | C7: =IFERROR(INDEX('Base Runes'!$D:$D,MATCH($B7,'Base Runes'!$A:$A,0)),"") -> Thaw | D7: =IFERROR(INDEX('Base Runes'!$E:$E,MATCH($B7,'Base Runes'!$A:$A,0)),"") -> 🜁 | E7: release, melt free | G7: =IFERROR(INDEX('Base Runes'!$G:$G,MATCH($B7,'Base Runes'!$A:$A,0)),"") -> Freeze
A8: 2 | B8: ICE-2a | C8: =IFERROR(INDEX('Base Runes'!$D:$D,MATCH($B8,'Base Runes'!$A:$A,0)),"") -> Frost | D8: =IFERROR(INDEX('Base Runes'!$E:$E,MATCH($B8,'Base Runes'!$A:$A,0)),"") -> 🜂 | E8: creeping cold on the ground that grips and slows | G8: =IFERROR(INDEX('Base Runes'!$G:$G,MATCH($B8,'Base Runes'!$A:$A,0)),"") -> Glaze
A9: 2 | B9: ICE-2b | C9: =IFERROR(INDEX('Base Runes'!$D:$D,MATCH($B9,'Base Runes'!$A:$A,0)),"") -> Glaze | D9: =IFERROR(INDEX('Base Runes'!$E:$E,MATCH($B9,'Base Runes'!$A:$A,0)),"") -> 🜃 | E9: glazed ice: fast and slippery | G9: =IFERROR(INDEX('Base Runes'!$G:$G,MATCH($B9,'Base Runes'!$A:$A,0)),"") -> Frost
A10: 3 | B10: ICE-3a | C10: =IFERROR(INDEX('Base Runes'!$D:$D,MATCH($B10,'Base Runes'!$A:$A,0)),"") -> Snow | D10: =IFERROR(INDEX('Base Runes'!$E:$E,MATCH($B10,'Base Runes'!$A:$A,0)),"") -> 🜄 | E10: a fall of snow that blinds and buries | G10: =IFERROR(INDEX('Base Runes'!$G:$G,MATCH($B10,'Base Runes'!$A:$A,0)),"") -> Melt
A11: 3 | B11: ICE-3b | C11: =IFERROR(INDEX('Base Runes'!$D:$D,MATCH($B11,'Base Runes'!$A:$A,0)),"") -> Melt | D11: =IFERROR(INDEX('Base Runes'!$E:$E,MATCH($B11,'Base Runes'!$A:$A,0)),"") -> 🜅 | E11: turn ice and snow to water | G11: =IFERROR(INDEX('Base Runes'!$G:$G,MATCH($B11,'Base Runes'!$A:$A,0)),"") -> Snow
A12: 4 | B12: ICE-4a | C12: =IFERROR(INDEX('Base Runes'!$D:$D,MATCH($B12,'Base Runes'!$A:$A,0)),"") -> Rime | D12: =IFERROR(INDEX('Base Runes'!$E:$E,MATCH($B12,'Base Runes'!$A:$A,0)),"") -> 🜆 | E12: build ice: walls, armour, spikes | G12: =IFERROR(INDEX('Base Runes'!$G:$G,MATCH($B12,'Base Runes'!$A:$A,0)),"") -> Shatter
A13: 4 | B13: ICE-4b | C13: =IFERROR(INDEX('Base Runes'!$D:$D,MATCH($B13,'Base Runes'!$A:$A,0)),"") -> Shatter | D13: =IFERROR(INDEX('Base Runes'!$E:$E,MATCH($B13,'Base Runes'!$A:$A,0)),"") -> 🜇 | E13: break ice; brittle things burst | G13: =IFERROR(INDEX('Base Runes'!$G:$G,MATCH($B13,'Base Runes'!$A:$A,0)),"") -> Rime
A14: 5 | B14: ICE-5a | C14: =IFERROR(INDEX('Base Runes'!$D:$D,MATCH($B14,'Base Runes'!$A:$A,0)),"") -> Brittle | D14: =IFERROR(INDEX('Base Runes'!$E:$E,MATCH($B14,'Base Runes'!$A:$A,0)),"") -> 🜈 | E14: make a thing fragile | G14: =IFERROR(INDEX('Base Runes'!$G:$G,MATCH($B14,'Base Runes'!$A:$A,0)),"") -> Toughen
A15: 5 | B15: ICE-5b | C15: =IFERROR(INDEX('Base Runes'!$D:$D,MATCH($B15,'Base Runes'!$A:$A,0)),"") -> Toughen | D15: =IFERROR(INDEX('Base Runes'!$E:$E,MATCH($B15,'Base Runes'!$A:$A,0)),"") -> 🜉 | E15: cold-harden it | G15: =IFERROR(INDEX('Base Runes'!$G:$G,MATCH($B15,'Base Runes'!$A:$A,0)),"") -> Brittle
A17: Blue: type here. Green: pulled from Base Runes (rename a rune or change its character there). Yellow: not written yet.

Sheet Dark
A1: Dark
A2: Rule: Strongest where the light is weakest
A3: Shadows are places it can use: it hides in them, moves through them and feeds on light. Status: First pass (new 2026-10-22). Source: B 2026-10-21: dark is an affinity; MODEL: the rule.
A5: Pair | B5: ID | C5: Rune | D5: Character | E5: As a skill (the verb a skill is built on) | F5: As a means (added to another skill) | G5: Opposite | H5: Together (rune + opposite release) | I5: Skills on it | J5: Notes
A6: 1 | B6: DRK-1a | C6: =IFERROR(INDEX('Base Runes'!$D:$D,MATCH($B6,'Base Runes'!$A:$A,0)),"") -> Darken | D6: =IFERROR(INDEX('Base Runes'!$E:$E,MATCH($B6,'Base Runes'!$A:$A,0)),"") -> 🜊 | E6: make it darker | G6: =IFERROR(INDEX('Base Runes'!$G:$G,MATCH($B6,'Base Runes'!$A:$A,0)),"") -> Lighten
A7: 1 | B7: DRK-1b | C7: =IFERROR(INDEX('Base Runes'!$D:$D,MATCH($B7,'Base Runes'!$A:$A,0)),"") -> Lighten | D7: =IFERROR(INDEX('Base Runes'!$E:$E,MATCH($B7,'Base Runes'!$A:$A,0)),"") -> 🜋 | E7: let the light back in | G7: =IFERROR(INDEX('Base Runes'!$G:$G,MATCH($B7,'Base Runes'!$A:$A,0)),"") -> Darken
A8: 2 | B8: DRK-2a | C8: =IFERROR(INDEX('Base Runes'!$D:$D,MATCH($B8,'Base Runes'!$A:$A,0)),"") -> Obscure | D8: =IFERROR(INDEX('Base Runes'!$E:$E,MATCH($B8,'Base Runes'!$A:$A,0)),"") -> 🜌 | E8: hide a thing in darkness | G8: =IFERROR(INDEX('Base Runes'!$G:$G,MATCH($B8,'Base Runes'!$A:$A,0)),"") -> Expose
A9: 2 | B9: DRK-2b | C9: =IFERROR(INDEX('Base Runes'!$D:$D,MATCH($B9,'Base Runes'!$A:$A,0)),"") -> Expose | D9: =IFERROR(INDEX('Base Runes'!$E:$E,MATCH($B9,'Base Runes'!$A:$A,0)),"") -> 🜍 | E9: make a hidden target stand out | G9: =IFERROR(INDEX('Base Runes'!$G:$G,MATCH($B9,'Base Runes'!$A:$A,0)),"") -> Obscure
A10: 3 | B10: DRK-3a | C10: =IFERROR(INDEX('Base Runes'!$D:$D,MATCH($B10,'Base Runes'!$A:$A,0)),"") -> Shadowstep | D10: =IFERROR(INDEX('Base Runes'!$E:$E,MATCH($B10,'Base Runes'!$A:$A,0)),"") -> 🜎 | E10: move through shadows | G10: =IFERROR(INDEX('Base Runes'!$G:$G,MATCH($B10,'Base Runes'!$A:$A,0)),"") -> Pin
A11: 3 | B11: DRK-3b | C11: =IFERROR(INDEX('Base Runes'!$D:$D,MATCH($B11,'Base Runes'!$A:$A,0)),"") -> Pin | D11: =IFERROR(INDEX('Base Runes'!$E:$E,MATCH($B11,'Base Runes'!$A:$A,0)),"") -> 🜏 | E11: nail a target's shadow, and the target with it | G11: =IFERROR(INDEX('Base Runes'!$G:$G,MATCH($B11,'Base Runes'!$A:$A,0)),"") -> Shadowstep
A12: 4 | B12: DRK-4a | C12: =IFERROR(INDEX('Base Runes'!$D:$D,MATCH($B12,'Base Runes'!$A:$A,0)),"") -> Hush | D12: =IFERROR(INDEX('Base Runes'!$E:$E,MATCH($B12,'Base Runes'!$A:$A,0)),"") -> 🜐 | E12: smother sound | G12: =IFERROR(INDEX('Base Runes'!$G:$G,MATCH($B12,'Base Runes'!$A:$A,0)),"") -> Resound
A13: 4 | B13: DRK-4b | C13: =IFERROR(INDEX('Base Runes'!$D:$D,MATCH($B13,'Base Runes'!$A:$A,0)),"") -> Resound | D13: =IFERROR(INDEX('Base Runes'!$E:$E,MATCH($B13,'Base Runes'!$A:$A,0)),"") -> 🜑 | E13: sound carries and echoes in the dark | G13: =IFERROR(INDEX('Base Runes'!$G:$G,MATCH($B13,'Base Runes'!$A:$A,0)),"") -> Hush
A14: 5 | B14: DRK-5a | C14: =IFERROR(INDEX('Base Runes'!$D:$D,MATCH($B14,'Base Runes'!$A:$A,0)),"") -> Devour | D14: =IFERROR(INDEX('Base Runes'!$E:$E,MATCH($B14,'Base Runes'!$A:$A,0)),"") -> 🜒 | E14: swallow light and energy | G14: =IFERROR(INDEX('Base Runes'!$G:$G,MATCH($B14,'Base Runes'!$A:$A,0)),"") -> Disgorge
A15: 5 | B15: DRK-5b | C15: =IFERROR(INDEX('Base Runes'!$D:$D,MATCH($B15,'Base Runes'!$A:$A,0)),"") -> Disgorge | D15: =IFERROR(INDEX('Base Runes'!$E:$E,MATCH($B15,'Base Runes'!$A:$A,0)),"") -> 🜓 | E15: release what was swallowed | G15: =IFERROR(INDEX('Base Runes'!$G:$G,MATCH($B15,'Base Runes'!$A:$A,0)),"") -> Devour
A17: Blue: type here. Green: pulled from Base Runes (rename a rune or change its character there). Yellow: not written yet.

Sheet Metal
A1: Metal
A2: Rule: Worn and carried metal is its material
A3: Armoured enemies are a liability against metal: their own gear can be pulled, rung or stripped. Status: First pass. Source: MODEL.
A5: Pair | B5: ID | C5: Rune | D5: Character | E5: As a skill (the verb a skill is built on) | F5: As a means (added to another skill) | G5: Opposite | H5: Together (rune + opposite release) | I5: Skills on it | J5: Notes
A6: 1 | B6: MET-1a | C6: =IFERROR(INDEX('Base Runes'!$D:$D,MATCH($B6,'Base Runes'!$A:$A,0)),"") -> Forge | D6: =IFERROR(INDEX('Base Runes'!$E:$E,MATCH($B6,'Base Runes'!$A:$A,0)),"") -> 🜔 | E6: shape and harden metal | G6: =IFERROR(INDEX('Base Runes'!$G:$G,MATCH($B6,'Base Runes'!$A:$A,0)),"") -> Rust
A7: 1 | B7: MET-1b | C7: =IFERROR(INDEX('Base Runes'!$D:$D,MATCH($B7,'Base Runes'!$A:$A,0)),"") -> Rust | D7: =IFERROR(INDEX('Base Runes'!$E:$E,MATCH($B7,'Base Runes'!$A:$A,0)),"") -> 🜕 | E7: corrode it | G7: =IFERROR(INDEX('Base Runes'!$G:$G,MATCH($B7,'Base Runes'!$A:$A,0)),"") -> Forge
A8: 2 | B8: MET-2a | C8: =IFERROR(INDEX('Base Runes'!$D:$D,MATCH($B8,'Base Runes'!$A:$A,0)),"") -> Fuse | D8: =IFERROR(INDEX('Base Runes'!$E:$E,MATCH($B8,'Base Runes'!$A:$A,0)),"") -> 🜖 | E8: join metal into one piece | G8: =IFERROR(INDEX('Base Runes'!$G:$G,MATCH($B8,'Base Runes'!$A:$A,0)),"") -> Sunder
A9: 2 | B9: MET-2b | C9: =IFERROR(INDEX('Base Runes'!$D:$D,MATCH($B9,'Base Runes'!$A:$A,0)),"") -> Sunder | D9: =IFERROR(INDEX('Base Runes'!$E:$E,MATCH($B9,'Base Runes'!$A:$A,0)),"") -> 🜗 | E9: split it apart | G9: =IFERROR(INDEX('Base Runes'!$G:$G,MATCH($B9,'Base Runes'!$A:$A,0)),"") -> Fuse
A10: 3 | B10: MET-3a | C10: =IFERROR(INDEX('Base Runes'!$D:$D,MATCH($B10,'Base Runes'!$A:$A,0)),"") -> Seal | D10: =IFERROR(INDEX('Base Runes'!$E:$E,MATCH($B10,'Base Runes'!$A:$A,0)),"") -> 🜘 | E10: close and lock with metal | G10: =IFERROR(INDEX('Base Runes'!$G:$G,MATCH($B10,'Base Runes'!$A:$A,0)),"") -> Breach
A11: 3 | B11: MET-3b | C11: =IFERROR(INDEX('Base Runes'!$D:$D,MATCH($B11,'Base Runes'!$A:$A,0)),"") -> Breach | D11: =IFERROR(INDEX('Base Runes'!$E:$E,MATCH($B11,'Base Runes'!$A:$A,0)),"") -> 🜙 | E11: break a seal; punch through plate | G11: =IFERROR(INDEX('Base Runes'!$G:$G,MATCH($B11,'Base Runes'!$A:$A,0)),"") -> Seal
A12: 4 | B12: MET-4a | C12: =IFERROR(INDEX('Base Runes'!$D:$D,MATCH($B12,'Base Runes'!$A:$A,0)),"") -> Hone | D12: =IFERROR(INDEX('Base Runes'!$E:$E,MATCH($B12,'Base Runes'!$A:$A,0)),"") -> 🜚 | E12: sharpen | G12: =IFERROR(INDEX('Base Runes'!$G:$G,MATCH($B12,'Base Runes'!$A:$A,0)),"") -> Dull
A13: 4 | B13: MET-4b | C13: =IFERROR(INDEX('Base Runes'!$D:$D,MATCH($B13,'Base Runes'!$A:$A,0)),"") -> Dull | D13: =IFERROR(INDEX('Base Runes'!$E:$E,MATCH($B13,'Base Runes'!$A:$A,0)),"") -> 🜛 | E13: blunt edges, theirs included | G13: =IFERROR(INDEX('Base Runes'!$G:$G,MATCH($B13,'Base Runes'!$A:$A,0)),"") -> Hone
A14: 5 | B14: MET-5a | C14: =IFERROR(INDEX('Base Runes'!$D:$D,MATCH($B14,'Base Runes'!$A:$A,0)),"") -> Plate | D14: =IFERROR(INDEX('Base Runes'!$E:$E,MATCH($B14,'Base Runes'!$A:$A,0)),"") -> 🜜 | E14: armour up | G14: =IFERROR(INDEX('Base Runes'!$G:$G,MATCH($B14,'Base Runes'!$A:$A,0)),"") -> Strip
A15: 5 | B15: MET-5b | C15: =IFERROR(INDEX('Base Runes'!$D:$D,MATCH($B15,'Base Runes'!$A:$A,0)),"") -> Strip | D15: =IFERROR(INDEX('Base Runes'!$E:$E,MATCH($B15,'Base Runes'!$A:$A,0)),"") -> 🜝 | E15: tear armour off | G15: =IFERROR(INDEX('Base Runes'!$G:$G,MATCH($B15,'Base Runes'!$A:$A,0)),"") -> Plate
A17: Blue: type here. Green: pulled from Base Runes (rename a rune or change its character there). Yellow: not written yet.

Sheet Blood
A1: Blood
A2: Rule: Works the blood that is already out
A3: [B 2026-10-21] Blood does not pay in health. First-pass rule, to be settled in its deep dive: the wounds you open spill blood, and blood skills work that spilled and stored blood, like water working the water that is there. Status: First pass. Source: C: blood storage and blood-to-metal techniques exist; MODEL: the rule.
A5: Pair | B5: ID | C5: Rune | D5: Character | E5: As a skill (the verb a skill is built on) | F5: As a means (added to another skill) | G5: Opposite | H5: Together (rune + opposite release) | I5: Skills on it | J5: Notes
A6: 1 | B6: BLD-1a | C6: =IFERROR(INDEX('Base Runes'!$D:$D,MATCH($B6,'Base Runes'!$A:$A,0)),"") -> Bleed | D6: =IFERROR(INDEX('Base Runes'!$E:$E,MATCH($B6,'Base Runes'!$A:$A,0)),"") -> 🜞 | E6: open wounds | G6: =IFERROR(INDEX('Base Runes'!$G:$G,MATCH($B6,'Base Runes'!$A:$A,0)),"") -> Staunch
A7: 1 | B7: BLD-1b | C7: =IFERROR(INDEX('Base Runes'!$D:$D,MATCH($B7,'Base Runes'!$A:$A,0)),"") -> Staunch | D7: =IFERROR(INDEX('Base Runes'!$E:$E,MATCH($B7,'Base Runes'!$A:$A,0)),"") -> 🜟 | E7: close them | G7: =IFERROR(INDEX('Base Runes'!$G:$G,MATCH($B7,'Base Runes'!$A:$A,0)),"") -> Bleed
A8: 2 | B8: BLD-2a | C8: =IFERROR(INDEX('Base Runes'!$D:$D,MATCH($B8,'Base Runes'!$A:$A,0)),"") -> Drink | D8: =IFERROR(INDEX('Base Runes'!$E:$E,MATCH($B8,'Base Runes'!$A:$A,0)),"") -> 🜠 | E8: take blood in | G8: =IFERROR(INDEX('Base Runes'!$G:$G,MATCH($B8,'Base Runes'!$A:$A,0)),"") -> Spill
A9: 2 | B9: BLD-2b | C9: =IFERROR(INDEX('Base Runes'!$D:$D,MATCH($B9,'Base Runes'!$A:$A,0)),"") -> Spill | D9: =IFERROR(INDEX('Base Runes'!$E:$E,MATCH($B9,'Base Runes'!$A:$A,0)),"") -> 🜡 | E9: give it out, as a weapon or a gift | G9: =IFERROR(INDEX('Base Runes'!$G:$G,MATCH($B9,'Base Runes'!$A:$A,0)),"") -> Drink
A10: 3 | B10: BLD-3a | C10: =IFERROR(INDEX('Base Runes'!$D:$D,MATCH($B10,'Base Runes'!$A:$A,0)),"") -> Clot | D10: =IFERROR(INDEX('Base Runes'!$E:$E,MATCH($B10,'Base Runes'!$A:$A,0)),"") -> 🜢 | E10: blood hardens: armour, blades, a stopped wound | G10: =IFERROR(INDEX('Base Runes'!$G:$G,MATCH($B10,'Base Runes'!$A:$A,0)),"") -> Thin
A11: 3 | B11: BLD-3b | C11: =IFERROR(INDEX('Base Runes'!$D:$D,MATCH($B11,'Base Runes'!$A:$A,0)),"") -> Thin | D11: =IFERROR(INDEX('Base Runes'!$E:$E,MATCH($B11,'Base Runes'!$A:$A,0)),"") -> 🜣 | E11: blood runs quick: speed, reach | G11: =IFERROR(INDEX('Base Runes'!$G:$G,MATCH($B11,'Base Runes'!$A:$A,0)),"") -> Clot
A12: 4 | B12: BLD-4a | C12: =IFERROR(INDEX('Base Runes'!$D:$D,MATCH($B12,'Base Runes'!$A:$A,0)),"") -> Pulse | D12: =IFERROR(INDEX('Base Runes'!$E:$E,MATCH($B12,'Base Runes'!$A:$A,0)),"") -> 🜤 | E12: the heart pounds | G12: =IFERROR(INDEX('Base Runes'!$G:$G,MATCH($B12,'Base Runes'!$A:$A,0)),"") -> Still
A13: 4 | B13: BLD-4b | C13: =IFERROR(INDEX('Base Runes'!$D:$D,MATCH($B13,'Base Runes'!$A:$A,0)),"") -> Still | D13: =IFERROR(INDEX('Base Runes'!$E:$E,MATCH($B13,'Base Runes'!$A:$A,0)),"") -> 🜥 | E13: the heart slows | G13: =IFERROR(INDEX('Base Runes'!$G:$G,MATCH($B13,'Base Runes'!$A:$A,0)),"") -> Pulse
A14: 5 | B14: BLD-5a | C14: =IFERROR(INDEX('Base Runes'!$D:$D,MATCH($B14,'Base Runes'!$A:$A,0)),"") -> Choke | D14: =IFERROR(INDEX('Base Runes'!$E:$E,MATCH($B14,'Base Runes'!$A:$A,0)),"") -> 🜦 | E14: cut off breath | G14: =IFERROR(INDEX('Base Runes'!$G:$G,MATCH($B14,'Base Runes'!$A:$A,0)),"") -> Breathe
A15: 5 | B15: BLD-5b | C15: =IFERROR(INDEX('Base Runes'!$D:$D,MATCH($B15,'Base Runes'!$A:$A,0)),"") -> Breathe | D15: =IFERROR(INDEX('Base Runes'!$E:$E,MATCH($B15,'Base Runes'!$A:$A,0)),"") -> 🜧 | E15: give breath; steady the body | G15: =IFERROR(INDEX('Base Runes'!$G:$G,MATCH($B15,'Base Runes'!$A:$A,0)),"") -> Choke
A17: Blue: type here. Green: pulled from Base Runes (rename a rune or change its character there). Yellow: not written yet.

Sheet Life
A1: Life
A2: Rule: Works inside living bodies
A3: Strongest on the living; does nothing to stone, constructs or the dead. Status: First pass. Source: C: life practitioners work inside a body, with consent; MODEL: the rule.
A5: Pair | B5: ID | C5: Rune | D5: Character | E5: As a skill (the verb a skill is built on) | F5: As a means (added to another skill) | G5: Opposite | H5: Together (rune + opposite release) | I5: Skills on it | J5: Notes
A6: 1 | B6: LIF-1a | C6: =IFERROR(INDEX('Base Runes'!$D:$D,MATCH($B6,'Base Runes'!$A:$A,0)),"") -> Heal | D6: =IFERROR(INDEX('Base Runes'!$E:$E,MATCH($B6,'Base Runes'!$A:$A,0)),"") -> 🜨 | E6: restore health and close wounds | G6: =IFERROR(INDEX('Base Runes'!$G:$G,MATCH($B6,'Base Runes'!$A:$A,0)),"") -> Wither
A7: 1 | B7: LIF-1b | C7: =IFERROR(INDEX('Base Runes'!$D:$D,MATCH($B7,'Base Runes'!$A:$A,0)),"") -> Wither | D7: =IFERROR(INDEX('Base Runes'!$E:$E,MATCH($B7,'Base Runes'!$A:$A,0)),"") -> 🜩 | E7: harm from within | G7: =IFERROR(INDEX('Base Runes'!$G:$G,MATCH($B7,'Base Runes'!$A:$A,0)),"") -> Heal
A8: 2 | B8: LIF-2a | C8: =IFERROR(INDEX('Base Runes'!$D:$D,MATCH($B8,'Base Runes'!$A:$A,0)),"") -> Renew | D8: =IFERROR(INDEX('Base Runes'!$E:$E,MATCH($B8,'Base Runes'!$A:$A,0)),"") -> 🜪 | E8: restore vigour and stamina | G8: =IFERROR(INDEX('Base Runes'!$G:$G,MATCH($B8,'Base Runes'!$A:$A,0)),"") -> Exhaust
A9: 2 | B9: LIF-2b | C9: =IFERROR(INDEX('Base Runes'!$D:$D,MATCH($B9,'Base Runes'!$A:$A,0)),"") -> Exhaust | D9: =IFERROR(INDEX('Base Runes'!$E:$E,MATCH($B9,'Base Runes'!$A:$A,0)),"") -> 🜫 | E9: drain stamina; fatigue | G9: =IFERROR(INDEX('Base Runes'!$G:$G,MATCH($B9,'Base Runes'!$A:$A,0)),"") -> Renew
A10: 3 | B10: LIF-3a | C10: =IFERROR(INDEX('Base Runes'!$D:$D,MATCH($B10,'Base Runes'!$A:$A,0)),"") -> Strengthen | D10: =IFERROR(INDEX('Base Runes'!$E:$E,MATCH($B10,'Base Runes'!$A:$A,0)),"") -> 🜬 | E10: grow muscle and body | G10: =IFERROR(INDEX('Base Runes'!$G:$G,MATCH($B10,'Base Runes'!$A:$A,0)),"") -> Weaken
A11: 3 | B11: LIF-3b | C11: =IFERROR(INDEX('Base Runes'!$D:$D,MATCH($B11,'Base Runes'!$A:$A,0)),"") -> Weaken | D11: =IFERROR(INDEX('Base Runes'!$E:$E,MATCH($B11,'Base Runes'!$A:$A,0)),"") -> 🜭 | E11: waste the body away | G11: =IFERROR(INDEX('Base Runes'!$G:$G,MATCH($B11,'Base Runes'!$A:$A,0)),"") -> Strengthen
A12: 4 | B12: LIF-4a | C12: =IFERROR(INDEX('Base Runes'!$D:$D,MATCH($B12,'Base Runes'!$A:$A,0)),"") -> Cure | D12: =IFERROR(INDEX('Base Runes'!$E:$E,MATCH($B12,'Base Runes'!$A:$A,0)),"") -> 🜮 | E12: end a sickness or a poison | G12: =IFERROR(INDEX('Base Runes'!$G:$G,MATCH($B12,'Base Runes'!$A:$A,0)),"") -> Sicken
A13: 4 | B13: LIF-4b | C13: =IFERROR(INDEX('Base Runes'!$D:$D,MATCH($B13,'Base Runes'!$A:$A,0)),"") -> Sicken | D13: =IFERROR(INDEX('Base Runes'!$E:$E,MATCH($B13,'Base Runes'!$A:$A,0)),"") -> 🜯 | E13: make ill | G13: =IFERROR(INDEX('Base Runes'!$G:$G,MATCH($B13,'Base Runes'!$A:$A,0)),"") -> Cure
A14: 5 | B14: LIF-5a | C14: =IFERROR(INDEX('Base Runes'!$D:$D,MATCH($B14,'Base Runes'!$A:$A,0)),"") -> Regrow | D14: =IFERROR(INDEX('Base Runes'!$E:$E,MATCH($B14,'Base Runes'!$A:$A,0)),"") -> 🜰 | E14: restore what was lost, limbs included | G14: =IFERROR(INDEX('Base Runes'!$G:$G,MATCH($B14,'Base Runes'!$A:$A,0)),"") -> Arrest
A15: 5 | B15: LIF-5b | C15: =IFERROR(INDEX('Base Runes'!$D:$D,MATCH($B15,'Base Runes'!$A:$A,0)),"") -> Arrest | D15: =IFERROR(INDEX('Base Runes'!$E:$E,MATCH($B15,'Base Runes'!$A:$A,0)),"") -> 🜱 | E15: stop healing | G15: =IFERROR(INDEX('Base Runes'!$G:$G,MATCH($B15,'Base Runes'!$A:$A,0)),"") -> Regrow
A17: Blue: type here. Green: pulled from Base Runes (rename a rune or change its character there). Yellow: not written yet.

Sheet Death
A1: Death
A2: Rule: What has died stays useful
A3: Corpses are its material, and anything below half health is its prey. Status: First pass. Source: C: death affinity and undeath exist; MODEL: the rule.
A5: Pair | B5: ID | C5: Rune | D5: Character | E5: As a skill (the verb a skill is built on) | F5: As a means (added to another skill) | G5: Opposite | H5: Together (rune + opposite release) | I5: Skills on it | J5: Notes
A6: 1 | B6: DTH-1a | C6: =IFERROR(INDEX('Base Runes'!$D:$D,MATCH($B6,'Base Runes'!$A:$A,0)),"") -> Kill | D6: =IFERROR(INDEX('Base Runes'!$E:$E,MATCH($B6,'Base Runes'!$A:$A,0)),"") -> 🜲 | E6: finish the dying | G6: =IFERROR(INDEX('Base Runes'!$G:$G,MATCH($B6,'Base Runes'!$A:$A,0)),"") -> Spare
A7: 1 | B7: DTH-1b | C7: =IFERROR(INDEX('Base Runes'!$D:$D,MATCH($B7,'Base Runes'!$A:$A,0)),"") -> Spare | D7: =IFERROR(INDEX('Base Runes'!$E:$E,MATCH($B7,'Base Runes'!$A:$A,0)),"") -> 🜳 | E7: hold a life at the edge, for capture or mercy | G7: =IFERROR(INDEX('Base Runes'!$G:$G,MATCH($B7,'Base Runes'!$A:$A,0)),"") -> Kill
A8: 2 | B8: DTH-2a | C8: =IFERROR(INDEX('Base Runes'!$D:$D,MATCH($B8,'Base Runes'!$A:$A,0)),"") -> Animate | D8: =IFERROR(INDEX('Base Runes'!$E:$E,MATCH($B8,'Base Runes'!$A:$A,0)),"") -> 🜴 | E8: the dead get up | G8: =IFERROR(INDEX('Base Runes'!$G:$G,MATCH($B8,'Base Runes'!$A:$A,0)),"") -> Lay
A9: 2 | B9: DTH-2b | C9: =IFERROR(INDEX('Base Runes'!$D:$D,MATCH($B9,'Base Runes'!$A:$A,0)),"") -> Lay | D9: =IFERROR(INDEX('Base Runes'!$E:$E,MATCH($B9,'Base Runes'!$A:$A,0)),"") -> 🜵 | E9: put them down for good | G9: =IFERROR(INDEX('Base Runes'!$G:$G,MATCH($B9,'Base Runes'!$A:$A,0)),"") -> Animate
A10: 3 | B10: DTH-3a | C10: =IFERROR(INDEX('Base Runes'!$D:$D,MATCH($B10,'Base Runes'!$A:$A,0)),"") -> Rot | D10: =IFERROR(INDEX('Base Runes'!$E:$E,MATCH($B10,'Base Runes'!$A:$A,0)),"") -> 🜶 | E10: decay | G10: =IFERROR(INDEX('Base Runes'!$G:$G,MATCH($B10,'Base Runes'!$A:$A,0)),"") -> Preserve
A11: 3 | B11: DTH-3b | C11: =IFERROR(INDEX('Base Runes'!$D:$D,MATCH($B11,'Base Runes'!$A:$A,0)),"") -> Preserve | D11: =IFERROR(INDEX('Base Runes'!$E:$E,MATCH($B11,'Base Runes'!$A:$A,0)),"") -> 🜷 | E11: stop decay, the user's own body included | G11: =IFERROR(INDEX('Base Runes'!$G:$G,MATCH($B11,'Base Runes'!$A:$A,0)),"") -> Rot
A12: 4 | B12: DTH-4a | C12: =IFERROR(INDEX('Base Runes'!$D:$D,MATCH($B12,'Base Runes'!$A:$A,0)),"") -> Haunt | D12: =IFERROR(INDEX('Base Runes'!$E:$E,MATCH($B12,'Base Runes'!$A:$A,0)),"") -> 🜸 | E12: what dies lingers as a spirit | G12: =IFERROR(INDEX('Base Runes'!$G:$G,MATCH($B12,'Base Runes'!$A:$A,0)),"") -> Exorcise
A13: 4 | B13: DTH-4b | C13: =IFERROR(INDEX('Base Runes'!$D:$D,MATCH($B13,'Base Runes'!$A:$A,0)),"") -> Exorcise | D13: =IFERROR(INDEX('Base Runes'!$E:$E,MATCH($B13,'Base Runes'!$A:$A,0)),"") -> 🜹 | E13: banish spirits and constructs | G13: =IFERROR(INDEX('Base Runes'!$G:$G,MATCH($B13,'Base Runes'!$A:$A,0)),"") -> Haunt
A14: 5 | B14: DTH-5a | C14: =IFERROR(INDEX('Base Runes'!$D:$D,MATCH($B14,'Base Runes'!$A:$A,0)),"") -> Vanish | D14: =IFERROR(INDEX('Base Runes'!$E:$E,MATCH($B14,'Base Runes'!$A:$A,0)),"") -> 🜺 | E14: pass out of sight and reach | G14: =IFERROR(INDEX('Base Runes'!$G:$G,MATCH($B14,'Base Runes'!$A:$A,0)),"") -> Manifest
A15: 5 | B15: DTH-5b | C15: =IFERROR(INDEX('Base Runes'!$D:$D,MATCH($B15,'Base Runes'!$A:$A,0)),"") -> Manifest | D15: =IFERROR(INDEX('Base Runes'!$E:$E,MATCH($B15,'Base Runes'!$A:$A,0)),"") -> 🜻 | E15: appear; take form | G15: =IFERROR(INDEX('Base Runes'!$G:$G,MATCH($B15,'Base Runes'!$A:$A,0)),"") -> Vanish
A17: Blue: type here. Green: pulled from Base Runes (rename a rune or change its character there). Yellow: not written yet.

Sheet Nature
A1: Nature
A2: Rule: Grows from the ground and keeps growing
A3: What it plants stays, spreads and gets stronger over time. Status: First pass. Source: C: nature is named; MODEL: the rule.
A5: Pair | B5: ID | C5: Rune | D5: Character | E5: As a skill (the verb a skill is built on) | F5: As a means (added to another skill) | G5: Opposite | H5: Together (rune + opposite release) | I5: Skills on it | J5: Notes
A6: 1 | B6: NAT-1a | C6: =IFERROR(INDEX('Base Runes'!$D:$D,MATCH($B6,'Base Runes'!$A:$A,0)),"") -> Grow | D6: =IFERROR(INDEX('Base Runes'!$E:$E,MATCH($B6,'Base Runes'!$A:$A,0)),"") -> 🜼 | E6: make a thing larger and stronger | G6: =IFERROR(INDEX('Base Runes'!$G:$G,MATCH($B6,'Base Runes'!$A:$A,0)),"") -> Shrink
A7: 1 | B7: NAT-1b | C7: =IFERROR(INDEX('Base Runes'!$D:$D,MATCH($B7,'Base Runes'!$A:$A,0)),"") -> Shrink | D7: =IFERROR(INDEX('Base Runes'!$E:$E,MATCH($B7,'Base Runes'!$A:$A,0)),"") -> 🜽 | E7: make it smaller | G7: =IFERROR(INDEX('Base Runes'!$G:$G,MATCH($B7,'Base Runes'!$A:$A,0)),"") -> Grow
A8: 2 | B8: NAT-2a | C8: =IFERROR(INDEX('Base Runes'!$D:$D,MATCH($B8,'Base Runes'!$A:$A,0)),"") -> Sprout | D8: =IFERROR(INDEX('Base Runes'!$E:$E,MATCH($B8,'Base Runes'!$A:$A,0)),"") -> 🜾 | E8: grow plants from the ground | G8: =IFERROR(INDEX('Base Runes'!$G:$G,MATCH($B8,'Base Runes'!$A:$A,0)),"") -> Wilt
A9: 2 | B9: NAT-2b | C9: =IFERROR(INDEX('Base Runes'!$D:$D,MATCH($B9,'Base Runes'!$A:$A,0)),"") -> Wilt | D9: =IFERROR(INDEX('Base Runes'!$E:$E,MATCH($B9,'Base Runes'!$A:$A,0)),"") -> 🜿 | E9: kill plants; clear ground | G9: =IFERROR(INDEX('Base Runes'!$G:$G,MATCH($B9,'Base Runes'!$A:$A,0)),"") -> Sprout
A10: 3 | B10: NAT-3a | C10: =IFERROR(INDEX('Base Runes'!$D:$D,MATCH($B10,'Base Runes'!$A:$A,0)),"") -> Flourish | D10: =IFERROR(INDEX('Base Runes'!$E:$E,MATCH($B10,'Base Runes'!$A:$A,0)),"") -> 🝀 | E10: thrive: strengthen what grows | G10: =IFERROR(INDEX('Base Runes'!$G:$G,MATCH($B10,'Base Runes'!$A:$A,0)),"") -> Blight
A11: 3 | B11: NAT-3b | C11: =IFERROR(INDEX('Base Runes'!$D:$D,MATCH($B11,'Base Runes'!$A:$A,0)),"") -> Blight | D11: =IFERROR(INDEX('Base Runes'!$E:$E,MATCH($B11,'Base Runes'!$A:$A,0)),"") -> 🝁 | E11: a sickness of growing things | G11: =IFERROR(INDEX('Base Runes'!$G:$G,MATCH($B11,'Base Runes'!$A:$A,0)),"") -> Flourish
A12: 4 | B12: NAT-4a | C12: =IFERROR(INDEX('Base Runes'!$D:$D,MATCH($B12,'Base Runes'!$A:$A,0)),"") -> Harvest | D12: =IFERROR(INDEX('Base Runes'!$E:$E,MATCH($B12,'Base Runes'!$A:$A,0)),"") -> 🝂 | E12: take what has grown, and its yield | G12: =IFERROR(INDEX('Base Runes'!$G:$G,MATCH($B12,'Base Runes'!$A:$A,0)),"") -> Sow
A13: 4 | B13: NAT-4b | C13: =IFERROR(INDEX('Base Runes'!$D:$D,MATCH($B13,'Base Runes'!$A:$A,0)),"") -> Sow | D13: =IFERROR(INDEX('Base Runes'!$E:$E,MATCH($B13,'Base Runes'!$A:$A,0)),"") -> 🝃 | E13: plant it to act later | G13: =IFERROR(INDEX('Base Runes'!$G:$G,MATCH($B13,'Base Runes'!$A:$A,0)),"") -> Harvest
A14: 5 | B14: NAT-5a | C14: =IFERROR(INDEX('Base Runes'!$D:$D,MATCH($B14,'Base Runes'!$A:$A,0)),"") -> Tangle | D14: =IFERROR(INDEX('Base Runes'!$E:$E,MATCH($B14,'Base Runes'!$A:$A,0)),"") -> 🝄 | E14: vines bind | G14: =IFERROR(INDEX('Base Runes'!$G:$G,MATCH($B14,'Base Runes'!$A:$A,0)),"") -> Unravel
A15: 5 | B15: NAT-5b | C15: =IFERROR(INDEX('Base Runes'!$D:$D,MATCH($B15,'Base Runes'!$A:$A,0)),"") -> Unravel | D15: =IFERROR(INDEX('Base Runes'!$E:$E,MATCH($B15,'Base Runes'!$A:$A,0)),"") -> 🝅 | E15: free what is bound | G15: =IFERROR(INDEX('Base Runes'!$G:$G,MATCH($B15,'Base Runes'!$A:$A,0)),"") -> Tangle
A17: Blue: type here. Green: pulled from Base Runes (rename a rune or change its character there). Yellow: not written yet.

Sheet Light
A1: Light
A2: Rule: Straight and instant; reveals the hidden
A3: Status: First pass. Source: MODEL: the rule.
A5: Pair | B5: ID | C5: Rune | D5: Character | E5: As a skill (the verb a skill is built on) | F5: As a means (added to another skill) | G5: Opposite | H5: Together (rune + opposite release) | I5: Skills on it | J5: Notes
A6: 1 | B6: LGT-1a | C6: =IFERROR(INDEX('Base Runes'!$D:$D,MATCH($B6,'Base Runes'!$A:$A,0)),"") -> Shine | D6: =IFERROR(INDEX('Base Runes'!$E:$E,MATCH($B6,'Base Runes'!$A:$A,0)),"") -> 🝆 | E6: illuminate | G6: =IFERROR(INDEX('Base Runes'!$G:$G,MATCH($B6,'Base Runes'!$A:$A,0)),"") -> Dim
A7: 1 | B7: LGT-1b | C7: =IFERROR(INDEX('Base Runes'!$D:$D,MATCH($B7,'Base Runes'!$A:$A,0)),"") -> Dim | D7: =IFERROR(INDEX('Base Runes'!$E:$E,MATCH($B7,'Base Runes'!$A:$A,0)),"") -> 🝇 | E7: dull the light | G7: =IFERROR(INDEX('Base Runes'!$G:$G,MATCH($B7,'Base Runes'!$A:$A,0)),"") -> Shine
A8: 2 | B8: LGT-2a | C8: =IFERROR(INDEX('Base Runes'!$D:$D,MATCH($B8,'Base Runes'!$A:$A,0)),"") -> Flash | D8: =IFERROR(INDEX('Base Runes'!$E:$E,MATCH($B8,'Base Runes'!$A:$A,0)),"") -> 🝈 | E8: a sudden burst of light | G8: =IFERROR(INDEX('Base Runes'!$G:$G,MATCH($B8,'Base Runes'!$A:$A,0)),"") -> Glow
A9: 2 | B9: LGT-2b | C9: =IFERROR(INDEX('Base Runes'!$D:$D,MATCH($B9,'Base Runes'!$A:$A,0)),"") -> Glow | D9: =IFERROR(INDEX('Base Runes'!$E:$E,MATCH($B9,'Base Runes'!$A:$A,0)),"") -> 🝉 | E9: a steady soft light | G9: =IFERROR(INDEX('Base Runes'!$G:$G,MATCH($B9,'Base Runes'!$A:$A,0)),"") -> Flash
A10: 3 | B10: LGT-3a | C10: =IFERROR(INDEX('Base Runes'!$D:$D,MATCH($B10,'Base Runes'!$A:$A,0)),"") -> Radiate | D10: =IFERROR(INDEX('Base Runes'!$E:$E,MATCH($B10,'Base Runes'!$A:$A,0)),"") -> 🝊 | E10: send light and heat outward | G10: =IFERROR(INDEX('Base Runes'!$G:$G,MATCH($B10,'Base Runes'!$A:$A,0)),"") -> Absorb
A11: 3 | B11: LGT-3b | C11: =IFERROR(INDEX('Base Runes'!$D:$D,MATCH($B11,'Base Runes'!$A:$A,0)),"") -> Absorb | D11: =IFERROR(INDEX('Base Runes'!$E:$E,MATCH($B11,'Base Runes'!$A:$A,0)),"") -> 🝋 | E11: draw light and heat in | G11: =IFERROR(INDEX('Base Runes'!$G:$G,MATCH($B11,'Base Runes'!$A:$A,0)),"") -> Radiate
A12: 4 | B12: LGT-4a | C12: =IFERROR(INDEX('Base Runes'!$D:$D,MATCH($B12,'Base Runes'!$A:$A,0)),"") -> Glare | D12: =IFERROR(INDEX('Base Runes'!$E:$E,MATCH($B12,'Base Runes'!$A:$A,0)),"") -> 🝌 | E12: a blinding glare | G12: =IFERROR(INDEX('Base Runes'!$G:$G,MATCH($B12,'Base Runes'!$A:$A,0)),"") -> Clarity
A13: 4 | B13: LGT-4b | C13: =IFERROR(INDEX('Base Runes'!$D:$D,MATCH($B13,'Base Runes'!$A:$A,0)),"") -> Clarity | D13: =IFERROR(INDEX('Base Runes'!$E:$E,MATCH($B13,'Base Runes'!$A:$A,0)),"") -> 🝍 | E13: restore and sharpen sight | G13: =IFERROR(INDEX('Base Runes'!$G:$G,MATCH($B13,'Base Runes'!$A:$A,0)),"") -> Glare
A14: 5 | B14: LGT-5a | C14: =IFERROR(INDEX('Base Runes'!$D:$D,MATCH($B14,'Base Runes'!$A:$A,0)),"") -> Reflect | D14: =IFERROR(INDEX('Base Runes'!$E:$E,MATCH($B14,'Base Runes'!$A:$A,0)),"") -> 🝎 | E14: turn light, and shots, back | G14: =IFERROR(INDEX('Base Runes'!$G:$G,MATCH($B14,'Base Runes'!$A:$A,0)),"") -> Bend
A15: 5 | B15: LGT-5b | C15: =IFERROR(INDEX('Base Runes'!$D:$D,MATCH($B15,'Base Runes'!$A:$A,0)),"") -> Bend | D15: =IFERROR(INDEX('Base Runes'!$E:$E,MATCH($B15,'Base Runes'!$A:$A,0)),"") -> 🝏 | E15: bend light: false images, or nothing | G15: =IFERROR(INDEX('Base Runes'!$G:$G,MATCH($B15,'Base Runes'!$A:$A,0)),"") -> Reflect
A17: Blue: type here. Green: pulled from Base Runes (rename a rune or change its character there). Yellow: not written yet.

Sheet Dream
A1: Dream
A2: Rule: The mind
A3: It needs the target to see it or to sleep, and it grows stronger on the dazed and sleeping. Status: First pass. Source: C: dream is a named, valued affinity; MODEL: the rule.
A5: Pair | B5: ID | C5: Rune | D5: Character | E5: As a skill (the verb a skill is built on) | F5: As a means (added to another skill) | G5: Opposite | H5: Together (rune + opposite release) | I5: Skills on it | J5: Notes
A6: 1 | B6: DRM-1a | C6: =IFERROR(INDEX('Base Runes'!$D:$D,MATCH($B6,'Base Runes'!$A:$A,0)),"") -> Sleep | D6: =IFERROR(INDEX('Base Runes'!$E:$E,MATCH($B6,'Base Runes'!$A:$A,0)),"") -> 🝐 | E6: put to sleep | G6: =IFERROR(INDEX('Base Runes'!$G:$G,MATCH($B6,'Base Runes'!$A:$A,0)),"") -> Wake
A7: 1 | B7: DRM-1b | C7: =IFERROR(INDEX('Base Runes'!$D:$D,MATCH($B7,'Base Runes'!$A:$A,0)),"") -> Wake | D7: =IFERROR(INDEX('Base Runes'!$E:$E,MATCH($B7,'Base Runes'!$A:$A,0)),"") -> 🝑 | E7: rouse; break a trance | G7: =IFERROR(INDEX('Base Runes'!$G:$G,MATCH($B7,'Base Runes'!$A:$A,0)),"") -> Sleep
A8: 2 | B8: DRM-2a | C8: =IFERROR(INDEX('Base Runes'!$D:$D,MATCH($B8,'Base Runes'!$A:$A,0)),"") -> Conjure | D8: =IFERROR(INDEX('Base Runes'!$E:$E,MATCH($B8,'Base Runes'!$A:$A,0)),"") -> 🝒 | E8: an illusion | G8: =IFERROR(INDEX('Base Runes'!$G:$G,MATCH($B8,'Base Runes'!$A:$A,0)),"") -> Dispel
A9: 2 | B9: DRM-2b | C9: =IFERROR(INDEX('Base Runes'!$D:$D,MATCH($B9,'Base Runes'!$A:$A,0)),"") -> Dispel | D9: =IFERROR(INDEX('Base Runes'!$E:$E,MATCH($B9,'Base Runes'!$A:$A,0)),"") -> 🝓 | E9: break illusions | G9: =IFERROR(INDEX('Base Runes'!$G:$G,MATCH($B9,'Base Runes'!$A:$A,0)),"") -> Conjure
A10: 3 | B10: DRM-3a | C10: =IFERROR(INDEX('Base Runes'!$D:$D,MATCH($B10,'Base Runes'!$A:$A,0)),"") -> Dread | D10: =IFERROR(INDEX('Base Runes'!$E:$E,MATCH($B10,'Base Runes'!$A:$A,0)),"") -> 🝔 | E10: terror | G10: =IFERROR(INDEX('Base Runes'!$G:$G,MATCH($B10,'Base Runes'!$A:$A,0)),"") -> Soothe
A11: 3 | B11: DRM-3b | C11: =IFERROR(INDEX('Base Runes'!$D:$D,MATCH($B11,'Base Runes'!$A:$A,0)),"") -> Soothe | D11: =IFERROR(INDEX('Base Runes'!$E:$E,MATCH($B11,'Base Runes'!$A:$A,0)),"") -> 🝕 | E11: calm, bliss | G11: =IFERROR(INDEX('Base Runes'!$G:$G,MATCH($B11,'Base Runes'!$A:$A,0)),"") -> Dread
A12: 4 | B12: DRM-4a | C12: =IFERROR(INDEX('Base Runes'!$D:$D,MATCH($B12,'Base Runes'!$A:$A,0)),"") -> Mimic | D12: =IFERROR(INDEX('Base Runes'!$E:$E,MATCH($B12,'Base Runes'!$A:$A,0)),"") -> 🝖 | E12: take another's look or voice | G12: =IFERROR(INDEX('Base Runes'!$G:$G,MATCH($B12,'Base Runes'!$A:$A,0)),"") -> Unmask
A13: 4 | B13: DRM-4b | C13: =IFERROR(INDEX('Base Runes'!$D:$D,MATCH($B13,'Base Runes'!$A:$A,0)),"") -> Unmask | D13: =IFERROR(INDEX('Base Runes'!$E:$E,MATCH($B13,'Base Runes'!$A:$A,0)),"") -> 🝗 | E13: reveal a disguise | G13: =IFERROR(INDEX('Base Runes'!$G:$G,MATCH($B13,'Base Runes'!$A:$A,0)),"") -> Mimic
A14: 5 | B14: DRM-5a | C14: =IFERROR(INDEX('Base Runes'!$D:$D,MATCH($B14,'Base Runes'!$A:$A,0)),"") -> Whisper | D14: =IFERROR(INDEX('Base Runes'!$E:$E,MATCH($B14,'Base Runes'!$A:$A,0)),"") -> 🝘 | E14: plant a command | G14: =IFERROR(INDEX('Base Runes'!$G:$G,MATCH($B14,'Base Runes'!$A:$A,0)),"") -> Shut
A15: 5 | B15: DRM-5b | C15: =IFERROR(INDEX('Base Runes'!$D:$D,MATCH($B15,'Base Runes'!$A:$A,0)),"") -> Shut | D15: =IFERROR(INDEX('Base Runes'!$E:$E,MATCH($B15,'Base Runes'!$A:$A,0)),"") -> 🝙 | E15: close the mind to others | G15: =IFERROR(INDEX('Base Runes'!$G:$G,MATCH($B15,'Base Runes'!$A:$A,0)),"") -> Whisper
A17: Blue: type here. Green: pulled from Base Runes (rename a rune or change its character there). Yellow: not written yet.

Sheet Poison
A1: Poison
A2: Rule: Doses stack inside a body and come due later
A3: Status: First pass. Source: MODEL: the rule.
A5: Pair | B5: ID | C5: Rune | D5: Character | E5: As a skill (the verb a skill is built on) | F5: As a means (added to another skill) | G5: Opposite | H5: Together (rune + opposite release) | I5: Skills on it | J5: Notes
A6: 1 | B6: POI-1a | C6: =IFERROR(INDEX('Base Runes'!$D:$D,MATCH($B6,'Base Runes'!$A:$A,0)),"") -> Poison | D6: =IFERROR(INDEX('Base Runes'!$E:$E,MATCH($B6,'Base Runes'!$A:$A,0)),"") -> 🝚 | E6: dose a target | G6: =IFERROR(INDEX('Base Runes'!$G:$G,MATCH($B6,'Base Runes'!$A:$A,0)),"") -> Purge
A7: 1 | B7: POI-1b | C7: =IFERROR(INDEX('Base Runes'!$D:$D,MATCH($B7,'Base Runes'!$A:$A,0)),"") -> Purge | D7: =IFERROR(INDEX('Base Runes'!$E:$E,MATCH($B7,'Base Runes'!$A:$A,0)),"") -> 🝛 | E7: clear doses | G7: =IFERROR(INDEX('Base Runes'!$G:$G,MATCH($B7,'Base Runes'!$A:$A,0)),"") -> Poison
A8: 2 | B8: POI-2a | C8: =IFERROR(INDEX('Base Runes'!$D:$D,MATCH($B8,'Base Runes'!$A:$A,0)),"") -> Contaminate | D8: =IFERROR(INDEX('Base Runes'!$E:$E,MATCH($B8,'Base Runes'!$A:$A,0)),"") -> 🝜 | E8: foul an area or a thing | G8: =IFERROR(INDEX('Base Runes'!$G:$G,MATCH($B8,'Base Runes'!$A:$A,0)),"") -> Cleanse
A9: 2 | B9: POI-2b | C9: =IFERROR(INDEX('Base Runes'!$D:$D,MATCH($B9,'Base Runes'!$A:$A,0)),"") -> Cleanse | D9: =IFERROR(INDEX('Base Runes'!$E:$E,MATCH($B9,'Base Runes'!$A:$A,0)),"") -> 🝝 | E9: make it clean again | G9: =IFERROR(INDEX('Base Runes'!$G:$G,MATCH($B9,'Base Runes'!$A:$A,0)),"") -> Contaminate
A10: 3 | B10: POI-3a | C10: =IFERROR(INDEX('Base Runes'!$D:$D,MATCH($B10,'Base Runes'!$A:$A,0)),"") -> Corrode | D10: =IFERROR(INDEX('Base Runes'!$E:$E,MATCH($B10,'Base Runes'!$A:$A,0)),"") -> 🝞 | E10: acid that eats armour and metal | G10: =IFERROR(INDEX('Base Runes'!$G:$G,MATCH($B10,'Base Runes'!$A:$A,0)),"") -> Neutralise
A11: 3 | B11: POI-3b | C11: =IFERROR(INDEX('Base Runes'!$D:$D,MATCH($B11,'Base Runes'!$A:$A,0)),"") -> Neutralise | D11: =IFERROR(INDEX('Base Runes'!$E:$E,MATCH($B11,'Base Runes'!$A:$A,0)),"") -> 🝟 | E11: render a poison or acid harmless | G11: =IFERROR(INDEX('Base Runes'!$G:$G,MATCH($B11,'Base Runes'!$A:$A,0)),"") -> Corrode
A12: 4 | B12: POI-4a | C12: =IFERROR(INDEX('Base Runes'!$D:$D,MATCH($B12,'Base Runes'!$A:$A,0)),"") -> Linger | D12: =IFERROR(INDEX('Base Runes'!$E:$E,MATCH($B12,'Base Runes'!$A:$A,0)),"") -> 🝠 | E12: leave residue that stays | G12: =IFERROR(INDEX('Base Runes'!$G:$G,MATCH($B12,'Base Runes'!$A:$A,0)),"") -> Flush
A13: 4 | B13: POI-4b | C13: =IFERROR(INDEX('Base Runes'!$D:$D,MATCH($B13,'Base Runes'!$A:$A,0)),"") -> Flush | D13: =IFERROR(INDEX('Base Runes'!$E:$E,MATCH($B13,'Base Runes'!$A:$A,0)),"") -> 🝡 | E13: clean an area out | G13: =IFERROR(INDEX('Base Runes'!$G:$G,MATCH($B13,'Base Runes'!$A:$A,0)),"") -> Linger
A14: 5 | B14: POI-5a | C14: =IFERROR(INDEX('Base Runes'!$D:$D,MATCH($B14,'Base Runes'!$A:$A,0)),"") -> Sap | D14: =IFERROR(INDEX('Base Runes'!$E:$E,MATCH($B14,'Base Runes'!$A:$A,0)),"") -> 🝢 | E14: weaken | G14: =IFERROR(INDEX('Base Runes'!$G:$G,MATCH($B14,'Base Runes'!$A:$A,0)),"") -> Stimulate
A15: 5 | B15: POI-5b | C15: =IFERROR(INDEX('Base Runes'!$D:$D,MATCH($B15,'Base Runes'!$A:$A,0)),"") -> Stimulate | D15: =IFERROR(INDEX('Base Runes'!$E:$E,MATCH($B15,'Base Runes'!$A:$A,0)),"") -> 🝣 | E15: strengthen (poison as a drug) | G15: =IFERROR(INDEX('Base Runes'!$G:$G,MATCH($B15,'Base Runes'!$A:$A,0)),"") -> Sap
A17: Blue: type here. Green: pulled from Base Runes (rename a rune or change its character there). Yellow: not written yet.

Sheet Disease
A1: Disease
A2: Rule: A cloud that only harms flesh
A3: Armour, stone and constructs ignore it; it lingers and drifts. Status: First pass. Source: B 2026-10-21: renamed from Miasma; C: miasma is flesh-only and armour counters it; MODEL: the rest.
A5: Pair | B5: ID | C5: Rune | D5: Character | E5: As a skill (the verb a skill is built on) | F5: As a means (added to another skill) | G5: Opposite | H5: Together (rune + opposite release) | I5: Skills on it | J5: Notes
A6: 1 | B6: DIS-1a | C6: =IFERROR(INDEX('Base Runes'!$D:$D,MATCH($B6,'Base Runes'!$A:$A,0)),"") -> Infect | D6: =IFERROR(INDEX('Base Runes'!$E:$E,MATCH($B6,'Base Runes'!$A:$A,0)),"") -> 🝤 | E6: give a disease | G6: =IFERROR(INDEX('Base Runes'!$G:$G,MATCH($B6,'Base Runes'!$A:$A,0)),"") -> Disinfect
A7: 1 | B7: DIS-1b | C7: =IFERROR(INDEX('Base Runes'!$D:$D,MATCH($B7,'Base Runes'!$A:$A,0)),"") -> Disinfect | D7: =IFERROR(INDEX('Base Runes'!$E:$E,MATCH($B7,'Base Runes'!$A:$A,0)),"") -> 🝥 | E7: kill it | G7: =IFERROR(INDEX('Base Runes'!$G:$G,MATCH($B7,'Base Runes'!$A:$A,0)),"") -> Infect
A8: 2 | B8: DIS-2a | C8: =IFERROR(INDEX('Base Runes'!$D:$D,MATCH($B8,'Base Runes'!$A:$A,0)),"") -> Spread | D8: =IFERROR(INDEX('Base Runes'!$E:$E,MATCH($B8,'Base Runes'!$A:$A,0)),"") -> 🝦 | E8: it jumps body to body | G8: =IFERROR(INDEX('Base Runes'!$G:$G,MATCH($B8,'Base Runes'!$A:$A,0)),"") -> Contain
A9: 2 | B9: DIS-2b | C9: =IFERROR(INDEX('Base Runes'!$D:$D,MATCH($B9,'Base Runes'!$A:$A,0)),"") -> Contain | D9: =IFERROR(INDEX('Base Runes'!$E:$E,MATCH($B9,'Base Runes'!$A:$A,0)),"") -> 🝧 | E9: it stays in one body | G9: =IFERROR(INDEX('Base Runes'!$G:$G,MATCH($B9,'Base Runes'!$A:$A,0)),"") -> Spread
A10: 3 | B10: DIS-3a | C10: =IFERROR(INDEX('Base Runes'!$D:$D,MATCH($B10,'Base Runes'!$A:$A,0)),"") -> Fester | D10: =IFERROR(INDEX('Base Runes'!$E:$E,MATCH($B10,'Base Runes'!$A:$A,0)),"") -> 🝨 | E10: wounds rot | G10: =IFERROR(INDEX('Base Runes'!$G:$G,MATCH($B10,'Base Runes'!$A:$A,0)),"") -> Lance
A11: 3 | B11: DIS-3b | C11: =IFERROR(INDEX('Base Runes'!$D:$D,MATCH($B11,'Base Runes'!$A:$A,0)),"") -> Lance | D11: =IFERROR(INDEX('Base Runes'!$E:$E,MATCH($B11,'Base Runes'!$A:$A,0)),"") -> 🝩 | E11: open and drain a festering wound | G11: =IFERROR(INDEX('Base Runes'!$G:$G,MATCH($B11,'Base Runes'!$A:$A,0)),"") -> Fester
A12: 4 | B12: DIS-4a | C12: =IFERROR(INDEX('Base Runes'!$D:$D,MATCH($B12,'Base Runes'!$A:$A,0)),"") -> Billow | D12: =IFERROR(INDEX('Base Runes'!$E:$E,MATCH($B12,'Base Runes'!$A:$A,0)),"") -> 🝪 | E12: spread the cloud | G12: =IFERROR(INDEX('Base Runes'!$G:$G,MATCH($B12,'Base Runes'!$A:$A,0)),"") -> Clear
A13: 4 | B13: DIS-4b | C13: =IFERROR(INDEX('Base Runes'!$D:$D,MATCH($B13,'Base Runes'!$A:$A,0)),"") -> Clear | D13: =IFERROR(INDEX('Base Runes'!$E:$E,MATCH($B13,'Base Runes'!$A:$A,0)),"") -> 🝫 | E13: disperse it | G13: =IFERROR(INDEX('Base Runes'!$G:$G,MATCH($B13,'Base Runes'!$A:$A,0)),"") -> Billow
A14: 5 | B14: DIS-5a | C14: =IFERROR(INDEX('Base Runes'!$D:$D,MATCH($B14,'Base Runes'!$A:$A,0)),"") -> Overrun | D14: =IFERROR(INDEX('Base Runes'!$E:$E,MATCH($B14,'Base Runes'!$A:$A,0)),"") -> 🝬 | E14: overwhelm the body's defences | G14: =IFERROR(INDEX('Base Runes'!$G:$G,MATCH($B14,'Base Runes'!$A:$A,0)),"") -> Immunise
A15: 5 | B15: DIS-5b | C15: =IFERROR(INDEX('Base Runes'!$D:$D,MATCH($B15,'Base Runes'!$A:$A,0)),"") -> Immunise | D15: =IFERROR(INDEX('Base Runes'!$E:$E,MATCH($B15,'Base Runes'!$A:$A,0)),"") -> 🝭 | E15: build resistance | G15: =IFERROR(INDEX('Base Runes'!$G:$G,MATCH($B15,'Base Runes'!$A:$A,0)),"") -> Overrun
A17: Blue: type here. Green: pulled from Base Runes (rename a rune or change its character there). Yellow: not written yet.

Sheet Slider Links
A1: Affinity | B1: Heat (slider, 0-20) | C1: Substance (slider, 0-20) | D1: Vitality (slider, 0-20) | E1: Light (slider, 0-20) | F1: Mind/Matter (slider, 0-20) | G1: Heat (-1 to +1) | H1: Substance (-1 to +1) | I1: Vitality (-1 to +1) | J1: Light (-1 to +1) | K1: Mind/Matter (-1 to +1)
A2: =Affinities!$A$2 -> Water | B2: 7 | C2: 4 | D2: 15 | E2: 10 | F2: 16 | G2: =(B2-10)/10 -> -0.3 | H2: =(C2-10)/10 -> -0.6 | I2: =(D2-10)/10 -> 0.5 | J2: =(E2-10)/10 -> 0 | K2: =(F2-10)/10 -> 0.6
A3: =Affinities!$A$3 -> Fire | B3: 20 | C3: 7 | D3: 10 | E3: 16 | F3: 10 | G3: =(B3-10)/10 -> 1 | H3: =(C3-10)/10 -> -0.3 | I3: =(D3-10)/10 -> 0 | J3: =(E3-10)/10 -> 0.6 | K3: =(F3-10)/10 -> 0
A4: =Affinities!$A$4 -> Earth | B4: 10 | C4: 20 | D4: 12 | E4: 8 | F4: 20 | G4: =(B4-10)/10 -> 0 | H4: =(C4-10)/10 -> 1 | I4: =(D4-10)/10 -> 0.2 | J4: =(E4-10)/10 -> -0.2 | K4: =(F4-10)/10 -> 1
A5: =Affinities!$A$5 -> Wind | B5: 10 | C5: 2 | D5: 12 | E5: 10 | F5: 14 | G5: =(B5-10)/10 -> 0 | H5: =(C5-10)/10 -> -0.8 | I5: =(D5-10)/10 -> 0.2 | J5: =(E5-10)/10 -> 0 | K5: =(F5-10)/10 -> 0.4
A6: =Affinities!$A$6 -> Lightning | B6: 16 | C6: 5 | D6: 10 | E6: 17 | F6: 9 | G6: =(B6-10)/10 -> 0.6 | H6: =(C6-10)/10 -> -0.5 | I6: =(D6-10)/10 -> 0 | J6: =(E6-10)/10 -> 0.7 | K6: =(F6-10)/10 -> -0.1
A7: =Affinities!$A$7 -> Ice | B7: 0 | C7: 15 | D7: 7 | E7: 11 | F7: 12 | G7: =(B7-10)/10 -> -1 | H7: =(C7-10)/10 -> 0.5 | I7: =(D7-10)/10 -> -0.3 | J7: =(E7-10)/10 -> 0.1 | K7: =(F7-10)/10 -> 0.2
A8: =Affinities!$A$8 -> Dark | B8: 7 | C8: 7 | D8: 8 | E8: 0 | F8: 6 | G8: =(B8-10)/10 -> -0.3 | H8: =(C8-10)/10 -> -0.3 | I8: =(D8-10)/10 -> -0.2 | J8: =(E8-10)/10 -> -1 | K8: =(F8-10)/10 -> -0.4
A9: =Affinities!$A$9 -> Metal | B9: 10 | C9: 18 | D9: 7 | E9: 12 | F9: 20 | G9: =(B9-10)/10 -> 0 | H9: =(C9-10)/10 -> 0.8 | I9: =(D9-10)/10 -> -0.3 | J9: =(E9-10)/10 -> 0.2 | K9: =(F9-10)/10 -> 1
A10: =Affinities!$A$10 -> Blood | B10: 13 | C10: 5 | D10: 16 | E10: 8 | F10: 18 | G10: =(B10-10)/10 -> 0.3 | H10: =(C10-10)/10 -> -0.5 | I10: =(D10-10)/10 -> 0.6 | J10: =(E10-10)/10 -> -0.2 | K10: =(F10-10)/10 -> 0.8
A11: =Affinities!$A$11 -> Life | B11: 13 | C11: 10 | D11: 20 | E11: 12 | F11: 14 | G11: =(B11-10)/10 -> 0.3 | H11: =(C11-10)/10 -> 0 | I11: =(D11-10)/10 -> 1 | J11: =(E11-10)/10 -> 0.2 | K11: =(F11-10)/10 -> 0.4
A12: =Affinities!$A$12 -> Death | B12: 5 | C12: 12 | D12: 0 | E12: 6 | F12: 10 | G12: =(B12-10)/10 -> -0.5 | H12: =(C12-10)/10 -> 0.2 | I12: =(D12-10)/10 -> -1 | J12: =(E12-10)/10 -> -0.4 | K12: =(F12-10)/10 -> 0
A13: =Affinities!$A$13 -> Nature | B13: 10 | C13: 12 | D13: 20 | E13: 11 | F13: 15 | G13: =(B13-10)/10 -> 0 | H13: =(C13-10)/10 -> 0.2 | I13: =(D13-10)/10 -> 1 | J13: =(E13-10)/10 -> 0.1 | K13: =(F13-10)/10 -> 0.5
A14: =Affinities!$A$14 -> Light | B14: 14 | C14: 6 | D14: 13 | E14: 20 | F14: 10 | G14: =(B14-10)/10 -> 0.4 | H14: =(C14-10)/10 -> -0.4 | I14: =(D14-10)/10 -> 0.3 | J14: =(E14-10)/10 -> 1 | K14: =(F14-10)/10 -> 0
A15: =Affinities!$A$15 -> Dream | B15: 10 | C15: 4 | D15: 10 | E15: 4 | F15: 0 | G15: =(B15-10)/10 -> 0 | H15: =(C15-10)/10 -> -0.6 | I15: =(D15-10)/10 -> 0 | J15: =(E15-10)/10 -> -0.6 | K15: =(F15-10)/10 -> -1
A16: =Affinities!$A$16 -> Poison | B16: 10 | C16: 7 | D16: 2 | E16: 4 | F16: 14 | G16: =(B16-10)/10 -> 0 | H16: =(C16-10)/10 -> -0.3 | I16: =(D16-10)/10 -> -0.8 | J16: =(E16-10)/10 -> -0.6 | K16: =(F16-10)/10 -> 0.4
A17: =Affinities!$A$17 -> Disease | B17: 12 | C17: 5 | D17: 0 | E17: 7 | F17: 13 | G17: =(B17-10)/10 -> 0.2 | H17: =(C17-10)/10 -> -0.5 | I17: =(D17-10)/10 -> -1 | J17: =(E17-10)/10 -> -0.3 | K17: =(F17-10)/10 -> 0.3
A19: The sliders on the Affinities sheet write the 0-20 numbers in columns B-F; columns G-K turn them into positions from -1 to +1. You can also type 0-20 here directly.
